Workbook
Name a_coupon: Inputs!$B$15
Name a_notional: Inputs!$B$14
Name b_coupon: Inputs!$B$17
Name b_notional: Inputs!$B$16
Name case_number: Case!$B$2
Name coupon: Inputs!$B$10
Name face: Inputs!$B$9
Name lgd: Inputs!$B$12
Name Number_of_Cases: Inputs!$B$21
Name pd_annual: Inputs!$B$11
Name rho: Inputs!$B$13

Sheet Inputs
A1: Miniproject 3 (Part 1) - Simplified CDO analysis
A2: FRE 6103 Valuation for Financial Engineering (NYU Tandon) | Raj Pawar (rsp9234) and Michael Brick (mb11311)
A3: Yellow cells are inputs; everything else in the workbook is a formula. All amounts are in $ millions. The case to display is chosen on the Case sheet.
A5: Parameter | B5: Value | C5: Note
A6: Number of bonds | B6: 10 | C6: Fixed by the layout of the sheets (10 columns per block).
A7: Years to maturity | B7: 5 | C7: Fixed by the layout (20 quarterly columns).
A8: Payments per year | B8: 4 | C8: Quarterly.
A9: Face value per bond ($MM) | B9: 10 | C9: Given.
A10: Coupon rate, annual | B10: 0.06 | C10: Given. Paid quarterly: coupon / 4 x face.
A11: Default probability, annual (pi) | B11: 0.04 | C11: Given. Default time in years t = ln(1 - u) / ln(1 - pi).
A12: Loss given default (lambda) | B12: 0.6 | C12: Given. BIS model: 1 - LGD of every promised payment is always paid.
A13: Correlation between default dates | B13: 0.2 | C13: Given. Applied to the normals through the Cholesky factor.
A14: Class A notional ($MM) | B14: 20 | C14: Given.
A15: Class A coupon, annual | B15: 0.02 | C15: Given. Paid quarterly, principal at maturity.
A16: Class B notional ($MM) | B16: 10 | C16: Given.
A17: Class B coupon, annual | B17: 0.04 | C17: Given. Paid quarterly, principal at maturity.
... A19: Risk-free rate | B19: 0.01 | C19: Given. Not used until Part 2.
A20: Seed of the fixed random numbers | B20: 6103
A21: Number of cases | B21: =COUNT(Random!$A$18:$A$1017) -> 1000 | C21: Given. Counted from the Random sheet: the layout has one row per case, so this is not an input.
A23: Promised cash flows ($MM)
A24: Quarter | B24: One bond | C24: Pool (10 bonds) | D24: Due to Class A | E24: Due to Class B
A25: 1 | B25: =face*coupon/4+IF(A25=20,face,0) -> 0.15 | C25: =10*B25 -> 1.5 | D25: =a_notional*a_coupon/4+IF(A25=20,a_notional,0) -> 0.1 | E25: =b_notional*b_coupon/4+IF(A25=20,b_notional,0) -> 0.1
A26: 2 | B26: =face*coupon/4+IF(A26=20,face,0) -> 0.15 | C26: =10*B26 -> 1.5 | D26: =a_notional*a_coupon/4+IF(A26=20,a_notional,0) -> 0.1 | E26: =b_notional*b_coupon/4+IF(A26=20,b_notional,0) -> 0.1
A27: 3 | B27: =face*coupon/4+IF(A27=20,face,0) -> 0.15 | C27: =10*B27 -> 1.5 | D27: =a_notional*a_coupon/4+IF(A27=20,a_notional,0) -> 0.1 | E27: =b_notional*b_coupon/4+IF(A27=20,b_notional,0) -> 0.1
A28: 4 | B28: =face*coupon/4+IF(A28=20,face,0) -> 0.15 | C28: =10*B28 -> 1.5 | D28: =a_notional*a_coupon/4+IF(A28=20,a_notional,0) -> 0.1 | E28: =b_notional*b_coupon/4+IF(A28=20,b_notional,0) -> 0.1
A29: 5 | B29: =face*coupon/4+IF(A29=20,face,0) -> 0.15 | C29: =10*B29 -> 1.5 | D29: =a_notional*a_coupon/4+IF(A29=20,a_notional,0) -> 0.1 | E29: =b_notional*b_coupon/4+IF(A29=20,b_notional,0) -> 0.1
A30: 6 | B30: =face*coupon/4+IF(A30=20,face,0) -> 0.15 | C30: =10*B30 -> 1.5 | D30: =a_notional*a_coupon/4+IF(A30=20,a_notional,0) -> 0.1 | E30: =b_notional*b_coupon/4+IF(A30=20,b_notional,0) -> 0.1
A31: 7 | B31: =face*coupon/4+IF(A31=20,face,0) -> 0.15 | C31: =10*B31 -> 1.5 | D31: =a_notional*a_coupon/4+IF(A31=20,a_notional,0) -> 0.1 | E31: =b_notional*b_coupon/4+IF(A31=20,b_notional,0) -> 0.1
A32: 8 | B32: =face*coupon/4+IF(A32=20,face,0) -> 0.15 | C32: =10*B32 -> 1.5 | D32: =a_notional*a_coupon/4+IF(A32=20,a_notional,0) -> 0.1 | E32: =b_notional*b_coupon/4+IF(A32=20,b_notional,0) -> 0.1
A33: 9 | B33: =face*coupon/4+IF(A33=20,face,0) -> 0.15 | C33: =10*B33 -> 1.5 | D33: =a_notional*a_coupon/4+IF(A33=20,a_notional,0) -> 0.1 | E33: =b_notional*b_coupon/4+IF(A33=20,b_notional,0) -> 0.1
A34: 10 | B34: =face*coupon/4+IF(A34=20,face,0) -> 0.15 | C34: =10*B34 -> 1.5 | D34: =a_notional*a_coupon/4+IF(A34=20,a_notional,0) -> 0.1 | E34: =b_notional*b_coupon/4+IF(A34=20,b_notional,0) -> 0.1
A35: 11 | B35: =face*coupon/4+IF(A35=20,face,0) -> 0.15 | C35: =10*B35 -> 1.5 | D35: =a_notional*a_coupon/4+IF(A35=20,a_notional,0) -> 0.1 | E35: =b_notional*b_coupon/4+IF(A35=20,b_notional,0) -> 0.1
A36: 12 | B36: =face*coupon/4+IF(A36=20,face,0) -> 0.15 | C36: =10*B36 -> 1.5 | D36: =a_notional*a_coupon/4+IF(A36=20,a_notional,0) -> 0.1 | E36: =b_notional*b_coupon/4+IF(A36=20,b_notional,0) -> 0.1
... A44: 20 | B44: =face*coupon/4+IF(A44=20,face,0) -> 10.15 | C44: =10*B44 -> 101.5 | D44: =a_notional*a_coupon/4+IF(A44=20,a_notional,0) -> 20.1 | E44: =b_notional*b_coupon/4+IF(A44=20,b_notional,0) -> 10.1
A45: Total | B45: =SUM(B25:B44) -> 13 | C45: =SUM(C25:C44) -> 130 | D45: =SUM(D25:D44) -> 22 | E45: =SUM(E25:E44) -> 12

Sheet Case
A1: Case viewer
A2: Case to display (1 to 1000) | B2: 5 | C2: Type any case number in the yellow cell. Everything on this sheet follows it.
A5: Bond | B5: Random normal z | C5: Moment-matched z | D5: Correlated normal x | E5: Uniform u | F5: Default time (years) | G5: Default quarter (21 = none) | H5: Status | I5: Total cash received ($MM)
A6: Bond 1 | B6: =INDEX(Random!$B$18:$K$1017,case_number,1) -> -1.8599871 | C6: =INDEX(Random!$X$18:$AG$1017,case_number,1) -> -1.8690173 | D6: =INDEX(Defaults!$B$18:$K$1017,case_number,1) -> -1.8690173 | E6: =INDEX(Defaults!$M$18:$V$1017,case_number,1) -> 0.030810203 | F6: =INDEX(Defaults!$X$18:$AG$1017,case_number,1) -> 0.76661658 | G6: =INDEX(Defaults!$AI$18:$AR$1017,case_number,1) -> 4 | H6: =IF(G6<=20,"defaults in quarter "&G6,"survives") -> defaults in quarter 4 | I6: =SUM(B20:B39) -> 5.47
A7: Bond 2 | B7: =INDEX(Random!$B$18:$K$1017,case_number,2) -> 0.75061757 | C7: =INDEX(Random!$X$18:$AG$1017,case_number,2) -> 0.73225356 | D7: =INDEX(Defaults!$B$18:$K$1017,case_number,2) -> 0.34365558 | E7: =INDEX(Defaults!$M$18:$V$1017,case_number,2) -> 0.63444734 | F7: =INDEX(Defaults!$X$18:$AG$1017,case_number,2) -> 24.652027 | G7: =INDEX(Defaults!$AI$18:$AR$1017,case_number,2) -> 21 | H7: =IF(G7<=20,"defaults in quarter "&G7,"survives") -> survives | I7: =SUM(C20:C39) -> 13
A8: Bond 3 | B8: =INDEX(Random!$B$18:$K$1017,case_number,3) -> 0.2224588 | C8: =INDEX(Random!$X$18:$AG$1017,case_number,3) -> 0.18387329 | D8: =INDEX(Defaults!$B$18:$K$1017,case_number,3) -> -0.076588476 | E8: =INDEX(Defaults!$M$18:$V$1017,case_number,3) -> 0.46947546 | F8: =INDEX(Defaults!$X$18:$AG$1017,case_number,3) -> 15.528126 | G8: =INDEX(Defaults!$AI$18:$AR$1017,case_number,3) -> 21 | H8: =IF(G8<=20,"defaults in quarter "&G8,"survives") -> survives | I8: =SUM(D20:D39) -> 13
A9: Bond 4 | B9: =INDEX(Random!$B$18:$K$1017,case_number,4) -> -0.78341897 | C9: =INDEX(Random!$X$18:$AG$1017,case_number,4) -> -0.72151866 | D9: =INDEX(Defaults!$B$18:$K$1017,case_number,4) -> -0.91875382 | E9: =INDEX(Defaults!$M$18:$V$1017,case_number,4) -> 0.17911217 | F9: =INDEX(Defaults!$X$18:$AG$1017,case_number,4) -> 4.8348645 | G9: =INDEX(Defaults!$AI$18:$AR$1017,case_number,4) -> 20 | H9: =IF(G9<=20,"defaults in quarter "&G9,"survives") -> defaults in quarter 20 | I9: =SUM(E20:E39) -> 6.91
A10: Bond 5 | B10: =INDEX(Random!$B$18:$K$1017,case_number,5) -> -1.5263177 | C10: =INDEX(Random!$X$18:$AG$1017,case_number,5) -> -1.4417872 | D10: =INDEX(Defaults!$B$18:$K$1017,case_number,5) -> -1.6828875 | E10: =INDEX(Defaults!$M$18:$V$1017,case_number,5) -> 0.046198439 | F10: =INDEX(Defaults!$X$18:$AG$1017,case_number,5) -> 1.1586802 | G10: =INDEX(Defaults!$AI$18:$AR$1017,case_number,5) -> 5 | H10: =IF(G10<=20,"defaults in quarter "&G10,"survives") -> defaults in quarter 5 | I10: =SUM(F20:F39) -> 5.56
A11: Bond 6 | B11: =INDEX(Random!$B$18:$K$1017,case_number,6) -> -0.78531154 | C11: =INDEX(Random!$X$18:$AG$1017,case_number,6) -> -0.74971084 | D11: =INDEX(Defaults!$B$18:$K$1017,case_number,6) -> -1.1738999 | E11: =INDEX(Defaults!$M$18:$V$1017,case_number,6) -> 0.12021756 | F11: =INDEX(Defaults!$X$18:$AG$1017,case_number,6) -> 3.1375398 | G11: =INDEX(Defaults!$AI$18:$AR$1017,case_number,6) -> 13 | H11: =IF(G11<=20,"defaults in quarter "&G11,"survives") -> defaults in quarter 13 | I11: =SUM(G20:G39) -> 6.28
A12: Bond 7 | B12: =INDEX(Random!$B$18:$K$1017,case_number,7) -> -0.83463465 | C12: =INDEX(Random!$X$18:$AG$1017,case_number,7) -> -0.73423477 | D12: =INDEX(Defaults!$B$18:$K$1017,case_number,7) -> -1.2265224 | E12: =INDEX(Defaults!$M$18:$V$1017,case_number,7) -> 0.11000107 | F12: =INDEX(Defaults!$X$18:$AG$1017,case_number,7) -> 2.8547117 | G12: =INDEX(Defaults!$AI$18:$AR$1017,case_number,7) -> 12 | H12: =IF(G12<=20,"defaults in quarter "&G12,"survives") -> defaults in quarter 12 | I12: =SUM(H20:H39) -> 6.19
A13: Bond 8 | B13: =INDEX(Random!$B$18:$K$1017,case_number,8) -> -0.079703706 | C13: =INDEX(Random!$X$18:$AG$1017,case_number,8) -> -0.10079161 | D13: =INDEX(Defaults!$B$18:$K$1017,case_number,8) -> -0.69452428 | E13: =INDEX(Defaults!$M$18:$V$1017,case_number,8) -> 0.24367674 | F13: =INDEX(Defaults!$X$18:$AG$1017,case_number,8) -> 6.8415667 | G13: =INDEX(Defaults!$AI$18:$AR$1017,case_number,8) -> 21 | H13: =IF(G13<=20,"defaults in quarter "&G13,"survives") -> survives | I13: =SUM(I20:I39) -> 13
A14: Bond 9 | B14: =INDEX(Random!$B$18:$K$1017,case_number,9) -> -0.83237702 | C14: =INDEX(Random!$X$18:$AG$1017,case_number,9) -> -0.95491939 | D14: =INDEX(Defaults!$B$18:$K$1017,case_number,9) -> -1.4971931 | E14: =INDEX(Defaults!$M$18:$V$1017,case_number,9) -> 0.067171513 | F14: =INDEX(Defaults!$X$18:$AG$1017,case_number,9) -> 1.7033446 | G14: =INDEX(Defaults!$AI$18:$AR$1017,case_number,9) -> 7 | H14: =IF(G14<=20,"defaults in quarter "&G14,"survives") -> defaults in quarter 7 | I14: =SUM(J20:J39) -> 5.74
A15: Bond 10 | B15: =INDEX(Random!$B$18:$K$1017,case_number,10) -> 0.28584576 | C15: =INDEX(Random!$X$18:$AG$1017,case_number,10) -> 0.25074514 | D15: =INDEX(Defaults!$B$18:$K$1017,case_number,10) -> -0.44385533 | E15: =INDEX(Defaults!$M$18:$V$1017,case_number,10) -> 0.32857359 | F15: =INDEX(Defaults!$X$18:$AG$1017,case_number,10) -> 9.758241 | G15: =INDEX(Defaults!$AI$18:$AR$1017,case_number,10) -> 21 | H15: =IF(G15<=20,"defaults in quarter "&G15,"survives") -> survives | I15: =SUM(K20:K39) -> 13
A16: Bonds defaulting within 5 years | G16: =COUNTIF(G6:G15,"<=20") -> 6
A19: Quarter | B19: Bond 1 | C19: Bond 2 | D19: Bond 3 | E19: Bond 4 | F19: Bond 5 | G19: Bond 6 | H19: Bond 7 | I19: Bond 8 | J19: Bond 9 | K19: Bond 10 | L19: Pool | M19: Class A | N19: Class B | O19: Equity | P19: Pool promised
A20: 1 | B20: =Inputs!$B$25*IF($A20>=$G$6,1-lgd,1) -> 0.15 | C20: =Inputs!$B$25*IF($A20>=$G$7,1-lgd,1) -> 0.15 | D20: =Inputs!$B$25*IF($A20>=$G$8,1-lgd,1) -> 0.15 | E20: =Inputs!$B$25*IF($A20>=$G$9,1-lgd,1) -> 0.15 | F20: =Inputs!$B$25*IF($A20>=$G$10,1-lgd,1) -> 0.15 | G20: =Inputs!$B$25*IF($A20>=$G$11,1-lgd,1) -> 0.15 | H20: =Inputs!$B$25*IF($A20>=$G$12,1-lgd,1) -> 0.15 | I20: =Inputs!$B$25*IF($A20>=$G$13,1-lgd,1) -> 0.15 | J20: =Inputs!$B$25*IF($A20>=$G$14,1-lgd,1) -> 0.15 | K20: =Inputs!$B$25*IF($A20>=$G$15,1-lgd,1) -> 0.15 | L20: =SUM(B20:K20) -> 1.5 | M20: =MIN(L20,Inputs!$D$25) -> 0.1 | N20: =MIN(L20-M20,Inputs!$E$25) -> 0.1 | O20: =L20-M20-N20 -> 1.3 | P20: =Inputs!$C$25 -> 1.5
A21: 2 | B21: =Inputs!$B$26*IF($A21>=$G$6,1-lgd,1) -> 0.15 | C21: =Inputs!$B$26*IF($A21>=$G$7,1-lgd,1) -> 0.15 | D21: =Inputs!$B$26*IF($A21>=$G$8,1-lgd,1) -> 0.15 | E21: =Inputs!$B$26*IF($A21>=$G$9,1-lgd,1) -> 0.15 | F21: =Inputs!$B$26*IF($A21>=$G$10,1-lgd,1) -> 0.15 | G21: =Inputs!$B$26*IF($A21>=$G$11,1-lgd,1) -> 0.15 | H21: =Inputs!$B$26*IF($A21>=$G$12,1-lgd,1) -> 0.15 | I21: =Inputs!$B$26*IF($A21>=$G$13,1-lgd,1) -> 0.15 | J21: =Inputs!$B$26*IF($A21>=$G$14,1-lgd,1) -> 0.15 | K21: =Inputs!$B$26*IF($A21>=$G$15,1-lgd,1) -> 0.15 | L21: =SUM(B21:K21) -> 1.5 | M21: =MIN(L21,Inputs!$D$26) -> 0.1 | N21: =MIN(L21-M21,Inputs!$E$26) -> 0.1 | O21: =L21-M21-N21 -> 1.3 | P21: =Inputs!$C$26 -> 1.5
A22: 3 | B22: =Inputs!$B$27*IF($A22>=$G$6,1-lgd,1) -> 0.15 | C22: =Inputs!$B$27*IF($A22>=$G$7,1-lgd,1) -> 0.15 | D22: =Inputs!$B$27*IF($A22>=$G$8,1-lgd,1) -> 0.15 | E22: =Inputs!$B$27*IF($A22>=$G$9,1-lgd,1) -> 0.15 | F22: =Inputs!$B$27*IF($A22>=$G$10,1-lgd,1) -> 0.15 | G22: =Inputs!$B$27*IF($A22>=$G$11,1-lgd,1) -> 0.15 | H22: =Inputs!$B$27*IF($A22>=$G$12,1-lgd,1) -> 0.15 | I22: =Inputs!$B$27*IF($A22>=$G$13,1-lgd,1) -> 0.15 | J22: =Inputs!$B$27*IF($A22>=$G$14,1-lgd,1) -> 0.15 | K22: =Inputs!$B$27*IF($A22>=$G$15,1-lgd,1) -> 0.15 | L22: =SUM(B22:K22) -> 1.5 | M22: =MIN(L22,Inputs!$D$27) -> 0.1 | N22: =MIN(L22-M22,Inputs!$E$27) -> 0.1 | O22: =L22-M22-N22 -> 1.3 | P22: =Inputs!$C$27 -> 1.5
A23: 4 | B23: =Inputs!$B$28*IF($A23>=$G$6,1-lgd,1) -> 0.06 | C23: =Inputs!$B$28*IF($A23>=$G$7,1-lgd,1) -> 0.15 | D23: =Inputs!$B$28*IF($A23>=$G$8,1-lgd,1) -> 0.15 | E23: =Inputs!$B$28*IF($A23>=$G$9,1-lgd,1) -> 0.15 | F23: =Inputs!$B$28*IF($A23>=$G$10,1-lgd,1) -> 0.15 | G23: =Inputs!$B$28*IF($A23>=$G$11,1-lgd,1) -> 0.15 | H23: =Inputs!$B$28*IF($A23>=$G$12,1-lgd,1) -> 0.15 | I23: =Inputs!$B$28*IF($A23>=$G$13,1-lgd,1) -> 0.15 | J23: =Inputs!$B$28*IF($A23>=$G$14,1-lgd,1) -> 0.15 | K23: =Inputs!$B$28*IF($A23>=$G$15,1-lgd,1) -> 0.15 | L23: =SUM(B23:K23) -> 1.41 | M23: =MIN(L23,Inputs!$D$28) -> 0.1 | N23: =MIN(L23-M23,Inputs!$E$28) -> 0.1 | O23: =L23-M23-N23 -> 1.21 | P23: =Inputs!$C$28 -> 1.5
A24: 5 | B24: =Inputs!$B$29*IF($A24>=$G$6,1-lgd,1) -> 0.06 | C24: =Inputs!$B$29*IF($A24>=$G$7,1-lgd,1) -> 0.15 | D24: =Inputs!$B$29*IF($A24>=$G$8,1-lgd,1) -> 0.15 | E24: =Inputs!$B$29*IF($A24>=$G$9,1-lgd,1) -> 0.15 | F24: =Inputs!$B$29*IF($A24>=$G$10,1-lgd,1) -> 0.06 | G24: =Inputs!$B$29*IF($A24>=$G$11,1-lgd,1) -> 0.15 | H24: =Inputs!$B$29*IF($A24>=$G$12,1-lgd,1) -> 0.15 | I24: =Inputs!$B$29*IF($A24>=$G$13,1-lgd,1) -> 0.15 | J24: =Inputs!$B$29*IF($A24>=$G$14,1-lgd,1) -> 0.15 | K24: =Inputs!$B$29*IF($A24>=$G$15,1-lgd,1) -> 0.15 | L24: =SUM(B24:K24) -> 1.32 | M24: =MIN(L24,Inputs!$D$29) -> 0.1 | N24: =MIN(L24-M24,Inputs!$E$29) -> 0.1 | O24: =L24-M24-N24 -> 1.12 | P24: =Inputs!$C$29 -> 1.5
A25: 6 | B25: =Inputs!$B$30*IF($A25>=$G$6,1-lgd,1) -> 0.06 | C25: =Inputs!$B$30*IF($A25>=$G$7,1-lgd,1) -> 0.15 | D25: =Inputs!$B$30*IF($A25>=$G$8,1-lgd,1) -> 0.15 | E25: =Inputs!$B$30*IF($A25>=$G$9,1-lgd,1) -> 0.15 | F25: =Inputs!$B$30*IF($A25>=$G$10,1-lgd,1) -> 0.06 | G25: =Inputs!$B$30*IF($A25>=$G$11,1-lgd,1) -> 0.15 | H25: =Inputs!$B$30*IF($A25>=$G$12,1-lgd,1) -> 0.15 | I25: =Inputs!$B$30*IF($A25>=$G$13,1-lgd,1) -> 0.15 | J25: =Inputs!$B$30*IF($A25>=$G$14,1-lgd,1) -> 0.15 | K25: =Inputs!$B$30*IF($A25>=$G$15,1-lgd,1) -> 0.15 | L25: =SUM(B25:K25) -> 1.32 | M25: =MIN(L25,Inputs!$D$30) -> 0.1 | N25: =MIN(L25-M25,Inputs!$E$30) -> 0.1 | O25: =L25-M25-N25 -> 1.12 | P25: =Inputs!$C$30 -> 1.5
A26: 7 | B26: =Inputs!$B$31*IF($A26>=$G$6,1-lgd,1) -> 0.06 | C26: =Inputs!$B$31*IF($A26>=$G$7,1-lgd,1) -> 0.15 | D26: =Inputs!$B$31*IF($A26>=$G$8,1-lgd,1) -> 0.15 | E26: =Inputs!$B$31*IF($A26>=$G$9,1-lgd,1) -> 0.15 | F26: =Inputs!$B$31*IF($A26>=$G$10,1-lgd,1) -> 0.06 | G26: =Inputs!$B$31*IF($A26>=$G$11,1-lgd,1) -> 0.15 | H26: =Inputs!$B$31*IF($A26>=$G$12,1-lgd,1) -> 0.15 | I26: =Inputs!$B$31*IF($A26>=$G$13,1-lgd,1) -> 0.15 | J26: =Inputs!$B$31*IF($A26>=$G$14,1-lgd,1) -> 0.06 | K26: =Inputs!$B$31*IF($A26>=$G$15,1-lgd,1) -> 0.15 | L26: =SUM(B26:K26) -> 1.23 | M26: =MIN(L26,Inputs!$D$31) -> 0.1 | N26: =MIN(L26-M26,Inputs!$E$31) -> 0.1 | O26: =L26-M26-N26 -> 1.03 | P26: =Inputs!$C$31 -> 1.5
A27: 8 | B27: =Inputs!$B$32*IF($A27>=$G$6,1-lgd,1) -> 0.06 | C27: =Inputs!$B$32*IF($A27>=$G$7,1-lgd,1) -> 0.15 | D27: =Inputs!$B$32*IF($A27>=$G$8,1-lgd,1) -> 0.15 | E27: =Inputs!$B$32*IF($A27>=$G$9,1-lgd,1) -> 0.15 | F27: =Inputs!$B$32*IF($A27>=$G$10,1-lgd,1) -> 0.06 | G27: =Inputs!$B$32*IF($A27>=$G$11,1-lgd,1) -> 0.15 | H27: =Inputs!$B$32*IF($A27>=$G$12,1-lgd,1) -> 0.15 | I27: =Inputs!$B$32*IF($A27>=$G$13,1-lgd,1) -> 0.15 | J27: =Inputs!$B$32*IF($A27>=$G$14,1-lgd,1) -> 0.06 | K27: =Inputs!$B$32*IF($A27>=$G$15,1-lgd,1) -> 0.15 | L27: =SUM(B27:K27) -> 1.23 | M27: =MIN(L27,Inputs!$D$32) -> 0.1 | N27: =MIN(L27-M27,Inputs!$E$32) -> 0.1 | O27: =L27-M27-N27 -> 1.03 | P27: =Inputs!$C$32 -> 1.5
A28: 9 | B28: =Inputs!$B$33*IF($A28>=$G$6,1-lgd,1) -> 0.06 | C28: =Inputs!$B$33*IF($A28>=$G$7,1-lgd,1) -> 0.15 | D28: =Inputs!$B$33*IF($A28>=$G$8,1-lgd,1) -> 0.15 | E28: =Inputs!$B$33*IF($A28>=$G$9,1-lgd,1) -> 0.15 | F28: =Inputs!$B$33*IF($A28>=$G$10,1-lgd,1) -> 0.06 | G28: =Inputs!$B$33*IF($A28>=$G$11,1-lgd,1) -> 0.15 | H28: =Inputs!$B$33*IF($A28>=$G$12,1-lgd,1) -> 0.15 | I28: =Inputs!$B$33*IF($A28>=$G$13,1-lgd,1) -> 0.15 | J28: =Inputs!$B$33*IF($A28>=$G$14,1-lgd,1) -> 0.06 | K28: =Inputs!$B$33*IF($A28>=$G$15,1-lgd,1) -> 0.15 | L28: =SUM(B28:K28) -> 1.23 | M28: =MIN(L28,Inputs!$D$33) -> 0.1 | N28: =MIN(L28-M28,Inputs!$E$33) -> 0.1 | O28: =L28-M28-N28 -> 1.03 | P28: =Inputs!$C$33 -> 1.5
A29: 10 | B29: =Inputs!$B$34*IF($A29>=$G$6,1-lgd,1) -> 0.06 | C29: =Inputs!$B$34*IF($A29>=$G$7,1-lgd,1) -> 0.15 | D29: =Inputs!$B$34*IF($A29>=$G$8,1-lgd,1) -> 0.15 | E29: =Inputs!$B$34*IF($A29>=$G$9,1-lgd,1) -> 0.15 | F29: =Inputs!$B$34*IF($A29>=$G$10,1-lgd,1) -> 0.06 | G29: =Inputs!$B$34*IF($A29>=$G$11,1-lgd,1) -> 0.15 | H29: =Inputs!$B$34*IF($A29>=$G$12,1-lgd,1) -> 0.15 | I29: =Inputs!$B$34*IF($A29>=$G$13,1-lgd,1) -> 0.15 | J29: =Inputs!$B$34*IF($A29>=$G$14,1-lgd,1) -> 0.06 | K29: =Inputs!$B$34*IF($A29>=$G$15,1-lgd,1) -> 0.15 | L29: =SUM(B29:K29) -> 1.23 | M29: =MIN(L29,Inputs!$D$34) -> 0.1 | N29: =MIN(L29-M29,Inputs!$E$34) -> 0.1 | O29: =L29-M29-N29 -> 1.03 | P29: =Inputs!$C$34 -> 1.5
A30: 11 | B30: =Inputs!$B$35*IF($A30>=$G$6,1-lgd,1) -> 0.06 | C30: =Inputs!$B$35*IF($A30>=$G$7,1-lgd,1) -> 0.15 | D30: =Inputs!$B$35*IF($A30>=$G$8,1-lgd,1) -> 0.15 | E30: =Inputs!$B$35*IF($A30>=$G$9,1-lgd,1) -> 0.15 | F30: =Inputs!$B$35*IF($A30>=$G$10,1-lgd,1) -> 0.06 | G30: =Inputs!$B$35*IF($A30>=$G$11,1-lgd,1) -> 0.15 | H30: =Inputs!$B$35*IF($A30>=$G$12,1-lgd,1) -> 0.15 | I30: =Inputs!$B$35*IF($A30>=$G$13,1-lgd,1) -> 0.15 | J30: =Inputs!$B$35*IF($A30>=$G$14,1-lgd,1) -> 0.06 | K30: =Inputs!$B$35*IF($A30>=$G$15,1-lgd,1) -> 0.15 | L30: =SUM(B30:K30) -> 1.23 | M30: =MIN(L30,Inputs!$D$35) -> 0.1 | N30: =MIN(L30-M30,Inputs!$E$35) -> 0.1 | O30: =L30-M30-N30 -> 1.03 | P30: =Inputs!$C$35 -> 1.5
A31: 12 | B31: =Inputs!$B$36*IF($A31>=$G$6,1-lgd,1) -> 0.06 | C31: =Inputs!$B$36*IF($A31>=$G$7,1-lgd,1) -> 0.15 | D31: =Inputs!$B$36*IF($A31>=$G$8,1-lgd,1) -> 0.15 | E31: =Inputs!$B$36*IF($A31>=$G$9,1-lgd,1) -> 0.15 | F31: =Inputs!$B$36*IF($A31>=$G$10,1-lgd,1) -> 0.06 | G31: =Inputs!$B$36*IF($A31>=$G$11,1-lgd,1) -> 0.15 | H31: =Inputs!$B$36*IF($A31>=$G$12,1-lgd,1) -> 0.06 | I31: =Inputs!$B$36*IF($A31>=$G$13,1-lgd,1) -> 0.15 | J31: =Inputs!$B$36*IF($A31>=$G$14,1-lgd,1) -> 0.06 | K31: =Inputs!$B$36*IF($A31>=$G$15,1-lgd,1) -> 0.15 | L31: =SUM(B31:K31) -> 1.14 | M31: =MIN(L31,Inputs!$D$36) -> 0.1 | N31: =MIN(L31-M31,Inputs!$E$36) -> 0.1 | O31: =L31-M31-N31 -> 0.94 | P31: =Inputs!$C$36 -> 1.5
A32: 13 | B32: =Inputs!$B$37*IF($A32>=$G$6,1-lgd,1) -> 0.06 | C32: =Inputs!$B$37*IF($A32>=$G$7,1-lgd,1) -> 0.15 | D32: =Inputs!$B$37*IF($A32>=$G$8,1-lgd,1) -> 0.15 | E32: =Inputs!$B$37*IF($A32>=$G$9,1-lgd,1) -> 0.15 | F32: =Inputs!$B$37*IF($A32>=$G$10,1-lgd,1) -> 0.06 | G32: =Inputs!$B$37*IF($A32>=$G$11,1-lgd,1) -> 0.06 | H32: =Inputs!$B$37*IF($A32>=$G$12,1-lgd,1) -> 0.06 | I32: =Inputs!$B$37*IF($A32>=$G$13,1-lgd,1) -> 0.15 | J32: =Inputs!$B$37*IF($A32>=$G$14,1-lgd,1) -> 0.06 | K32: =Inputs!$B$37*IF($A32>=$G$15,1-lgd,1) -> 0.15 | L32: =SUM(B32:K32) -> 1.05 | M32: =MIN(L32,Inputs!$D$37) -> 0.1 | N32: =MIN(L32-M32,Inputs!$E$37) -> 0.1 | O32: =L32-M32-N32 -> 0.85 | P32: =Inputs!$C$37 -> 1.5
A33: 14 | B33: =Inputs!$B$38*IF($A33>=$G$6,1-lgd,1) -> 0.06 | C33: =Inputs!$B$38*IF($A33>=$G$7,1-lgd,1) -> 0.15 | D33: =Inputs!$B$38*IF($A33>=$G$8,1-lgd,1) -> 0.15 | E33: =Inputs!$B$38*IF($A33>=$G$9,1-lgd,1) -> 0.15 | F33: =Inputs!$B$38*IF($A33>=$G$10,1-lgd,1) -> 0.06 | G33: =Inputs!$B$38*IF($A33>=$G$11,1-lgd,1) -> 0.06 | H33: =Inputs!$B$38*IF($A33>=$G$12,1-lgd,1) -> 0.06 | I33: =Inputs!$B$38*IF($A33>=$G$13,1-lgd,1) -> 0.15 | J33: =Inputs!$B$38*IF($A33>=$G$14,1-lgd,1) -> 0.06 | K33: =Inputs!$B$38*IF($A33>=$G$15,1-lgd,1) -> 0.15 | L33: =SUM(B33:K33) -> 1.05 | M33: =MIN(L33,Inputs!$D$38) -> 0.1 | N33: =MIN(L33-M33,Inputs!$E$38) -> 0.1 | O33: =L33-M33-N33 -> 0.85 | P33: =Inputs!$C$38 -> 1.5
A34: 15 | B34: =Inputs!$B$39*IF($A34>=$G$6,1-lgd,1) -> 0.06 | C34: =Inputs!$B$39*IF($A34>=$G$7,1-lgd,1) -> 0.15 | D34: =Inputs!$B$39*IF($A34>=$G$8,1-lgd,1) -> 0.15 | E34: =Inputs!$B$39*IF($A34>=$G$9,1-lgd,1) -> 0.15 | F34: =Inputs!$B$39*IF($A34>=$G$10,1-lgd,1) -> 0.06 | G34: =Inputs!$B$39*IF($A34>=$G$11,1-lgd,1) -> 0.06 | H34: =Inputs!$B$39*IF($A34>=$G$12,1-lgd,1) -> 0.06 | I34: =Inputs!$B$39*IF($A34>=$G$13,1-lgd,1) -> 0.15 | J34: =Inputs!$B$39*IF($A34>=$G$14,1-lgd,1) -> 0.06 | K34: =Inputs!$B$39*IF($A34>=$G$15,1-lgd,1) -> 0.15 | L34: =SUM(B34:K34) -> 1.05 | M34: =MIN(L34,Inputs!$D$39) -> 0.1 | N34: =MIN(L34-M34,Inputs!$E$39) -> 0.1 | O34: =L34-M34-N34 -> 0.85 | P34: =Inputs!$C$39 -> 1.5
A35: 16 | B35: =Inputs!$B$40*IF($A35>=$G$6,1-lgd,1) -> 0.06 | C35: =Inputs!$B$40*IF($A35>=$G$7,1-lgd,1) -> 0.15 | D35: =Inputs!$B$40*IF($A35>=$G$8,1-lgd,1) -> 0.15 | E35: =Inputs!$B$40*IF($A35>=$G$9,1-lgd,1) -> 0.15 | F35: =Inputs!$B$40*IF($A35>=$G$10,1-lgd,1) -> 0.06 | G35: =Inputs!$B$40*IF($A35>=$G$11,1-lgd,1) -> 0.06 | H35: =Inputs!$B$40*IF($A35>=$G$12,1-lgd,1) -> 0.06 | I35: =Inputs!$B$40*IF($A35>=$G$13,1-lgd,1) -> 0.15 | J35: =Inputs!$B$40*IF($A35>=$G$14,1-lgd,1) -> 0.06 | K35: =Inputs!$B$40*IF($A35>=$G$15,1-lgd,1) -> 0.15 | L35: =SUM(B35:K35) -> 1.05 | M35: =MIN(L35,Inputs!$D$40) -> 0.1 | N35: =MIN(L35-M35,Inputs!$E$40) -> 0.1 | O35: =L35-M35-N35 -> 0.85 | P35: =Inputs!$C$40 -> 1.5
A36: 17 | B36: =Inputs!$B$41*IF($A36>=$G$6,1-lgd,1) -> 0.06 | C36: =Inputs!$B$41*IF($A36>=$G$7,1-lgd,1) -> 0.15 | D36: =Inputs!$B$41*IF($A36>=$G$8,1-lgd,1) -> 0.15 | E36: =Inputs!$B$41*IF($A36>=$G$9,1-lgd,1) -> 0.15 | F36: =Inputs!$B$41*IF($A36>=$G$10,1-lgd,1) -> 0.06 | G36: =Inputs!$B$41*IF($A36>=$G$11,1-lgd,1) -> 0.06 | H36: =Inputs!$B$41*IF($A36>=$G$12,1-lgd,1) -> 0.06 | I36: =Inputs!$B$41*IF($A36>=$G$13,1-lgd,1) -> 0.15 | J36: =Inputs!$B$41*IF($A36>=$G$14,1-lgd,1) -> 0.06 | K36: =Inputs!$B$41*IF($A36>=$G$15,1-lgd,1) -> 0.15 | L36: =SUM(B36:K36) -> 1.05 | M36: =MIN(L36,Inputs!$D$41) -> 0.1 | N36: =MIN(L36-M36,Inputs!$E$41) -> 0.1 | O36: =L36-M36-N36 -> 0.85 | P36: =Inputs!$C$41 -> 1.5
A37: 18 | B37: =Inputs!$B$42*IF($A37>=$G$6,1-lgd,1) -> 0.06 | C37: =Inputs!$B$42*IF($A37>=$G$7,1-lgd,1) -> 0.15 | D37: =Inputs!$B$42*IF($A37>=$G$8,1-lgd,1) -> 0.15 | E37: =Inputs!$B$42*IF($A37>=$G$9,1-lgd,1) -> 0.15 | F37: =Inputs!$B$42*IF($A37>=$G$10,1-lgd,1) -> 0.06 | G37: =Inputs!$B$42*IF($A37>=$G$11,1-lgd,1) -> 0.06 | H37: =Inputs!$B$42*IF($A37>=$G$12,1-lgd,1) -> 0.06 | I37: =Inputs!$B$42*IF($A37>=$G$13,1-lgd,1) -> 0.15 | J37: =Inputs!$B$42*IF($A37>=$G$14,1-lgd,1) -> 0.06 | K37: =Inputs!$B$42*IF($A37>=$G$15,1-lgd,1) -> 0.15 | L37: =SUM(B37:K37) -> 1.05 | M37: =MIN(L37,Inputs!$D$42) -> 0.1 | N37: =MIN(L37-M37,Inputs!$E$42) -> 0.1 | O37: =L37-M37-N37 -> 0.85 | P37: =Inputs!$C$42 -> 1.5
A38: 19 | B38: =Inputs!$B$43*IF($A38>=$G$6,1-lgd,1) -> 0.06 | C38: =Inputs!$B$43*IF($A38>=$G$7,1-lgd,1) -> 0.15 | D38: =Inputs!$B$43*IF($A38>=$G$8,1-lgd,1) -> 0.15 | E38: =Inputs!$B$43*IF($A38>=$G$9,1-lgd,1) -> 0.15 | F38: =Inputs!$B$43*IF($A38>=$G$10,1-lgd,1) -> 0.06 | G38: =Inputs!$B$43*IF($A38>=$G$11,1-lgd,1) -> 0.06 | H38: =Inputs!$B$43*IF($A38>=$G$12,1-lgd,1) -> 0.06 | I38: =Inputs!$B$43*IF($A38>=$G$13,1-lgd,1) -> 0.15 | J38: =Inputs!$B$43*IF($A38>=$G$14,1-lgd,1) -> 0.06 | K38: =Inputs!$B$43*IF($A38>=$G$15,1-lgd,1) -> 0.15 | L38: =SUM(B38:K38) -> 1.05 | M38: =MIN(L38,Inputs!$D$43) -> 0.1 | N38: =MIN(L38-M38,Inputs!$E$43) -> 0.1 | O38: =L38-M38-N38 -> 0.85 | P38: =Inputs!$C$43 -> 1.5
A39: 20 | B39: =Inputs!$B$44*IF($A39>=$G$6,1-lgd,1) -> 4.06 | C39: =Inputs!$B$44*IF($A39>=$G$7,1-lgd,1) -> 10.15 | D39: =Inputs!$B$44*IF($A39>=$G$8,1-lgd,1) -> 10.15 | E39: =Inputs!$B$44*IF($A39>=$G$9,1-lgd,1) -> 4.06 | F39: =Inputs!$B$44*IF($A39>=$G$10,1-lgd,1) -> 4.06 | G39: =Inputs!$B$44*IF($A39>=$G$11,1-lgd,1) -> 4.06 | H39: =Inputs!$B$44*IF($A39>=$G$12,1-lgd,1) -> 4.06 | I39: =Inputs!$B$44*IF($A39>=$G$13,1-lgd,1) -> 10.15 | J39: =Inputs!$B$44*IF($A39>=$G$14,1-lgd,1) -> 4.06 | K39: =Inputs!$B$44*IF($A39>=$G$15,1-lgd,1) -> 10.15 | L39: =SUM(B39:K39) -> 64.96 | M39: =MIN(L39,Inputs!$D$44) -> 20.1 | N39: =MIN(L39-M39,Inputs!$E$44) -> 10.1 | O39: =L39-M39-N39 -> 34.76 | P39: =Inputs!$C$44 -> 101.5
A40: Total | B40: =SUM(B20:B39) -> 5.47 | C40: =SUM(C20:C39) -> 13 | D40: =SUM(D20:D39) -> 13 | E40: =SUM(E20:E39) -> 6.91 | F40: =SUM(F20:F39) -> 5.56 | G40: =SUM(G20:G39) -> 6.28 | H40: =SUM(H20:H39) -> 6.19 | I40: =SUM(I20:I39) -> 13 | ... P40: =SUM(P20:P39) -> 130
A42: Check: pool total for this case on the CashFlows sheet minus the total above (should be 0) | L42: =ROUND(INDEX(CashFlows!$CH$18:$CH$1017,case_number)-L40,9) -> 0

Sheet Random
A1: Fixed random numbers and moment matching
A2: 1000 cases x 10 bonds of independent standard normals, generated once in Python (numpy default_rng, seed 6103) and stored as values, so every recalculation uses the same numbers. They are then de-meaned and moment matched: multiplied by the inverse of the Cholesky factor of their covariance, which gives numbers with means of exactly 0, variances of exactly 1 and no correlation.
B3: Covariance of the initial numbers (population) | M3: Cholesky factor L of that covariance | X3: Inverse of L | AI3: Check: covariance of the moment-matched numbers (identity)
B4: =COVAR($B$18:$B$1017,$B$18:$B$1017) -> 1.0092959 | C4: =COVAR($B$18:$B$1017,$C$18:$C$1017) -> -0.0075252807 | D4: =COVAR($B$18:$B$1017,$D$18:$D$1017) -> -0.0015624279 | E4: =COVAR($B$18:$B$1017,$E$18:$E$1017) -> 0.0070805288 | F4: =COVAR($B$18:$B$1017,$F$18:$F$1017) -> 0.023571375 | G4: =COVAR($B$18:$B$1017,$G$18:$G$1017) -> 0.01507392 | H4: =COVAR($B$18:$B$1017,$H$18:$H$1017) -> 0.02057704 | I4: =COVAR($B$18:$B$1017,$I$18:$I$1017) -> 0.020295584 | J4: =COVAR($B$18:$B$1017,$J$18:$J$1017) -> -0.010252705 | K4: =COVAR($B$18:$B$1017,$K$18:$K$1017) -> -0.0234292 | M4: =SQRT(B4) -> 1.0046372 | N4: 0 | O4: 0 | P4: 0 | Q4: 0 | R4: 0 | S4: 0 | T4: 0 | U4: 0 | V4: 0 | X4: {=MINVERSE(M4:V13)} -> 0.99538421 | Y4: 0 | Z4: 0 | AA4: 0 | AB4: 0 | AC4: 0 | AD4: 0 | AE4: 0 | AF4: 0 | AG4: 0 | AI4: =COVAR($X$18:$X$1017,$X$18:$X$1017) -> 1 | AJ4: =COVAR($X$18:$X$1017,$Y$18:$Y$1017) -> -1.831868e-17 | AK4: =COVAR($X$18:$X$1017,$Z$18:$Z$1017) -> -1.5765167e-17 | AL4: =COVAR($X$18:$X$1017,$AA$18:$AA$1017) -> -8.6874952e-18 | AM4: =COVAR($X$18:$X$1017,$AB$18:$AB$1017) -> -1.3877788e-17 | AN4: =COVAR($X$18:$X$1017,$AC$18:$AC$1017) -> 1.7319479e-17 | AO4: =COVAR($X$18:$X$1017,$AD$18:$AD$1017) -> -2.5757174e-17 | AP4: =COVAR($X$18:$X$1017,$AE$18:$AE$1017) -> 1.7597035e-17 | AQ4: =COVAR($X$18:$X$1017,$AF$18:$AF$1017) -> 3.9135362e-17 | AR4: =COVAR($X$18:$X$1017,$AG$18:$AG$1017) -> 4.2327253e-19
B5: =COVAR($C$18:$C$1017,$B$18:$B$1017) -> -0.0075252807 | C5: =COVAR($C$18:$C$1017,$C$18:$C$1017) -> 1.0286454 | D5: =COVAR($C$18:$C$1017,$D$18:$D$1017) -> 0.0034923397 | E5: =COVAR($C$18:$C$1017,$E$18:$E$1017) -> 0.0062694234 | F5: =COVAR($C$18:$C$1017,$F$18:$F$1017) -> 0.021607608 | G5: =COVAR($C$18:$C$1017,$G$18:$G$1017) -> 0.042956429 | H5: =COVAR($C$18:$C$1017,$H$18:$H$1017) -> -0.052975298 | I5: =COVAR($C$18:$C$1017,$I$18:$I$1017) -> 0.088553723 | J5: =COVAR($C$18:$C$1017,$J$18:$J$1017) -> -0.062365207 | K5: =COVAR($C$18:$C$1017,$K$18:$K$1017) -> 0.016286095 | M5: =B5/$M$4 -> -0.0074905456 | N5: =SQRT(C5-SUMSQ($M5:M5)) -> 1.0141939 | O5: 0 | P5: 0 | Q5: 0 | R5: 0 | S5: 0 | T5: 0 | U5: 0 | V5: 0 | X5: 0.0073516226 | Y5: 0.98600473 | Z5: 0 | AA5: 0 | AB5: 0 | AC5: 0 | AD5: 0 | AE5: 0 | AF5: 0 | AG5: 0 | AI5: =COVAR($Y$18:$Y$1017,$X$18:$X$1017) -> -1.831868e-17 | AJ5: =COVAR($Y$18:$Y$1017,$Y$18:$Y$1017) -> 1 | AK5: =COVAR($Y$18:$Y$1017,$Z$18:$Z$1017) -> 1.4321877e-17 | AL5: =COVAR($Y$18:$Y$1017,$AA$18:$AA$1017) -> -1.1268764e-17 | AM5: =COVAR($Y$18:$Y$1017,$AB$18:$AB$1017) -> -4.2132964e-17 | AN5: =COVAR($Y$18:$Y$1017,$AC$18:$AC$1017) -> -6.5725203e-17 | AO5: =COVAR($Y$18:$Y$1017,$AD$18:$AD$1017) -> 4.2382764e-17 | AP5: =COVAR($Y$18:$Y$1017,$AE$18:$AE$1017) -> 1.2451151e-16 | AQ5: =COVAR($Y$18:$Y$1017,$AF$18:$AF$1017) -> 7.6050277e-18 | AR5: =COVAR($Y$18:$Y$1017,$AG$18:$AG$1017) -> 3.2925052e-17
B6: =COVAR($D$18:$D$1017,$B$18:$B$1017) -> -0.0015624279 | C6: =COVAR($D$18:$D$1017,$C$18:$C$1017) -> 0.0034923397 | D6: =COVAR($D$18:$D$1017,$D$18:$D$1017) -> 1.0013933 | E6: =COVAR($D$18:$D$1017,$E$18:$E$1017) -> 0.034972157 | F6: =COVAR($D$18:$D$1017,$F$18:$F$1017) -> 0.0075113511 | G6: =COVAR($D$18:$D$1017,$G$18:$G$1017) -> 0.0081424253 | H6: =COVAR($D$18:$D$1017,$H$18:$H$1017) -> 0.034026381 | I6: =COVAR($D$18:$D$1017,$I$18:$I$1017) -> 0.020532999 | J6: =COVAR($D$18:$D$1017,$J$18:$J$1017) -> 0.0060919711 | K6: =COVAR($D$18:$D$1017,$K$18:$K$1017) -> 0.070295138 | M6: =B6/$M$4 -> -0.0015552161 | N6: =(C6-SUMPRODUCT($M6:M6,$M5:M5))/N5 -> 0.0034319771 | O6: =SQRT(D6-SUMSQ($M6:N6)) -> 1.0006893 | P6: 0 | Q6: 0 | R6: 0 | S6: 0 | T6: 0 | U6: 0 | V6: 0 | X6: 0.0015217579 | Y6: -0.0033816146 | Z6: 0.99931115 | AA6: 0 | AB6: 0 | AC6: 0 | AD6: 0 | AE6: 0 | AF6: 0 | AG6: 0 | AI6: =COVAR($Z$18:$Z$1017,$X$18:$X$1017) -> -1.5765167e-17 | AJ6: =COVAR($Z$18:$Z$1017,$Y$18:$Y$1017) -> 1.4321877e-17 | AK6: =COVAR($Z$18:$Z$1017,$Z$18:$Z$1017) -> 1 | AL6: =COVAR($Z$18:$Z$1017,$AA$18:$AA$1017) -> -6.3282712e-17 | AM6: =COVAR($Z$18:$Z$1017,$AB$18:$AB$1017) -> -3.1086245e-18 | AN6: =COVAR($Z$18:$Z$1017,$AC$18:$AC$1017) -> 3.7747583e-17 | AO6: =COVAR($Z$18:$Z$1017,$AD$18:$AD$1017) -> 2.4202862e-17 | AP6: =COVAR($Z$18:$Z$1017,$AE$18:$AE$1017) -> 9.7699626e-18 | AQ6: =COVAR($Z$18:$Z$1017,$AF$18:$AF$1017) -> 1.9095836e-17 | AR6: =COVAR($Z$18:$Z$1017,$AG$18:$AG$1017) -> 6.0562666e-17
B7: =COVAR($E$18:$E$1017,$B$18:$B$1017) -> 0.0070805288 | C7: =COVAR($E$18:$E$1017,$C$18:$C$1017) -> 0.0062694234 | D7: =COVAR($E$18:$E$1017,$D$18:$D$1017) -> 0.034972157 | E7: =COVAR($E$18:$E$1017,$E$18:$E$1017) -> 0.98057864 | F7: =COVAR($E$18:$E$1017,$F$18:$F$1017) -> 0.019587025 | G7: =COVAR($E$18:$E$1017,$G$18:$G$1017) -> 0.01930415 | H7: =COVAR($E$18:$E$1017,$H$18:$H$1017) -> 0.028531027 | I7: =COVAR($E$18:$E$1017,$I$18:$I$1017) -> 0.024922848 | J7: =COVAR($E$18:$E$1017,$J$18:$J$1017) -> -0.052906483 | K7: =COVAR($E$18:$E$1017,$K$18:$K$1017) -> -0.028253352 | M7: =B7/$M$4 -> 0.0070478466 | N7: =(C7-SUMPRODUCT($M7:M7,$M5:M5))/N5 -> 0.0062337345 | O7: =(D7-SUMPRODUCT($M7:N7,$M6:N6))/O6 -> 0.034937641 | P7: =SQRT(E7-SUMSQ($M7:O7)) -> 0.98958045 | Q7: 0 | R7: 0 | S7: 0 | T7: 0 | U7: 0 | V7: 0 | X7: -0.0071892184 | Y7: -0.0060918201 | Z7: -0.035281188 | AA7: 1.0105293 | AB7: 0 | AC7: 0 | AD7: 0 | AE7: 0 | AF7: 0 | AG7: 0 | AI7: =COVAR($AA$18:$AA$1017,$X$18:$X$1017) -> -8.6874952e-18 | AJ7: =COVAR($AA$18:$AA$1017,$Y$18:$Y$1017) -> -1.1268764e-17 | AK7: =COVAR($AA$18:$AA$1017,$Z$18:$Z$1017) -> -6.3282712e-17 | AL7: =COVAR($AA$18:$AA$1017,$AA$18:$AA$1017) -> 1 | AM7: =COVAR($AA$18:$AA$1017,$AB$18:$AB$1017) -> -9.4479979e-17 | AN7: =COVAR($AA$18:$AA$1017,$AC$18:$AC$1017) -> -3.9301895e-17 | AO7: =COVAR($AA$18:$AA$1017,$AD$18:$AD$1017) -> -6.1450844e-17 | AP7: =COVAR($AA$18:$AA$1017,$AE$18:$AE$1017) -> -9.8809849e-17 | AQ7: =COVAR($AA$18:$AA$1017,$AF$18:$AF$1017) -> 6.2561067e-17 | AR7: =COVAR($AA$18:$AA$1017,$AG$18:$AG$1017) -> 8.1254448e-17
B8: =COVAR($F$18:$F$1017,$B$18:$B$1017) -> 0.023571375 | C8: =COVAR($F$18:$F$1017,$C$18:$C$1017) -> 0.021607608 | D8: =COVAR($F$18:$F$1017,$D$18:$D$1017) -> 0.0075113511 | E8: =COVAR($F$18:$F$1017,$E$18:$E$1017) -> 0.019587025 | F8: =COVAR($F$18:$F$1017,$F$18:$F$1017) -> 1.0388062 | G8: =COVAR($F$18:$F$1017,$G$18:$G$1017) -> -0.012111641 | H8: =COVAR($F$18:$F$1017,$H$18:$H$1017) -> -0.0014115587 | I8: =COVAR($F$18:$F$1017,$I$18:$I$1017) -> -0.010611901 | J8: =COVAR($F$18:$F$1017,$J$18:$J$1017) -> -0.041997899 | K8: =COVAR($F$18:$F$1017,$K$18:$K$1017) -> 0.045961781 | M8: =B8/$M$4 -> 0.023462575 | N8: =(C8-SUMPRODUCT($M8:M8,$M5:M5))/N5 -> 0.021478492 | O8: =(D8-SUMPRODUCT($M8:N8,$M6:N6))/O6 -> 0.0074689782 | P8: =(E8-SUMPRODUCT($M8:O8,$M7:O7))/P7 -> 0.019227163 | Q8: =SQRT(F8-SUMSQ($M8:P8)) -> 1.0185131 | R8: 0 | S8: 0 | T8: 0 | U8: 0 | V8: 0 | X8: -0.02296025 | Y8: -0.020653155 | Z8: -0.0066621391 | AA8: -0.019076447 | AB8: 0.9818234 | AC8: 0 | AD8: 0 | AE8: 0 | AF8: 0 | AG8: 0 | AI8: =COVAR($AB$18:$AB$1017,$X$18:$X$1017) -> -1.3877788e-17 | AJ8: =COVAR($AB$18:$AB$1017,$Y$18:$Y$1017) -> -4.2132964e-17 | AK8: =COVAR($AB$18:$AB$1017,$Z$18:$Z$1017) -> -3.1086245e-18 | AL8: =COVAR($AB$18:$AB$1017,$AA$18:$AA$1017) -> -9.4479979e-17 | AM8: =COVAR($AB$18:$AB$1017,$AB$18:$AB$1017) -> 1 | AN8: =COVAR($AB$18:$AB$1017,$AC$18:$AC$1017) -> -3.9968029e-18 | AO8: =COVAR($AB$18:$AB$1017,$AD$18:$AD$1017) -> 2.9976022e-18 | AP8: =COVAR($AB$18:$AB$1017,$AE$18:$AE$1017) -> -9.547918e-18 | AQ8: =COVAR($AB$18:$AB$1017,$AF$18:$AF$1017) -> -4.773959e-17 | AR8: =COVAR($AB$18:$AB$1017,$AG$18:$AG$1017) -> -3.494427e-17
B9: =COVAR($G$18:$G$1017,$B$18:$B$1017) -> 0.01507392 | C9: =COVAR($G$18:$G$1017,$C$18:$C$1017) -> 0.042956429 | D9: =COVAR($G$18:$G$1017,$D$18:$D$1017) -> 0.0081424253 | E9: =COVAR($G$18:$G$1017,$E$18:$E$1017) -> 0.01930415 | F9: =COVAR($G$18:$G$1017,$F$18:$F$1017) -> -0.012111641 | G9: =COVAR($G$18:$G$1017,$G$18:$G$1017) -> 1.0256948 | H9: =COVAR($G$18:$G$1017,$H$18:$H$1017) -> -0.0011387811 | I9: =COVAR($G$18:$G$1017,$I$18:$I$1017) -> 0.052862551 | J9: =COVAR($G$18:$G$1017,$J$18:$J$1017) -> -0.060624425 | K9: =COVAR($G$18:$G$1017,$K$18:$K$1017) -> -0.010844416 | M9: =B9/$M$4 -> 0.015004342 | N9: =(C9-SUMPRODUCT($M9:M9,$M5:M5))/N5 -> 0.04246606 | O9: =(D9-SUMPRODUCT($M9:N9,$M6:N6))/O6 -> 0.0080144931 | P9: =(E9-SUMPRODUCT($M9:O9,$M7:O7))/P7 -> 0.018850082 | Q9: =(F9-SUMPRODUCT($M9:P9,$M8:P8))/Q8 -> -0.01354728 | R9: =SQRT(G9-SUMSQ($M9:Q9)) -> 1.0114659 | S9: 0 | T9: 0 | U9: 0 | V9: 0 | X9: -0.015260038 | Y9: -0.04153338 | Z9: -0.0073498999 | AA9: -0.019088131 | AB9: 0.013150257 | AC9: 0.9886641 | AD9: 0 | AE9: 0 | AF9: 0 | AG9: 0 | AI9: =COVAR($AC$18:$AC$1017,$X$18:$X$1017) -> 1.7319479e-17 | AJ9: =COVAR($AC$18:$AC$1017,$Y$18:$Y$1017) -> -6.5725203e-17 | AK9: =COVAR($AC$18:$AC$1017,$Z$18:$Z$1017) -> 3.7747583e-17 | AL9: =COVAR($AC$18:$AC$1017,$AA$18:$AA$1017) -> -3.9301895e-17 | AM9: =COVAR($AC$18:$AC$1017,$AB$18:$AB$1017) -> -3.9968029e-18 | AN9: =COVAR($AC$18:$AC$1017,$AC$18:$AC$1017) -> 1 | AO9: =COVAR($AC$18:$AC$1017,$AD$18:$AD$1017) -> -1.6653345e-18 | AP9: =COVAR($AC$18:$AC$1017,$AE$18:$AE$1017) -> -8.3266727e-17 | AQ9: =COVAR($AC$18:$AC$1017,$AF$18:$AF$1017) -> -2.4646951e-17 | AR9: =COVAR($AC$18:$AC$1017,$AG$18:$AG$1017) -> -1.8735014e-17
B10: =COVAR($H$18:$H$1017,$B$18:$B$1017) -> 0.02057704 | C10: =COVAR($H$18:$H$1017,$C$18:$C$1017) -> -0.052975298 | D10: =COVAR($H$18:$H$1017,$D$18:$D$1017) -> 0.034026381 | E10: =COVAR($H$18:$H$1017,$E$18:$E$1017) -> 0.028531027 | F10: =COVAR($H$18:$H$1017,$F$18:$F$1017) -> -0.0014115587 | G10: =COVAR($H$18:$H$1017,$G$18:$G$1017) -> -0.0011387811 | H10: =COVAR($H$18:$H$1017,$H$18:$H$1017) -> 1.0053972 | I10: =COVAR($H$18:$H$1017,$I$18:$I$1017) -> 0.0064358816 | J10: =COVAR($H$18:$H$1017,$J$18:$J$1017) -> 0.0023051558 | K10: =COVAR($H$18:$H$1017,$K$18:$K$1017) -> 0.024469756 | M10: =B10/$M$4 -> 0.020482061 | N10: =(C10-SUMPRODUCT($M10:M10,$M5:M5))/N5 -> -0.05208262 | O10: =(D10-SUMPRODUCT($M10:N10,$M6:N6))/O6 -> 0.034213397 | P10: =(E10-SUMPRODUCT($M10:O10,$M7:O7))/P7 -> 0.027805729 | Q10: =(F10-SUMPRODUCT($M10:P10,$M8:P8))/Q8 -> -0.0015352074 | R10: =(G10-SUMPRODUCT($M10:Q10,$M9:Q9))/R9 -> -5.2892081e-05 | S10: =SQRT(H10-SUMSQ($M10:R10)) -> 1.0001595 | T10: 0 | U10: 0 | V10: 0 | X10: -0.019889675 | Y10: 0.05159666 | Z10: -0.033214129 | AA10: -0.028124313 | AB10: 0.0015077576 | AC10: 5.2284163e-05 | AD10: 0.99984053 | AE10: 0 | AF10: 0 | AG10: 0 | AI10: =COVAR($AD$18:$AD$1017,$X$18:$X$1017) -> -2.5757174e-17 | AJ10: =COVAR($AD$18:$AD$1017,$Y$18:$Y$1017) -> 4.2382764e-17 | AK10: =COVAR($AD$18:$AD$1017,$Z$18:$Z$1017) -> 2.4202862e-17 | AL10: =COVAR($AD$18:$AD$1017,$AA$18:$AA$1017) -> -6.1450844e-17 | AM10: =COVAR($AD$18:$AD$1017,$AB$18:$AB$1017) -> 2.9976022e-18 | AN10: =COVAR($AD$18:$AD$1017,$AC$18:$AC$1017) -> -1.6653345e-18 | AO10: =COVAR($AD$18:$AD$1017,$AD$18:$AD$1017) -> 1 | AP10: =COVAR($AD$18:$AD$1017,$AE$18:$AE$1017) -> 1.5654145e-17 | AQ10: =COVAR($AD$18:$AD$1017,$AF$18:$AF$1017) -> 1.8873791e-17 | AR10: =COVAR($AD$18:$AD$1017,$AG$18:$AG$1017) -> 6.5225603e-18
B11: =COVAR($I$18:$I$1017,$B$18:$B$1017) -> 0.020295584 | C11: =COVAR($I$18:$I$1017,$C$18:$C$1017) -> 0.088553723 | D11: =COVAR($I$18:$I$1017,$D$18:$D$1017) -> 0.020532999 | E11: =COVAR($I$18:$I$1017,$E$18:$E$1017) -> 0.024922848 | F11: =COVAR($I$18:$I$1017,$F$18:$F$1017) -> -0.010611901 | G11: =COVAR($I$18:$I$1017,$G$18:$G$1017) -> 0.052862551 | H11: =COVAR($I$18:$I$1017,$H$18:$H$1017) -> 0.0064358816 | I11: =COVAR($I$18:$I$1017,$I$18:$I$1017) -> 0.99533869 | J11: =COVAR($I$18:$I$1017,$J$18:$J$1017) -> 0.002067126 | K11: =COVAR($I$18:$I$1017,$K$18:$K$1017) -> -0.01220048 | M11: =B11/$M$4 -> 0.020201904 | N11: =(C11-SUMPRODUCT($M11:M11,$M5:M5))/N5 -> 0.087463595 | O11: =(D11-SUMPRODUCT($M11:N11,$M6:N6))/O6 -> 0.020250285 | P11: =(E11-SUMPRODUCT($M11:O11,$M7:O7))/P7 -> 0.023775476 | Q11: =(F11-SUMPRODUCT($M11:P11,$M8:P8))/Q8 -> -0.013326151 | R11: =(G11-SUMPRODUCT($M11:Q11,$M9:Q9))/R9 -> 0.047509464 | S11: =(H11-SUMPRODUCT($M11:R11,$M10:R10))/S10 -> 0.0092040991 | T11: =SQRT(I11-SUMSQ($M11:S11)) -> 0.99185982 | U11: 0 | V11: 0 | X11: -0.020173671 | Y11: -0.085499082 | Z11: -0.018985942 | AA11: -0.023304003 | AB11: 0.012547426 | AC11: -0.047356876 | AD11: -0.0092781572 | AE11: 1.008207 | AF11: 0 | AG11: 0 | AI11: =COVAR($AE$18:$AE$1017,$X$18:$X$1017) -> 1.7597035e-17 | AJ11: =COVAR($AE$18:$AE$1017,$Y$18:$Y$1017) -> 1.2451151e-16 | AK11: =COVAR($AE$18:$AE$1017,$Z$18:$Z$1017) -> 9.7699626e-18 | AL11: =COVAR($AE$18:$AE$1017,$AA$18:$AA$1017) -> -9.8809849e-17 | AM11: =COVAR($AE$18:$AE$1017,$AB$18:$AB$1017) -> -9.547918e-18 | AN11: =COVAR($AE$18:$AE$1017,$AC$18:$AC$1017) -> -8.3266727e-17 | AO11: =COVAR($AE$18:$AE$1017,$AD$18:$AD$1017) -> 1.5654145e-17 | AP11: =COVAR($AE$18:$AE$1017,$AE$18:$AE$1017) -> 1 | AQ11: =COVAR($AE$18:$AE$1017,$AF$18:$AF$1017) -> -5.1958438e-17 | AR11: =COVAR($AE$18:$AE$1017,$AG$18:$AG$1017) -> -6.6613381e-18
B12: =COVAR($J$18:$J$1017,$B$18:$B$1017) -> -0.010252705 | C12: =COVAR($J$18:$J$1017,$C$18:$C$1017) -> -0.062365207 | D12: =COVAR($J$18:$J$1017,$D$18:$D$1017) -> 0.0060919711 | E12: =COVAR($J$18:$J$1017,$E$18:$E$1017) -> -0.052906483 | F12: =COVAR($J$18:$J$1017,$F$18:$F$1017) -> -0.041997899 | G12: =COVAR($J$18:$J$1017,$G$18:$G$1017) -> -0.060624425 | H12: =COVAR($J$18:$J$1017,$H$18:$H$1017) -> 0.0023051558 | I12: =COVAR($J$18:$J$1017,$I$18:$I$1017) -> 0.002067126 | J12: =COVAR($J$18:$J$1017,$J$18:$J$1017) -> 0.95791619 | K12: =COVAR($J$18:$J$1017,$K$18:$K$1017) -> -0.029365866 | M12: =B12/$M$4 -> -0.010205381 | N12: =(C12-SUMPRODUCT($M12:M12,$M5:M5))/N5 -> -0.061567763 | O12: =(D12-SUMPRODUCT($M12:N12,$M6:N6))/O6 -> 0.0062830676 | P12: =(E12-SUMPRODUCT($M12:O12,$M7:O7))/P7 -> -0.053224855 | Q12: =(F12-SUMPRODUCT($M12:P12,$M8:P8))/Q8 -> -0.038742394 | R12: =(G12-SUMPRODUCT($M12:Q12,$M9:Q9))/R9 -> -0.056777671 | S12: =(H12-SUMPRODUCT($M12:R12,$M10:R10))/S10 -> 0.0005100014 | T12: =(I12-SUMPRODUCT($M12:S12,$M11:S11))/T11 -> 0.011062995 | U12: =SQRT(J12-SUMSQ($M12:T12)) -> 0.97278043 | V12: 0 | X12: 0.0089393784 | Y12: 0.059791866 | Z12: -0.008845791 | AA12: 0.053696168 | AB12: 0.03972659 | AC12: 0.058243284 | AD12: -0.00041867193 | AE12: -0.011465885 | AF12: 1.0279812 | AG12: 0 | AI12: =COVAR($AF$18:$AF$1017,$X$18:$X$1017) -> 3.9135362e-17 | AJ12: =COVAR($AF$18:$AF$1017,$Y$18:$Y$1017) -> 7.6050277e-18 | AK12: =COVAR($AF$18:$AF$1017,$Z$18:$Z$1017) -> 1.9095836e-17 | AL12: =COVAR($AF$18:$AF$1017,$AA$18:$AA$1017) -> 6.2561067e-17 | AM12: =COVAR($AF$18:$AF$1017,$AB$18:$AB$1017) -> -4.773959e-17 | AN12: =COVAR($AF$18:$AF$1017,$AC$18:$AC$1017) -> -2.4646951e-17 | AO12: =COVAR($AF$18:$AF$1017,$AD$18:$AD$1017) -> 1.8873791e-17 | AP12: =COVAR($AF$18:$AF$1017,$AE$18:$AE$1017) -> -5.1958438e-17 | AQ12: =COVAR($AF$18:$AF$1017,$AF$18:$AF$1017) -> 1 | AR12: =COVAR($AF$18:$AF$1017,$AG$18:$AG$1017) -> -3.8774539e-17
B13: =COVAR($K$18:$K$1017,$B$18:$B$1017) -> -0.0234292 | C13: =COVAR($K$18:$K$1017,$C$18:$C$1017) -> 0.016286095 | D13: =COVAR($K$18:$K$1017,$D$18:$D$1017) -> 0.070295138 | E13: =COVAR($K$18:$K$1017,$E$18:$E$1017) -> -0.028253352 | F13: =COVAR($K$18:$K$1017,$F$18:$F$1017) -> 0.045961781 | G13: =COVAR($K$18:$K$1017,$G$18:$G$1017) -> -0.010844416 | H13: =COVAR($K$18:$K$1017,$H$18:$H$1017) -> 0.024469756 | I13: =COVAR($K$18:$K$1017,$I$18:$I$1017) -> -0.01220048 | J13: =COVAR($K$18:$K$1017,$J$18:$J$1017) -> -0.029365866 | K13: =COVAR($K$18:$K$1017,$K$18:$K$1017) -> 1.0111057 | M13: =B13/$M$4 -> -0.023321055 | N13: =(C13-SUMPRODUCT($M13:M13,$M5:M5))/N5 -> 0.015885924 | O13: =(D13-SUMPRODUCT($M13:N13,$M6:N6))/O6 -> 0.070155988 | P13: =(E13-SUMPRODUCT($M13:O13,$M7:O7))/P7 -> -0.030961709 | Q13: =(F13-SUMPRODUCT($M13:P13,$M8:P8))/Q8 -> 0.045398591 | R13: =(G13-SUMPRODUCT($M13:Q13,$M9:Q9))/R9 -> -0.01041332 | S13: =(H13-SUMPRODUCT($M13:R13,$M10:R10))/S10 -> 0.024300708 | T13: =(I13-SUMPRODUCT($M13:S13,$M11:S11))/T11 -> -0.01303338 | U13: =(J13-SUMPRODUCT($M13:T13,$M12:T12))/U12 -> -0.030238202 | V13: =SQRT(K13-SUMSQ($M13:U13)) -> 1.0002924 | X13: 0.024134384 | Y13: -0.015665444 | Z13: -0.070661259 | AA13: 0.033948447 | AB13: -0.043095705 | AC13: 0.011434614 | AD13: -0.024423278 | AE13: 0.012789898 | AF13: 0.031075219 | AG13: 0.99970772 | AI13: =COVAR($AG$18:$AG$1017,$X$18:$X$1017) -> 4.2327253e-19 | AJ13: =COVAR($AG$18:$AG$1017,$Y$18:$Y$1017) -> 3.2925052e-17 | AK13: =COVAR($AG$18:$AG$1017,$Z$18:$Z$1017) -> 6.0562666e-17 | AL13: =COVAR($AG$18:$AG$1017,$AA$18:$AA$1017) -> 8.1254448e-17 | AM13: =COVAR($AG$18:$AG$1017,$AB$18:$AB$1017) -> -3.494427e-17 | AN13: =COVAR($AG$18:$AG$1017,$AC$18:$AC$1017) -> -1.8735014e-17 | AO13: =COVAR($AG$18:$AG$1017,$AD$18:$AD$1017) -> 6.5225603e-18 | AP13: =COVAR($AG$18:$AG$1017,$AE$18:$AE$1017) -> -6.6613381e-18 | AQ13: =COVAR($AG$18:$AG$1017,$AF$18:$AF$1017) -> -3.8774539e-17 | AR13: =COVAR($AG$18:$AG$1017,$AG$18:$AG$1017) -> 1
A15: Mean | B15: =AVERAGE($B$18:$B$1017) -> 0.017697198 | C15: =AVERAGE($C$18:$C$1017) -> -0.0060295035 | D15: =AVERAGE($D$18:$D$1017) -> 0.033038951 | E15: =AVERAGE($E$18:$E$1017) -> -0.067234436 | F15: =AVERAGE($F$18:$F$1017) -> -0.017214866 | G15: =AVERAGE($G$18:$G$1017) -> -0.037462411 | H15: =AVERAGE($H$18:$H$1017) -> -0.012345434 | I15: =AVERAGE($I$18:$I$1017) -> 0.03057344 | J15: =AVERAGE($J$18:$J$1017) -> -0.013934566 | K15: =AVERAGE($K$18:$K$1017) -> -0.010130081 | M15: =AVERAGE($M$18:$M$1017) -> 3.6248782e-17 | N15: =AVERAGE($N$18:$N$1017) -> -2.2759572e-17 | O15: =AVERAGE($O$18:$O$1017) -> -3.2418512e-17 | P15: =AVERAGE($P$18:$P$1017) -> 8.2156504e-18 | Q15: =AVERAGE($Q$18:$Q$1017) -> 0 | R15: =AVERAGE($R$18:$R$1017) -> -3.3084646e-17 | S15: =AVERAGE($S$18:$S$1017) -> 1.6431301e-17 | T15: =AVERAGE($T$18:$T$1017) -> -2.6645353e-17 | U15: =AVERAGE($U$18:$U$1017) -> -6.5725203e-17 | V15: =AVERAGE($V$18:$V$1017) -> 3.0253577e-17 | X15: =AVERAGE($X$18:$X$1017) -> 3.9190873e-17 | Y15: =AVERAGE($Y$18:$Y$1017) -> -6.8278716e-18 | Z15: =AVERAGE($Z$18:$Z$1017) -> 4.8849813e-18 | AA15: =AVERAGE($AA$18:$AA$1017) -> -2.220446e-18 | AB15: =AVERAGE($AB$18:$AB$1017) -> -1.6653345e-17 | AC15: =AVERAGE($AC$18:$AC$1017) -> -4.3520743e-17 | AD15: =AVERAGE($AD$18:$AD$1017) -> 1.8873791e-17 | AE15: =AVERAGE($AE$18:$AE$1017) -> -2.6201263e-17 | AF15: =AVERAGE($AF$18:$AF$1017) -> -5.7731597e-17 | AG15: =AVERAGE($AG$18:$AG$1017) -> 1.1518564e-17
B16: Initial random normals | M16: De-meaned (initial number minus its column mean) | X16: Moment matched = de-meaned x inverse of L (the numbers the model uses)
A17: Case | B17: Bond 1 | C17: Bond 2 | D17: Bond 3 | E17: Bond 4 | F17: Bond 5 | G17: Bond 6 | H17: Bond 7 | I17: Bond 8 | J17: Bond 9 | K17: Bond 10 | M17: Bond 1 | N17: Bond 2 | O17: Bond 3 | P17: Bond 4 | Q17: Bond 5 | R17: Bond 6 | S17: Bond 7 | T17: Bond 8 | U17: Bond 9 | V17: Bond 10 | X17: Bond 1 | Y17: Bond 2 | Z17: Bond 3 | AA17: Bond 4 | AB17: Bond 5 | AC17: Bond 6 | AD17: Bond 7 | AE17: Bond 8 | AF17: Bond 9 | AG17: Bond 10
A18: 1 | B18: -0.38920512 | C18: 1.1578214 | D18: 0.094403827 | E18: 0.34719004 | F18: 1.1101905 | G18: 0.65847745 | H18: 1.0467667 | I18: -0.47334846 | J18: -0.65241813 | K18: -0.11150449 | M18: =B18-B$15 -> -0.40690232 | N18: =C18-C$15 -> 1.1638509 | O18: =D18-D$15 -> 0.061364877 | P18: =E18-E$15 -> 0.41442448 | Q18: =F18-F$15 -> 1.1274054 | R18: =G18-G$15 -> 0.69593986 | S18: =H18-H$15 -> 1.0591121 | T18: =I18-I$15 -> -0.5039219 | ... V18: =K18-K$15 -> -0.10137441 | X18: =SUMPRODUCT($M18:$V18,$X$4:$AG$4) -> -0.40502414 | Y18: =SUMPRODUCT($M18:$V18,$X$5:$AG$5) -> 1.1445711 | Z18: =SUMPRODUCT($M18:$V18,$X$6:$AG$6) -> 0.056767703 | AA18: =SUMPRODUCT($M18:$V18,$X$7:$AG$7) -> 0.41245837 | AB18: =SUMPRODUCT($M18:$V18,$X$8:$AG$8) -> 1.0839038 | AC18: =SUMPRODUCT($M18:$V18,$X$9:$AG$9) -> 0.65238549 | AD18: =SUMPRODUCT($M18:$V18,$X$10:$AG$10) -> 1.1151299 | AE18: =SUMPRODUCT($M18:$V18,$X$11:$AG$11) -> -0.63881799 | AF18: =SUMPRODUCT($M18:$V18,$X$12:$AG$12) -> -0.47803127 | AG18: =SUMPRODUCT($M18:$V18,$X$13:$AG$13) -> -0.21244605
A19: 2 | B19: -0.74367182 | C19: 1.2128351 | D19: -0.52110702 | E19: 0.86518459 | F19: 0.49348088 | G19: 0.54080648 | H19: 0.11461121 | I19: 0.80470891 | J19: 0.65395696 | K19: 0.21914285 | M19: =B19-B$15 -> -0.76136902 | N19: =C19-C$15 -> 1.2188647 | O19: =D19-D$15 -> -0.55414597 | P19: =E19-E$15 -> 0.93241903 | Q19: =F19-F$15 -> 0.51069575 | R19: =G19-G$15 -> 0.57826889 | S19: =H19-H$15 -> 0.12695665 | T19: =I19-I$15 -> 0.77413547 | ... V19: =K19-K$15 -> 0.22927293 | X19: =SUMPRODUCT($M19:$V19,$X$4:$AG$4) -> -0.75785471 | Y19: =SUMPRODUCT($M19:$V19,$X$5:$AG$5) -> 1.196209 | Z19: =SUMPRODUCT($M19:$V19,$X$6:$AG$6) -> -0.55904459 | AA19: =SUMPRODUCT($M19:$V19,$X$7:$AG$7) -> 0.95983618 | AB19: =SUMPRODUCT($M19:$V19,$X$8:$AG$8) -> 0.47962541 | AC19: =SUMPRODUCT($M19:$V19,$X$9:$AG$9) -> 0.52569921 | AD19: =SUMPRODUCT($M19:$V19,$X$10:$AG$10) -> 0.1979512 | AE19: =SUMPRODUCT($M19:$V19,$X$11:$AG$11) -> 0.65827346 | AF19: =SUMPRODUCT($M19:$V19,$X$12:$AG$12) -> 0.85266033 | AG19: =SUMPRODUCT($M19:$V19,$X$13:$AG$13) -> 0.2747063
A20: 3 | B20: 1.0929463 | C20: -1.0385714 | D20: 0.38965042 | E20: -0.49165919 | F20: -0.70360164 | G20: -0.18083038 | H20: -0.79099469 | I20: 0.12244058 | J20: -0.21931383 | K20: -0.47094783 | M20: =B20-B$15 -> 1.0752491 | N20: =C20-C$15 -> -1.0325419 | O20: =D20-D$15 -> 0.35661147 | P20: =E20-E$15 -> -0.42442475 | Q20: =F20-F$15 -> -0.68638677 | R20: =G20-G$15 -> -0.14336797 | S20: =H20-H$15 -> -0.77864926 | T20: =I20-I$15 -> 0.091867136 | ... V20: =K20-K$15 -> -0.46081775 | X20: =SUMPRODUCT($M20:$V20,$X$4:$AG$4) -> 1.070286 | Y20: =SUMPRODUCT($M20:$V20,$X$5:$AG$5) -> -1.0101864 | Z20: =SUMPRODUCT($M20:$V20,$X$6:$AG$6) -> 0.36149375 | AA20: =SUMPRODUCT($M20:$V20,$X$7:$AG$7) -> -0.44291545 | AB20: =SUMPRODUCT($M20:$V20,$X$8:$AG$8) -> -0.67155261 | AC20: =SUMPRODUCT($M20:$V20,$X$9:$AG$9) -> -0.1188119 | AD20: =SUMPRODUCT($M20:$V20,$X$10:$AG$10) -> -0.85413744 | AE20: =SUMPRODUCT($M20:$V20,$X$11:$AG$11) -> 0.16773245 | AF20: =SUMPRODUCT($M20:$V20,$X$12:$AG$12) -> -0.32554143 | AG20: =SUMPRODUCT($M20:$V20,$X$13:$AG$13) -> -0.41641364
A21: 4 | B21: -0.43419587 | C21: 1.9155 | D21: -0.9390708 | E21: -0.40533839 | F21: -0.050325829 | G21: 1.3117309 | H21: -0.8812356 | I21: -1.6061502 | J21: -0.91029713 | K21: -1.0652618 | M21: =B21-B$15 -> -0.45189307 | N21: =C21-C$15 -> 1.9215296 | O21: =D21-D$15 -> -0.97210975 | P21: =E21-E$15 -> -0.33810395 | Q21: =F21-F$15 -> -0.033110963 | R21: =G21-G$15 -> 1.3491933 | S21: =H21-H$15 -> -0.86889016 | T21: =I21-I$15 -> -1.6367237 | ... V21: =K21-K$15 -> -1.0551317 | X21: =SUMPRODUCT($M21:$V21,$X$4:$AG$4) -> -0.44980723 | Y21: =SUMPRODUCT($M21:$V21,$X$5:$AG$5) -> 1.8913151 | Z21: =SUMPRODUCT($M21:$V21,$X$6:$AG$6) -> -0.97862565 | AA21: =SUMPRODUCT($M21:$V21,$X$7:$AG$7) -> -0.31582361 | AB21: =SUMPRODUCT($M21:$V21,$X$8:$AG$8) -> -0.048893034 | AC21: =SUMPRODUCT($M21:$V21,$X$9:$AG$9) -> 1.2741505 | AD21: =SUMPRODUCT($M21:$V21,$X$10:$AG$10) -> -0.71880175 | AE21: =SUMPRODUCT($M21:$V21,$X$11:$AG$11) -> -1.8352407 | AF21: =SUMPRODUCT($M21:$V21,$X$12:$AG$12) -> -0.72375115 | AG21: =SUMPRODUCT($M21:$V21,$X$13:$AG$13) -> -1.0493313
A22: 5 | B22: -1.8599871 | C22: 0.75061757 | D22: 0.2224588 | E22: -0.78341897 | F22: -1.5263177 | G22: -0.78531154 | H22: -0.83463465 | I22: -0.079703706 | J22: -0.83237702 | K22: 0.28584576 | M22: =B22-B$15 -> -1.8776843 | N22: =C22-C$15 -> 0.75664707 | O22: =D22-D$15 -> 0.18941985 | P22: =E22-E$15 -> -0.71618453 | Q22: =F22-F$15 -> -1.5091029 | R22: =G22-G$15 -> -0.74784913 | S22: =H22-H$15 -> -0.82228921 | T22: =I22-I$15 -> -0.11027715 | ... V22: =K22-K$15 -> 0.29597584 | X22: =SUMPRODUCT($M22:$V22,$X$4:$AG$4) -> -1.8690173 | Y22: =SUMPRODUCT($M22:$V22,$X$5:$AG$5) -> 0.73225356 | Z22: =SUMPRODUCT($M22:$V22,$X$6:$AG$6) -> 0.18387329 | AA22: =SUMPRODUCT($M22:$V22,$X$7:$AG$7) -> -0.72151866 | AB22: =SUMPRODUCT($M22:$V22,$X$8:$AG$8) -> -1.4417872 | AC22: =SUMPRODUCT($M22:$V22,$X$9:$AG$9) -> -0.74971084 | AD22: =SUMPRODUCT($M22:$V22,$X$10:$AG$10) -> -0.73423477 | AE22: =SUMPRODUCT($M22:$V22,$X$11:$AG$11) -> -0.10079161 | AF22: =SUMPRODUCT($M22:$V22,$X$12:$AG$12) -> -0.95491939 | AG22: =SUMPRODUCT($M22:$V22,$X$13:$AG$13) -> 0.25074514
A23: 6 | B23: -0.98899926 | C23: 0.84004433 | D23: -0.01239904 | E23: -0.22507499 | F23: -0.527264 | G23: 1.5757522 | H23: 2.1505611 | I23: -1.1115642 | J23: -0.28865514 | K23: -1.1891091 | M23: =B23-B$15 -> -1.0066965 | N23: =C23-C$15 -> 0.84607383 | O23: =D23-D$15 -> -0.045437991 | P23: =E23-E$15 -> -0.15784055 | Q23: =F23-F$15 -> -0.51004913 | R23: =G23-G$15 -> 1.6132146 | S23: =H23-H$15 -> 2.1629065 | T23: =I23-I$15 -> -1.1421376 | ... V23: =K23-K$15 -> -1.1789791 | X23: =SUMPRODUCT($M23:$V23,$X$4:$AG$4) -> -1.0020498 | Y23: =SUMPRODUCT($M23:$V23,$X$5:$AG$5) -> 0.82683195 | Z23: =SUMPRODUCT($M23:$V23,$X$6:$AG$6) -> -0.049799734 | AA23: =SUMPRODUCT($M23:$V23,$X$7:$AG$7) -> -0.15581616 | AB23: =SUMPRODUCT($M23:$V23,$X$8:$AG$8) -> -0.49182451 | AC23: =SUMPRODUCT($M23:$V23,$X$9:$AG$9) -> 1.5717889 | AD23: =SUMPRODUCT($M23:$V23,$X$10:$AG$10) -> 2.2315027 | AE23: =SUMPRODUCT($M23:$V23,$X$11:$AG$11) -> -1.3018643 | AF23: =SUMPRODUCT($M23:$V23,$X$12:$AG$12) -> -0.16300552 | AG23: =SUMPRODUCT($M23:$V23,$X$13:$AG$13) -> -1.253875
A24: 7 | B24: 0.1824142 | C24: 2.5256254 | D24: 2.4366612 | E24: 0.065815591 | F24: 0.04363933 | G24: -0.97949866 | H24: -1.165684 | I24: 0.27741593 | J24: 0.57217075 | K24: 0.63146098 | M24: =B24-B$15 -> 0.164717 | N24: =C24-C$15 -> 2.5316549 | O24: =D24-D$15 -> 2.4036222 | P24: =E24-E$15 -> 0.13305003 | Q24: =F24-F$15 -> 0.060854197 | R24: =G24-G$15 -> -0.94203625 | S24: =H24-H$15 -> -1.1533386 | T24: =I24-I$15 -> 0.24684249 | ... V24: =K24-K$15 -> 0.64159106 | X24: =SUMPRODUCT($M24:$V24,$X$4:$AG$4) -> 0.1639567 | Y24: =SUMPRODUCT($M24:$V24,$X$5:$AG$5) -> 2.4974347 | Z24: =SUMPRODUCT($M24:$V24,$X$6:$AG$6) -> 2.3936561 | AA24: =SUMPRODUCT($M24:$V24,$X$7:$AG$7) -> 0.033041725 | AB24: =SUMPRODUCT($M24:$V24,$X$8:$AG$8) -> -0.014871917 | AC24: =SUMPRODUCT($M24:$V24,$X$9:$AG$9) -> -1.058425 | AD24: =SUMPRODUCT($M24:$V24,$X$10:$AG$10) -> -1.1093395 | AE24: =SUMPRODUCT($M24:$V24,$X$11:$AG$11) -> 0.03643189 | AF24: =SUMPRODUCT($M24:$V24,$X$12:$AG$12) -> 0.68643528 | AG24: =SUMPRODUCT($M24:$V24,$X$13:$AG$13) -> 0.47653762
A25: 8 | B25: 0.0012540824 | C25: 0.54616113 | D25: -1.2245455 | E25: -0.87999384 | F25: -0.6068162 | G25: 1.4799411 | H25: -0.36687766 | I25: -0.40923304 | J25: 0.83344716 | K25: -0.51006943 | M25: =B25-B$15 -> -0.016443116 | N25: =C25-C$15 -> 0.55219064 | O25: =D25-D$15 -> -1.2575845 | P25: =E25-E$15 -> -0.8127594 | Q25: =F25-F$15 -> -0.58960133 | R25: =G25-G$15 -> 1.5174035 | S25: =H25-H$15 -> -0.35453223 | T25: =I25-I$15 -> -0.43980648 | ... V25: =K25-K$15 -> -0.49993935 | X25: =SUMPRODUCT($M25:$V25,$X$4:$AG$4) -> -0.016367218 | Y25: =SUMPRODUCT($M25:$V25,$X$5:$AG$5) -> 0.5443417 | Z25: =SUMPRODUCT($M25:$V25,$X$6:$AG$6) -> -1.2586105 | AA25: =SUMPRODUCT($M25:$V25,$X$7:$AG$7) -> -0.78019372 | AB25: =SUMPRODUCT($M25:$V25,$X$8:$AG$8) -> -0.56602856 | AC25: =SUMPRODUCT($M25:$V25,$X$9:$AG$9) -> 1.4945227 | AD25: =SUMPRODUCT($M25:$V25,$X$10:$AG$10) -> -0.26183922 | AE25: =SUMPRODUCT($M25:$V25,$X$11:$AG$11) -> -0.52344713 | AF25: =SUMPRODUCT($M25:$V25,$X$12:$AG$12) -> 0.94159118 | AG25: =SUMPRODUCT($M25:$V25,$X$13:$AG$13) -> -0.37544326
A26: 9 | B26: -0.17451781 | C26: -0.9252292 | D26: 1.0322113 | E26: -0.24317831 | F26: 0.64296192 | G26: -0.084316859 | H26: -0.4738307 | I26: -0.16114309 | J26: -1.256032 | K26: 1.5574843 | M26: =B26-B$15 -> -0.192215 | N26: =C26-C$15 -> -0.91919969 | O26: =D26-D$15 -> 0.99917237 | P26: =E26-E$15 -> -0.17594387 | Q26: =F26-F$15 -> 0.66017679 | R26: =G26-G$15 -> -0.046854448 | S26: =H26-H$15 -> -0.46148526 | T26: =I26-I$15 -> -0.19171653 | ... V26: =K26-K$15 -> 1.5676143 | X26: =SUMPRODUCT($M26:$V26,$X$4:$AG$4) -> -0.19132778 | Y26: =SUMPRODUCT($M26:$V26,$X$5:$AG$5) -> -0.90774834 | Z26: =SUMPRODUCT($M26:$V26,$X$6:$AG$6) -> 1.0013 | AA26: =SUMPRODUCT($M26:$V26,$X$7:$AG$7) -> -0.20606694 | AB26: =SUMPRODUCT($M26:$V26,$X$8:$AG$8) -> 0.66827445 | AC26: =SUMPRODUCT($M26:$V26,$X$9:$AG$9) -> -0.00051651458 | AD26: =SUMPRODUCT($M26:$V26,$X$10:$AG$10) -> -0.53226161 | AE26: =SUMPRODUCT($M26:$V26,$X$11:$AG$11) -> -0.11090743 | AF26: =SUMPRODUCT($M26:$V26,$X$12:$AG$12) -> -1.3259287 | AG26: =SUMPRODUCT($M26:$V26,$X$13:$AG$13) -> 1.441575
A27: 10 | B27: 1.2427491 | C27: -1.2554048 | D27: 1.0855786 | E27: -0.9129 | F27: 0.026784291 | G27: 1.6927249 | H27: 1.8710602 | I27: 0.20541021 | J27: 1.0689602 | K27: 0.63146848 | M27: =B27-B$15 -> 1.2250519 | N27: =C27-C$15 -> -1.2493753 | O27: =D27-D$15 -> 1.0525397 | P27: =E27-E$15 -> -0.84566556 | Q27: =F27-F$15 -> 0.043999157 | R27: =G27-G$15 -> 1.7301874 | S27: =H27-H$15 -> 1.8834057 | T27: =I27-I$15 -> 0.17483677 | ... V27: =K27-K$15 -> 0.64159856 | X27: =SUMPRODUCT($M27:$V27,$X$4:$AG$4) -> 1.2193973 | Y27: =SUMPRODUCT($M27:$V27,$X$5:$AG$5) -> -1.2228838 | Z27: =SUMPRODUCT($M27:$V27,$X$6:$AG$6) -> 1.0579038 | AA27: =SUMPRODUCT($M27:$V27,$X$7:$AG$7) -> -0.89290084 | AB27: =SUMPRODUCT($M27:$V27,$X$8:$AG$8) -> 0.049995573 | AC27: =SUMPRODUCT($M27:$V27,$X$9:$AG$9) -> 1.7527553 | AD27: =SUMPRODUCT($M27:$V27,$X$10:$AG$10) -> 1.7832572 | AE27: =SUMPRODUCT($M27:$V27,$X$11:$AG$11) -> 0.15924351 | AF27: =SUMPRODUCT($M27:$V27,$X$12:$AG$12) -> 1.0944512 | AG27: =SUMPRODUCT($M27:$V27,$X$13:$AG$13) -> 0.59524236
A28: 11 | B28: -0.36636517 | C28: 0.63780897 | D28: 0.8268662 | E28: -0.27723605 | F28: 1.0565535 | G28: 2.2067925 | H28: -0.63085567 | I28: 0.30583377 | J28: -0.90104999 | K28: 0.1716398 | M28: =B28-B$15 -> -0.38406236 | N28: =C28-C$15 -> 0.64383847 | O28: =D28-D$15 -> 0.79382724 | P28: =E28-E$15 -> -0.21000161 | Q28: =F28-F$15 -> 1.0737683 | R28: =G28-G$15 -> 2.2442549 | S28: =H28-H$15 -> -0.61851023 | T28: =I28-I$15 -> 0.27526033 | ... V28: =K28-K$15 -> 0.18176988 | X28: =SUMPRODUCT($M28:$V28,$X$4:$AG$4) -> -0.38228961 | Y28: =SUMPRODUCT($M28:$V28,$X$5:$AG$5) -> 0.6320043 | Z28: =SUMPRODUCT($M28:$V28,$X$6:$AG$6) -> 0.79051875 | AA28: =SUMPRODUCT($M28:$V28,$X$7:$AG$7) -> -0.24138098 | AB28: =SUMPRODUCT($M28:$V28,$X$8:$AG$8) -> 1.0484892 | AC28: =SUMPRODUCT($M28:$V28,$X$9:$AG$9) -> 2.2102286 | AD28: =SUMPRODUCT($M28:$V28,$X$10:$AG$10) -> -0.59627662 | AE28: =SUMPRODUCT($M28:$V28,$X$11:$AG$11) -> 0.13297282 | AF28: =SUMPRODUCT($M28:$V28,$X$12:$AG$12) -> -0.7247005 | AG28: =SUMPRODUCT($M28:$V28,$X$13:$AG$13) -> 0.069586249
A29: 12 | B29: 0.99133786 | C29: 0.52432613 | D29: -0.57589875 | E29: -0.20999668 | F29: 1.550588 | G29: 1.2715391 | H29: 0.030732581 | I29: -1.014409 | J29: -0.49343134 | K29: -2.088819 | M29: =B29-B$15 -> 0.97364066 | N29: =C29-C$15 -> 0.53035563 | O29: =D29-D$15 -> -0.60893771 | P29: =E29-E$15 -> -0.14276224 | Q29: =F29-F$15 -> 1.5678028 | R29: =G29-G$15 -> 1.3090015 | S29: =H29-H$15 -> 0.043078015 | T29: =I29-I$15 -> -1.0449825 | ... V29: =K29-K$15 -> -2.0786889 | X29: =SUMPRODUCT($M29:$V29,$X$4:$AG$4) -> 0.96914654 | Y29: =SUMPRODUCT($M29:$V29,$X$5:$AG$5) -> 0.530091 | Z29: =SUMPRODUCT($M29:$V29,$X$6:$AG$6) -> -0.60883005 | AA29: =SUMPRODUCT($M29:$V29,$X$7:$AG$7) -> -0.13301192 | AB29: =SUMPRODUCT($M29:$V29,$X$8:$AG$8) -> 1.5127772 | AC29: =SUMPRODUCT($M29:$V29,$X$9:$AG$9) -> 1.2850952 | AD29: =SUMPRODUCT($M29:$V29,$X$10:$AG$10) -> 0.07774306 | AE29: =SUMPRODUCT($M29:$V29,$X$11:$AG$11) -> -1.1463753 | AF29: =SUMPRODUCT($M29:$V29,$X$12:$AG$12) -> -0.30429061 | AG29: =SUMPRODUCT($M29:$V29,$X$13:$AG$13) -> -2.106625
... A1017: 1000 | B1017: 0.39926353 | C1017: -0.3266436 | D1017: 2.2687587 | E1017: 0.5367822 | F1017: 1.431834 | G1017: -1.6368896 | H1017: 0.67420774 | I1017: -1.0191729 | J1017: 0.6192838 | K1017: 0.32254801 | M1017: =B1017-B$15 -> 0.38156633 | N1017: =C1017-C$15 -> -0.3206141 | O1017: =D1017-D$15 -> 2.2357198 | P1017: =E1017-E$15 -> 0.60401663 | Q1017: =F1017-F$15 -> 1.4490489 | R1017: =G1017-G$15 -> -1.5994272 | S1017: =H1017-H$15 -> 0.68655317 | T1017: =I1017-I$15 -> -1.0497463 | ... V1017: =K1017-K$15 -> 0.33267809 | X1017: =SUMPRODUCT($M1017:$V1017,$X$4:$AG$4) -> 0.3798051 | Y1017: =SUMPRODUCT($M1017:$V1017,$X$5:$AG$5) -> -0.31332189 | Z1017: =SUMPRODUCT($M1017:$V1017,$X$6:$AG$6) -> 2.2358446 | AA1017: =SUMPRODUCT($M1017:$V1017,$X$7:$AG$7) -> 0.53070759 | AB1017: =SUMPRODUCT($M1017:$V1017,$X$8:$AG$8) -> 1.3941537 | AC1017: =SUMPRODUCT($M1017:$V1017,$X$9:$AG$9) -> -1.5827092 | AD1017: =SUMPRODUCT($M1017:$V1017,$X$10:$AG$10) -> 0.57316799 | AE1017: =SUMPRODUCT($M1017:$V1017,$X$11:$AG$11) -> -1.0076144 | AF1017: =SUMPRODUCT($M1017:$V1017,$X$12:$AG$12) -> 0.62399281 | AG1017: =SUMPRODUCT($M1017:$V1017,$X$13:$AG$13) -> 0.11808569

Sheet Defaults
A1: Correlated default times
A2: Cholesky factor L of the 10 x 10 matrix with 1 on the diagonal and rho elsewhere. Each case: x = L m, with m the moment-matched numbers from the Random sheet, u = N(x), t = ln(1 - u) / ln(1 - pi) in years, default quarter = roundup(4 t); 21 means no default.
A3: L | B3: col 1 | C3: col 2 | D3: col 3 | E3: col 4 | F3: col 5 | G3: col 6 | H3: col 7 | I3: col 8 | J3: col 9 | K3: col 10
A4: Bond 1 | B4: 1 | C4: 0 | D4: 0 | E4: 0 | F4: 0 | G4: 0 | H4: 0 | I4: 0 | J4: 0 | K4: 0
A5: Bond 2 | B5: =rho/$B$4 -> 0.2 | C5: =SQRT(1-SUMSQ($B5:B5)) -> 0.9797959 | D5: 0 | E5: 0 | F5: 0 | G5: 0 | H5: 0 | I5: 0 | J5: 0 | K5: 0
A6: Bond 3 | B6: =rho/$B$4 -> 0.2 | C6: =(rho-SUMPRODUCT($B6:B6,$B5:B5))/C5 -> 0.16329932 | D6: =SQRT(1-SUMSQ($B6:C6)) -> 0.96609178 | E6: 0 | F6: 0 | G6: 0 | H6: 0 | I6: 0 | J6: 0 | K6: 0
A7: Bond 4 | B7: =rho/$B$4 -> 0.2 | C7: =(rho-SUMPRODUCT($B7:B7,$B5:B5))/C5 -> 0.16329932 | D7: =(rho-SUMPRODUCT($B7:C7,$B6:C6))/D6 -> 0.13801311 | E7: =SQRT(1-SUMSQ($B7:D7)) -> 0.95618289 | F7: 0 | G7: 0 | H7: 0 | I7: 0 | J7: 0 | K7: 0
A8: Bond 5 | B8: =rho/$B$4 -> 0.2 | C8: =(rho-SUMPRODUCT($B8:B8,$B5:B5))/C5 -> 0.16329932 | D8: =(rho-SUMPRODUCT($B8:C8,$B6:C6))/D6 -> 0.13801311 | E8: =(rho-SUMPRODUCT($B8:D8,$B7:D7))/E7 -> 0.11952286 | F8: =SQRT(1-SUMSQ($B8:E8)) -> 0.9486833 | G8: 0 | H8: 0 | I8: 0 | J8: 0 | K8: 0
A9: Bond 6 | B9: =rho/$B$4 -> 0.2 | C9: =(rho-SUMPRODUCT($B9:B9,$B5:B5))/C5 -> 0.16329932 | D9: =(rho-SUMPRODUCT($B9:C9,$B6:C6))/D6 -> 0.13801311 | E9: =(rho-SUMPRODUCT($B9:D9,$B7:D7))/E7 -> 0.11952286 | F9: =(rho-SUMPRODUCT($B9:E9,$B8:E8))/F8 -> 0.10540926 | G9: =SQRT(1-SUMSQ($B9:F9)) -> 0.94280904 | H9: 0 | I9: 0 | J9: 0 | K9: 0
A10: Bond 7 | B10: =rho/$B$4 -> 0.2 | C10: =(rho-SUMPRODUCT($B10:B10,$B5:B5))/C5 -> 0.16329932 | D10: =(rho-SUMPRODUCT($B10:C10,$B6:C6))/D6 -> 0.13801311 | E10: =(rho-SUMPRODUCT($B10:D10,$B7:D7))/E7 -> 0.11952286 | F10: =(rho-SUMPRODUCT($B10:E10,$B8:E8))/F8 -> 0.10540926 | G10: =(rho-SUMPRODUCT($B10:F10,$B9:F9))/G9 -> 0.094280904 | H10: =SQRT(1-SUMSQ($B10:G10)) -> 0.93808315 | I10: 0 | J10: 0 | K10: 0
A11: Bond 8 | B11: =rho/$B$4 -> 0.2 | C11: =(rho-SUMPRODUCT($B11:B11,$B5:B5))/C5 -> 0.16329932 | D11: =(rho-SUMPRODUCT($B11:C11,$B6:C6))/D6 -> 0.13801311 | E11: =(rho-SUMPRODUCT($B11:D11,$B7:D7))/E7 -> 0.11952286 | F11: =(rho-SUMPRODUCT($B11:E11,$B8:E8))/F8 -> 0.10540926 | G11: =(rho-SUMPRODUCT($B11:F11,$B9:F9))/G9 -> 0.094280904 | H11: =(rho-SUMPRODUCT($B11:G11,$B10:G10))/H10 -> 0.085280287 | I11: =SQRT(1-SUMSQ($B11:H11)) -> 0.93419873 | J11: 0 | K11: 0
A12: Bond 9 | B12: =rho/$B$4 -> 0.2 | C12: =(rho-SUMPRODUCT($B12:B12,$B5:B5))/C5 -> 0.16329932 | D12: =(rho-SUMPRODUCT($B12:C12,$B6:C6))/D6 -> 0.13801311 | E12: =(rho-SUMPRODUCT($B12:D12,$B7:D7))/E7 -> 0.11952286 | F12: =(rho-SUMPRODUCT($B12:E12,$B8:E8))/F8 -> 0.10540926 | G12: =(rho-SUMPRODUCT($B12:F12,$B9:F9))/G9 -> 0.094280904 | H12: =(rho-SUMPRODUCT($B12:G12,$B10:G10))/H10 -> 0.085280287 | I12: =(rho-SUMPRODUCT($B12:H12,$B11:H11))/I11 -> 0.077849894 | J12: =SQRT(1-SUMSQ($B12:I12)) -> 0.93094934 | K12: 0
A13: Bond 10 | B13: =rho/$B$4 -> 0.2 | C13: =(rho-SUMPRODUCT($B13:B13,$B5:B5))/C5 -> 0.16329932 | D13: =(rho-SUMPRODUCT($B13:C13,$B6:C6))/D6 -> 0.13801311 | E13: =(rho-SUMPRODUCT($B13:D13,$B7:D7))/E7 -> 0.11952286 | F13: =(rho-SUMPRODUCT($B13:E13,$B8:E8))/F8 -> 0.10540926 | G13: =(rho-SUMPRODUCT($B13:F13,$B9:F9))/G9 -> 0.094280904 | H13: =(rho-SUMPRODUCT($B13:G13,$B10:G10))/H10 -> 0.085280287 | I13: =(rho-SUMPRODUCT($B13:H13,$B11:H11))/I11 -> 0.077849894 | J13: =(rho-SUMPRODUCT($B13:I13,$B12:I12))/J12 -> 0.071611487 | K13: =SQRT(1-SUMSQ($B13:J13)) -> 0.92819096
B16: Correlated normal x | M16: Uniform u = N(x) | X16: Default time t (years) | AI16: Default quarter (21 = none)
A17: Case | B17: Bond 1 | C17: Bond 2 | D17: Bond 3 | E17: Bond 4 | F17: Bond 5 | G17: Bond 6 | H17: Bond 7 | I17: Bond 8 | J17: Bond 9 | K17: Bond 10 | M17: Bond 1 | N17: Bond 2 | O17: Bond 3 | P17: Bond 4 | Q17: Bond 5 | R17: Bond 6 | S17: Bond 7 | T17: Bond 8 | U17: Bond 9 | V17: Bond 10 | X17: Bond 1 | Y17: Bond 2 | Z17: Bond 3 | AA17: Bond 4 | AB17: Bond 5 | AC17: Bond 6 | AD17: Bond 7 | AE17: Bond 8 | AF17: Bond 9 | AG17: Bond 10 | AI17: Bond 1 | AJ17: Bond 2 | AK17: Bond 3 | AL17: Bond 4 | AM17: Bond 5 | AN17: Bond 6 | AO17: Bond 7 | AP17: Bond 8 | AQ17: Bond 9 | AR17: Bond 10 | AT17: Defaults in 5 years
A18: 1 | B18: =SUMPRODUCT(Random!$X18:$AG18,$B$4:$K$4) -> -0.40502414 | C18: =SUMPRODUCT(Random!$X18:$AG18,$B$5:$K$5) -> 1.0404413 | D18: =SUMPRODUCT(Random!$X18:$AG18,$B$6:$K$6) -> 0.16074566 | E18: =SUMPRODUCT(Random!$X18:$AG18,$B$7:$K$7) -> 0.50812318 | F18: =SUMPRODUCT(Random!$X18:$AG18,$B$8:$K$8) -> 1.1913172 | G18: =SUMPRODUCT(Random!$X18:$AG18,$B$9:$K$9) -> 0.89236417 | H18: =SUMPRODUCT(Random!$X18:$AG18,$B$10:$K$10) -> 1.3848813 | I18: =SUMPRODUCT(Random!$X18:$AG18,$B$11:$K$11) -> -0.16288763 | J18: =SUMPRODUCT(Random!$X18:$AG18,$B$12:$K$12) -> -0.060859482 | K18: =SUMPRODUCT(Random!$X18:$AG18,$B$13:$K$13) -> 0.15274037 | M18: =NORMSDIST(B18) -> 0.34272988 | N18: =NORMSDIST(C18) -> 0.85093253 | O18: =NORMSDIST(D18) -> 0.56385314 | P18: =NORMSDIST(E18) -> 0.69431652 | Q18: =NORMSDIST(F18) -> 0.88323545 | R18: =NORMSDIST(G18) -> 0.81390112 | S18: =NORMSDIST(H18) -> 0.91695561 | T18: =NORMSDIST(I18) -> 0.43530346 | ... V18: =NORMSDIST(K18) -> 0.56069849 | X18: =IF(pd_annual=0,"never",LN(1-M18)/LN(1-pd_annual)) -> 10.280248 | Y18: =IF(pd_annual=0,"never",LN(1-N18)/LN(1-pd_annual)) -> 46.625753 | Z18: =IF(pd_annual=0,"never",LN(1-O18)/LN(1-pd_annual)) -> 20.326696 | AA18: =IF(pd_annual=0,"never",LN(1-P18)/LN(1-pd_annual)) -> 29.033493 | AB18: =IF(pd_annual=0,"never",LN(1-Q18)/LN(1-pd_annual)) -> 52.608791 | AC18: =IF(pd_annual=0,"never",LN(1-R18)/LN(1-pd_annual)) -> 41.190469 | AD18: =IF(pd_annual=0,"never",LN(1-S18)/LN(1-pd_annual)) -> 60.956846 | AE18: =IF(pd_annual=0,"never",LN(1-T18)/LN(1-pd_annual)) -> 13.998992 | ... AG18: =IF(pd_annual=0,"never",LN(1-V18)/LN(1-pd_annual)) -> 20.150149 | AI18: =IF(pd_annual=0,21,MIN(21,MAX(1,ROUNDUP(4*X18,0)))) -> 21 | AJ18: =IF(pd_annual=0,21,MIN(21,MAX(1,ROUNDUP(4*Y18,0)))) -> 21 | AK18: =IF(pd_annual=0,21,MIN(21,MAX(1,ROUNDUP(4*Z18,0)))) -> 21 | AL18: =IF(pd_annual=0,21,MIN(21,MAX(1,ROUNDUP(4*AA18,0)))) -> 21 | AM18: =IF(pd_annual=0,21,MIN(21,MAX(1,ROUNDUP(4*AB18,0)))) -> 21 | AN18: =IF(pd_annual=0,21,MIN(21,MAX(1,ROUNDUP(4*AC18,0)))) -> 21 | AO18: =IF(pd_annual=0,21,MIN(21,MAX(1,ROUNDUP(4*AD18,0)))) -> 21 | AP18: =IF(pd_annual=0,21,MIN(21,MAX(1,ROUNDUP(4*AE18,0)))) -> 21 | ... AR18: =IF(pd_annual=0,21,MIN(21,MAX(1,ROUNDUP(4*AG18,0)))) -> 21 | AT18: =COUNTIF($AI18:$AR18,"<=20") -> 0
A19: 2 | B19: =SUMPRODUCT(Random!$X19:$AG19,$B$4:$K$4) -> -0.75785471 | C19: =SUMPRODUCT(Random!$X19:$AG19,$B$5:$K$5) -> 1.0204697 | D19: =SUMPRODUCT(Random!$X19:$AG19,$B$6:$K$6) -> -0.49631922 | E19: =SUMPRODUCT(Random!$X19:$AG19,$B$7:$K$7) -> 0.88439262 | F19: =SUMPRODUCT(Random!$X19:$AG19,$B$8:$K$8) -> 0.53634867 | G19: =SUMPRODUCT(Random!$X19:$AG19,$B$9:$K$9) -> 0.62752698 | H19: =SUMPRODUCT(Random!$X19:$AG19,$B$10:$K$10) -> 0.36715109 | I19: =SUMPRODUCT(Random!$X19:$AG19,$B$11:$K$11) -> 0.81329598 | J19: =SUMPRODUCT(Random!$X19:$AG19,$B$12:$K$12) -> 1.0433678 | K19: =SUMPRODUCT(Random!$X19:$AG19,$B$13:$K$13) -> 0.56562444 | M19: =NORMSDIST(B19) -> 0.22426898 | N19: =NORMSDIST(C19) -> 0.84624714 | O19: =NORMSDIST(D19) -> 0.30983461 | P19: =NORMSDIST(E19) -> 0.81175785 | Q19: =NORMSDIST(F19) -> 0.7041412 | R19: =NORMSDIST(G19) -> 0.73484307 | S19: =NORMSDIST(H19) -> 0.64324684 | T19: =NORMSDIST(I19) -> 0.79197581 | ... V19: =NORMSDIST(K19) -> 0.71417545 | X19: =IF(pd_annual=0,"never",LN(1-M19)/LN(1-pd_annual)) -> 6.2208976 | Y19: =IF(pd_annual=0,"never",LN(1-N19)/LN(1-pd_annual)) -> 45.867645 | Z19: =IF(pd_annual=0,"never",LN(1-O19)/LN(1-pd_annual)) -> 9.0839268 | AA19: =IF(pd_annual=0,"never",LN(1-P19)/LN(1-pd_annual)) -> 40.909958 | AB19: =IF(pd_annual=0,"never",LN(1-Q19)/LN(1-pd_annual)) -> 29.833745 | AC19: =IF(pd_annual=0,"never",LN(1-R19)/LN(1-pd_annual)) -> 32.517604 | AD19: =IF(pd_annual=0,"never",LN(1-S19)/LN(1-pd_annual)) -> 25.248917 | AE19: =IF(pd_annual=0,"never",LN(1-T19)/LN(1-pd_annual)) -> 38.462131 | ... AG19: =IF(pd_annual=0,"never",LN(1-V19)/LN(1-pd_annual)) -> 30.678979 | AI19: =IF(pd_annual=0,21,MIN(21,MAX(1,ROUNDUP(4*X19,0)))) -> 21 | AJ19: =IF(pd_annual=0,21,MIN(21,MAX(1,ROUNDUP(4*Y19,0)))) -> 21 | AK19: =IF(pd_annual=0,21,MIN(21,MAX(1,ROUNDUP(4*Z19,0)))) -> 21 | AL19: =IF(pd_annual=0,21,MIN(21,MAX(1,ROUNDUP(4*AA19,0)))) -> 21 | AM19: =IF(pd_annual=0,21,MIN(21,MAX(1,ROUNDUP(4*AB19,0)))) -> 21 | AN19: =IF(pd_annual=0,21,MIN(21,MAX(1,ROUNDUP(4*AC19,0)))) -> 21 | AO19: =IF(pd_annual=0,21,MIN(21,MAX(1,ROUNDUP(4*AD19,0)))) -> 21 | AP19: =IF(pd_annual=0,21,MIN(21,MAX(1,ROUNDUP(4*AE19,0)))) -> 21 | ... AR19: =IF(pd_annual=0,21,MIN(21,MAX(1,ROUNDUP(4*AG19,0)))) -> 21 | AT19: =COUNTIF($AI19:$AR19,"<=20") -> 0
A20: 3 | B20: =SUMPRODUCT(Random!$X20:$AG20,$B$4:$K$4) -> 1.070286 | C20: =SUMPRODUCT(Random!$X20:$AG20,$B$5:$K$5) -> -0.7757193 | D20: =SUMPRODUCT(Random!$X20:$AG20,$B$6:$K$6) -> 0.39833059 | E20: =SUMPRODUCT(Random!$X20:$AG20,$B$7:$K$7) -> -0.32452284 | F20: =SUMPRODUCT(Random!$X20:$AG20,$B$8:$K$8) -> -0.59104394 | G20: =SUMPRODUCT(Random!$X20:$AG20,$B$9:$K$9) -> -0.13675798 | H20: =SUMPRODUCT(Random!$X20:$AG20,$B$10:$K$10) -> -0.83719469 | I20: =SUMPRODUCT(Random!$X20:$AG20,$B$11:$K$11) -> 0.047911609 | J20: =SUMPRODUCT(Random!$X20:$AG20,$B$12:$K$12) -> -0.39878846 | K20: =SUMPRODUCT(Random!$X20:$AG20,$B$13:$K$13) -> -0.50554976 | M20: =NORMSDIST(B20) -> 0.85775471 | N20: =NORMSDIST(C20) -> 0.21895737 | O20: =NORMSDIST(D20) -> 0.65480674 | P20: =NORMSDIST(E20) -> 0.37277112 | Q20: =NORMSDIST(F20) -> 0.27724549 | R20: =NORMSDIST(G20) -> 0.44561105 | S20: =NORMSDIST(H20) -> 0.20124157 | T20: =NORMSDIST(I20) -> 0.51910666 | ... V20: =NORMSDIST(K20) -> 0.30658638 | X20: =IF(pd_annual=0,"never",LN(1-M20)/LN(1-pd_annual)) -> 47.773322 | Y20: =IF(pd_annual=0,"never",LN(1-N20)/LN(1-pd_annual)) -> 6.0537352 | Z20: =IF(pd_annual=0,"never",LN(1-O20)/LN(1-pd_annual)) -> 26.055828 | AA20: =IF(pd_annual=0,"never",LN(1-P20)/LN(1-pd_annual)) -> 11.426285 | AB20: =IF(pd_annual=0,"never",LN(1-Q20)/LN(1-pd_annual)) -> 7.9536942 | AC20: =IF(pd_annual=0,"never",LN(1-R20)/LN(1-pd_annual)) -> 14.450268 | AD20: =IF(pd_annual=0,"never",LN(1-S20)/LN(1-pd_annual)) -> 5.5043053 | AE20: =IF(pd_annual=0,"never",LN(1-T20)/LN(1-pd_annual)) -> 17.934199 | ... AG20: =IF(pd_annual=0,"never",LN(1-V20)/LN(1-pd_annual)) -> 8.9689052 | AI20: =IF(pd_annual=0,21,MIN(21,MAX(1,ROUNDUP(4*X20,0)))) -> 21 | AJ20: =IF(pd_annual=0,21,MIN(21,MAX(1,ROUNDUP(4*Y20,0)))) -> 21 | AK20: =IF(pd_annual=0,21,MIN(21,MAX(1,ROUNDUP(4*Z20,0)))) -> 21 | AL20: =IF(pd_annual=0,21,MIN(21,MAX(1,ROUNDUP(4*AA20,0)))) -> 21 | AM20: =IF(pd_annual=0,21,MIN(21,MAX(1,ROUNDUP(4*AB20,0)))) -> 21 | AN20: =IF(pd_annual=0,21,MIN(21,MAX(1,ROUNDUP(4*AC20,0)))) -> 21 | AO20: =IF(pd_annual=0,21,MIN(21,MAX(1,ROUNDUP(4*AD20,0)))) -> 21 | AP20: =IF(pd_annual=0,21,MIN(21,MAX(1,ROUNDUP(4*AE20,0)))) -> 21 | ... AR20: =IF(pd_annual=0,21,MIN(21,MAX(1,ROUNDUP(4*AG20,0)))) -> 21 | AT20: =COUNTIF($AI20:$AR20,"<=20") -> 0
A21: 4 | B21: =SUMPRODUCT(Random!$X21:$AG21,$B$4:$K$4) -> -0.44980723 | C21: =SUMPRODUCT(Random!$X21:$AG21,$B$5:$K$5) -> 1.7631413 | D21: =SUMPRODUCT(Random!$X21:$AG21,$B$6:$K$6) -> -0.72655319 | E21: =SUMPRODUCT(Random!$X21:$AG21,$B$7:$K$7) -> -0.21815928 | F21: =SUMPRODUCT(Random!$X21:$AG21,$B$8:$K$8) -> -0.00030630332 | G21: =SUMPRODUCT(Random!$X21:$AG21,$B$9:$K$9) -> 1.2422045 | H21: =SUMPRODUCT(Random!$X21:$AG21,$B$10:$K$10) -> -0.51324382 | I21: =SUMPRODUCT(Random!$X21:$AG21,$B$11:$K$11) -> -1.6147271 | J21: =SUMPRODUCT(Random!$X21:$AG21,$B$12:$K$12) -> -0.71689658 | K21: =SUMPRODUCT(Random!$X21:$AG21,$B$13:$K$13) -> -1.0689296 | M21: =NORMSDIST(B21) -> 0.32642472 | N21: =NORMSDIST(C21) -> 0.96106167 | O21: =NORMSDIST(D21) -> 0.23374986 | P21: =NORMSDIST(E21) -> 0.4136525 | Q21: =NORMSDIST(F21) -> 0.4998778 | R21: =NORMSDIST(G21) -> 0.89291945 | S21: =NORMSDIST(H21) -> 0.30389039 | T21: =NORMSDIST(I21) -> 0.053184898 | ... V21: =NORMSDIST(K21) -> 0.14255069 | X21: =IF(pd_annual=0,"never",LN(1-M21)/LN(1-pd_annual)) -> 9.679966 | Y21: =IF(pd_annual=0,"never",LN(1-N21)/LN(1-pd_annual)) -> 79.510475 | Z21: =IF(pd_annual=0,"never",LN(1-O21)/LN(1-pd_annual)) -> 6.5221361 | AA21: =IF(pd_annual=0,"never",LN(1-P21)/LN(1-pd_annual)) -> 13.077329 | AB21: =IF(pd_annual=0,"never",LN(1-Q21)/LN(1-pd_annual)) -> 16.973762 | AC21: =IF(pd_annual=0,"never",LN(1-R21)/LN(1-pd_annual)) -> 54.729661 | AD21: =IF(pd_annual=0,"never",LN(1-S21)/LN(1-pd_annual)) -> 8.8738472 | AE21: =IF(pd_annual=0,"never",LN(1-T21)/LN(1-pd_annual)) -> 1.3387746 | ... AG21: =IF(pd_annual=0,"never",LN(1-V21)/LN(1-pd_annual)) -> 3.7674107 | AI21: =IF(pd_annual=0,21,MIN(21,MAX(1,ROUNDUP(4*X21,0)))) -> 21 | AJ21: =IF(pd_annual=0,21,MIN(21,MAX(1,ROUNDUP(4*Y21,0)))) -> 21 | AK21: =IF(pd_annual=0,21,MIN(21,MAX(1,ROUNDUP(4*Z21,0)))) -> 21 | AL21: =IF(pd_annual=0,21,MIN(21,MAX(1,ROUNDUP(4*AA21,0)))) -> 21 | AM21: =IF(pd_annual=0,21,MIN(21,MAX(1,ROUNDUP(4*AB21,0)))) -> 21 | AN21: =IF(pd_annual=0,21,MIN(21,MAX(1,ROUNDUP(4*AC21,0)))) -> 21 | AO21: =IF(pd_annual=0,21,MIN(21,MAX(1,ROUNDUP(4*AD21,0)))) -> 21 | AP21: =IF(pd_annual=0,21,MIN(21,MAX(1,ROUNDUP(4*AE21,0)))) -> 6 | ... AR21: =IF(pd_annual=0,21,MIN(21,MAX(1,ROUNDUP(4*AG21,0)))) -> 16 | AT21: =COUNTIF($AI21:$AR21,"<=20") -> 2
A22: 5 | B22: =SUMPRODUCT(Random!$X22:$AG22,$B$4:$K$4) -> -1.8690173 | C22: =SUMPRODUCT(Random!$X22:$AG22,$B$5:$K$5) -> 0.34365558 | D22: =SUMPRODUCT(Random!$X22:$AG22,$B$6:$K$6) -> -0.076588476 | E22: =SUMPRODUCT(Random!$X22:$AG22,$B$7:$K$7) -> -0.91875382 | F22: =SUMPRODUCT(Random!$X22:$AG22,$B$8:$K$8) -> -1.6828875 | G22: =SUMPRODUCT(Random!$X22:$AG22,$B$9:$K$9) -> -1.1738999 | H22: =SUMPRODUCT(Random!$X22:$AG22,$B$10:$K$10) -> -1.2265224 | I22: =SUMPRODUCT(Random!$X22:$AG22,$B$11:$K$11) -> -0.69452428 | J22: =SUMPRODUCT(Random!$X22:$AG22,$B$12:$K$12) -> -1.4971931 | K22: =SUMPRODUCT(Random!$X22:$AG22,$B$13:$K$13) -> -0.44385533 | M22: =NORMSDIST(B22) -> 0.030810203 | N22: =NORMSDIST(C22) -> 0.63444734 | O22: =NORMSDIST(D22) -> 0.46947546 | P22: =NORMSDIST(E22) -> 0.17911217 | Q22: =NORMSDIST(F22) -> 0.046198439 | R22: =NORMSDIST(G22) -> 0.12021756 | S22: =NORMSDIST(H22) -> 0.11000107 | T22: =NORMSDIST(I22) -> 0.24367674 | ... V22: =NORMSDIST(K22) -> 0.32857359 | X22: =IF(pd_annual=0,"never",LN(1-M22)/LN(1-pd_annual)) -> 0.76661658 | Y22: =IF(pd_annual=0,"never",LN(1-N22)/LN(1-pd_annual)) -> 24.652027 | Z22: =IF(pd_annual=0,"never",LN(1-O22)/LN(1-pd_annual)) -> 15.528126 | AA22: =IF(pd_annual=0,"never",LN(1-P22)/LN(1-pd_annual)) -> 4.8348645 | AB22: =IF(pd_annual=0,"never",LN(1-Q22)/LN(1-pd_annual)) -> 1.1586802 | AC22: =IF(pd_annual=0,"never",LN(1-R22)/LN(1-pd_annual)) -> 3.1375398 | AD22: =IF(pd_annual=0,"never",LN(1-S22)/LN(1-pd_annual)) -> 2.8547117 | AE22: =IF(pd_annual=0,"never",LN(1-T22)/LN(1-pd_annual)) -> 6.8415667 | ... AG22: =IF(pd_annual=0,"never",LN(1-V22)/LN(1-pd_annual)) -> 9.758241 | AI22: =IF(pd_annual=0,21,MIN(21,MAX(1,ROUNDUP(4*X22,0)))) -> 4 | AJ22: =IF(pd_annual=0,21,MIN(21,MAX(1,ROUNDUP(4*Y22,0)))) -> 21 | AK22: =IF(pd_annual=0,21,MIN(21,MAX(1,ROUNDUP(4*Z22,0)))) -> 21 | AL22: =IF(pd_annual=0,21,MIN(21,MAX(1,ROUNDUP(4*AA22,0)))) -> 20 | AM22: =IF(pd_annual=0,21,MIN(21,MAX(1,ROUNDUP(4*AB22,0)))) -> 5 | AN22: =IF(pd_annual=0,21,MIN(21,MAX(1,ROUNDUP(4*AC22,0)))) -> 13 | AO22: =IF(pd_annual=0,21,MIN(21,MAX(1,ROUNDUP(4*AD22,0)))) -> 12 | AP22: =IF(pd_annual=0,21,MIN(21,MAX(1,ROUNDUP(4*AE22,0)))) -> 21 | ... AR22: =IF(pd_annual=0,21,MIN(21,MAX(1,ROUNDUP(4*AG22,0)))) -> 21 | AT22: =COUNTIF($AI22:$AR22,"<=20") -> 6
A23: 6 | B23: =SUMPRODUCT(Random!$X23:$AG23,$B$4:$K$4) -> -1.0020498 | C23: =SUMPRODUCT(Random!$X23:$AG23,$B$5:$K$5) -> 0.6097166 | D23: =SUMPRODUCT(Random!$X23:$AG23,$B$6:$K$6) -> -0.11349997 | E23: =SUMPRODUCT(Random!$X23:$AG23,$B$7:$K$7) -> -0.22125062 | F23: =SUMPRODUCT(Random!$X23:$AG23,$B$8:$K$8) -> -0.55747117 | G23: =SUMPRODUCT(Random!$X23:$AG23,$B$9:$K$9) -> 1.3391684 | H23: =SUMPRODUCT(Random!$X23:$AG23,$B$10:$K$10) -> 2.0987964 | I23: =SUMPRODUCT(Random!$X23:$AG23,$B$11:$K$11) -> -1.0204354 | J23: =SUMPRODUCT(Random!$X23:$AG23,$B$12:$K$12) -> -0.05733534 | K23: =SUMPRODUCT(Random!$X23:$AG23,$B$13:$K$13) -> -1.081094 | M23: =NORMSDIST(B23) -> 0.15815978 | N23: =NORMSDIST(C23) -> 0.72897522 | O23: =NORMSDIST(D23) -> 0.45481709 | P23: =NORMSDIST(E23) -> 0.41244865 | Q23: =NORMSDIST(F23) -> 0.28860278 | R23: =NORMSDIST(G23) -> 0.90974208 | S23: =NORMSDIST(H23) -> 0.98208258 | T23: =NORMSDIST(I23) -> 0.15376099 | ... V23: =NORMSDIST(K23) -> 0.13982765 | X23: =IF(pd_annual=0,"never",LN(1-M23)/LN(1-pd_annual)) -> 4.217458 | Y23: =IF(pd_annual=0,"never",LN(1-N23)/LN(1-pd_annual)) -> 31.981412 | Z23: =IF(pd_annual=0,"never",LN(1-O23)/LN(1-pd_annual)) -> 14.860468 | AA23: =IF(pd_annual=0,"never",LN(1-P23)/LN(1-pd_annual)) -> 13.027086 | AB23: =IF(pd_annual=0,"never",LN(1-Q23)/LN(1-pd_annual)) -> 8.3416875 | AC23: =IF(pd_annual=0,"never",LN(1-R23)/LN(1-pd_annual)) -> 58.916373 | AD23: =IF(pd_annual=0,"never",LN(1-S23)/LN(1-pd_annual)) -> 98.524868 | AE23: =IF(pd_annual=0,"never",LN(1-T23)/LN(1-pd_annual)) -> 4.0897915 | ... AG23: =IF(pd_annual=0,"never",LN(1-V23)/LN(1-pd_annual)) -> 3.6897391 | AI23: =IF(pd_annual=0,21,MIN(21,MAX(1,ROUNDUP(4*X23,0)))) -> 17 | AJ23: =IF(pd_annual=0,21,MIN(21,MAX(1,ROUNDUP(4*Y23,0)))) -> 21 | AK23: =IF(pd_annual=0,21,MIN(21,MAX(1,ROUNDUP(4*Z23,0)))) -> 21 | AL23: =IF(pd_annual=0,21,MIN(21,MAX(1,ROUNDUP(4*AA23,0)))) -> 21 | AM23: =IF(pd_annual=0,21,MIN(21,MAX(1,ROUNDUP(4*AB23,0)))) -> 21 | AN23: =IF(pd_annual=0,21,MIN(21,MAX(1,ROUNDUP(4*AC23,0)))) -> 21 | AO23: =IF(pd_annual=0,21,MIN(21,MAX(1,ROUNDUP(4*AD23,0)))) -> 21 | AP23: =IF(pd_annual=0,21,MIN(21,MAX(1,ROUNDUP(4*AE23,0)))) -> 17 | ... AR23: =IF(pd_annual=0,21,MIN(21,MAX(1,ROUNDUP(4*AG23,0)))) -> 15 | AT23: =COUNTIF($AI23:$AR23,"<=20") -> 3
A24: 7 | B24: =SUMPRODUCT(Random!$X24:$AG24,$B$4:$K$4) -> 0.1639567 | C24: =SUMPRODUCT(Random!$X24:$AG24,$B$5:$K$5) -> 2.4797676 | D24: =SUMPRODUCT(Random!$X24:$AG24,$B$6:$K$6) -> 2.7531122 | E24: =SUMPRODUCT(Random!$X24:$AG24,$B$7:$K$7) -> 0.80257057 | F24: =SUMPRODUCT(Random!$X24:$AG24,$B$8:$K$8) -> 0.76081714 | G24: =SUMPRODUCT(Random!$X24:$AG24,$B$9:$K$9) -> -0.22453443 | H24: =SUMPRODUCT(Random!$X24:$AG24,$B$10:$K$10) -> -0.36708375 | I24: =SUMPRODUCT(Random!$X24:$AG24,$B$11:$K$11) -> 0.6129988 | J24: =SUMPRODUCT(Random!$X24:$AG24,$B$12:$K$12) -> 1.2208369 | K24: =SUMPRODUCT(Random!$X24:$AG24,$B$13:$K$13) -> 1.073275 | M24: =NORMSDIST(B24) -> 0.56511739 | N24: =NORMSDIST(C24) -> 0.9934266 | O24: =NORMSDIST(D24) -> 0.99704842 | P24: =NORMSDIST(E24) -> 0.78888851 | Q24: =NORMSDIST(F24) -> 0.77661685 | R24: =NORMSDIST(G24) -> 0.41117074 | S24: =NORMSDIST(H24) -> 0.35677827 | T24: =NORMSDIST(I24) -> 0.73006143 | ... V24: =NORMSDIST(K24) -> 0.85842612 | X24: =IF(pd_annual=0,"never",LN(1-M24)/LN(1-pd_annual)) -> 20.397806 | Y24: =IF(pd_annual=0,"never",LN(1-N24)/LN(1-pd_annual)) -> 123.08864 | Z24: =IF(pd_annual=0,"never",LN(1-O24)/LN(1-pd_annual)) -> 142.70282 | AA24: =IF(pd_annual=0,"never",LN(1-P24)/LN(1-pd_annual)) -> 38.101247 | AB24: =IF(pd_annual=0,"never",LN(1-Q24)/LN(1-pd_annual)) -> 36.717139 | AC24: =IF(pd_annual=0,"never",LN(1-R24)/LN(1-pd_annual)) -> 12.973864 | AD24: =IF(pd_annual=0,"never",LN(1-S24)/LN(1-pd_annual)) -> 10.809511 | AE24: =IF(pd_annual=0,"never",LN(1-T24)/LN(1-pd_annual)) -> 32.079787 | ... AG24: =IF(pd_annual=0,"never",LN(1-V24)/LN(1-pd_annual)) -> 47.889222 | AI24: =IF(pd_annual=0,21,MIN(21,MAX(1,ROUNDUP(4*X24,0)))) -> 21 | AJ24: =IF(pd_annual=0,21,MIN(21,MAX(1,ROUNDUP(4*Y24,0)))) -> 21 | AK24: =IF(pd_annual=0,21,MIN(21,MAX(1,ROUNDUP(4*Z24,0)))) -> 21 | AL24: =IF(pd_annual=0,21,MIN(21,MAX(1,ROUNDUP(4*AA24,0)))) -> 21 | AM24: =IF(pd_annual=0,21,MIN(21,MAX(1,ROUNDUP(4*AB24,0)))) -> 21 | AN24: =IF(pd_annual=0,21,MIN(21,MAX(1,ROUNDUP(4*AC24,0)))) -> 21 | AO24: =IF(pd_annual=0,21,MIN(21,MAX(1,ROUNDUP(4*AD24,0)))) -> 21 | AP24: =IF(pd_annual=0,21,MIN(21,MAX(1,ROUNDUP(4*AE24,0)))) -> 21 | ... AR24: =IF(pd_annual=0,21,MIN(21,MAX(1,ROUNDUP(4*AG24,0)))) -> 21 | AT24: =COUNTIF($AI24:$AR24,"<=20") -> 0
A25: 8 | B25: =SUMPRODUCT(Random!$X25:$AG25,$B$4:$K$4) -> -0.016367218 | C25: =SUMPRODUCT(Random!$X25:$AG25,$B$5:$K$5) -> 0.53007032 | D25: =SUMPRODUCT(Random!$X25:$AG25,$B$6:$K$6) -> -1.1303161 | E25: =SUMPRODUCT(Random!$X25:$AG25,$B$7:$K$7) -> -0.83409545 | F25: =SUMPRODUCT(Random!$X25:$AG25,$B$8:$K$8) -> -0.71832039 | G25: =SUMPRODUCT(Random!$X25:$AG25,$B$9:$K$9) -> 1.1680463 | H25: =SUMPRODUCT(Random!$X25:$AG25,$B$10:$K$10) -> -0.34572521 | I25: =SUMPRODUCT(Random!$X25:$AG25,$B$11:$K$11) -> -0.61143162 | J25: =SUMPRODUCT(Random!$X25:$AG25,$B$12:$K$12) -> 0.71339541 | K25: =SUMPRODUCT(Random!$X25:$AG25,$B$13:$K$13) -> -0.44423257 | M25: =NORMSDIST(B25) -> 0.49347072 | N25: =NORMSDIST(C25) -> 0.70196841 | O25: =NORMSDIST(D25) -> 0.12917153 | P25: =NORMSDIST(E25) -> 0.2021136 | Q25: =NORMSDIST(F25) -> 0.23627988 | R25: =NORMSDIST(G25) -> 0.87860596 | S25: =NORMSDIST(H25) -> 0.36477462 | T25: =NORMSDIST(I25) -> 0.27045694 | ... V25: =NORMSDIST(K25) -> 0.32843722 | X25: =IF(pd_annual=0,"never",LN(1-M25)/LN(1-pd_annual)) -> 16.661928 | Y25: =IF(pd_annual=0,"never",LN(1-N25)/LN(1-pd_annual)) -> 29.654499 | Z25: =IF(pd_annual=0,"never",LN(1-O25)/LN(1-pd_annual)) -> 3.3881307 | AA25: =IF(pd_annual=0,"never",LN(1-P25)/LN(1-pd_annual)) -> 5.5310636 | AB25: =IF(pd_annual=0,"never",LN(1-Q25)/LN(1-pd_annual)) -> 6.6031534 | AC25: =IF(pd_annual=0,"never",LN(1-R25)/LN(1-pd_annual)) -> 51.656307 | AD25: =IF(pd_annual=0,"never",LN(1-S25)/LN(1-pd_annual)) -> 11.115954 | AE25: =IF(pd_annual=0,"never",LN(1-T25)/LN(1-pd_annual)) -> 7.7246809 | ... AG25: =IF(pd_annual=0,"never",LN(1-V25)/LN(1-pd_annual)) -> 9.7532662 | AI25: =IF(pd_annual=0,21,MIN(21,MAX(1,ROUNDUP(4*X25,0)))) -> 21 | AJ25: =IF(pd_annual=0,21,MIN(21,MAX(1,ROUNDUP(4*Y25,0)))) -> 21 | AK25: =IF(pd_annual=0,21,MIN(21,MAX(1,ROUNDUP(4*Z25,0)))) -> 14 | AL25: =IF(pd_annual=0,21,MIN(21,MAX(1,ROUNDUP(4*AA25,0)))) -> 21 | AM25: =IF(pd_annual=0,21,MIN(21,MAX(1,ROUNDUP(4*AB25,0)))) -> 21 | AN25: =IF(pd_annual=0,21,MIN(21,MAX(1,ROUNDUP(4*AC25,0)))) -> 21 | AO25: =IF(pd_annual=0,21,MIN(21,MAX(1,ROUNDUP(4*AD25,0)))) -> 21 | AP25: =IF(pd_annual=0,21,MIN(21,MAX(1,ROUNDUP(4*AE25,0)))) -> 21 | ... AR25: =IF(pd_annual=0,21,MIN(21,MAX(1,ROUNDUP(4*AG25,0)))) -> 21 | AT25: =COUNTIF($AI25:$AR25,"<=20") -> 1
A26: 9 | B26: =SUMPRODUCT(Random!$X26:$AG26,$B$4:$K$4) -> -0.19132778 | C26: =SUMPRODUCT(Random!$X26:$AG26,$B$5:$K$5) -> -0.92767366 | D26: =SUMPRODUCT(Random!$X26:$AG26,$B$6:$K$6) -> 0.78084742 | E26: =SUMPRODUCT(Random!$X26:$AG26,$B$7:$K$7) -> -0.2453454 | F26: =SUMPRODUCT(Random!$X26:$AG26,$B$8:$K$8) -> 0.56104339 | G26: =SUMPRODUCT(Random!$X26:$AG26,$B$9:$K$9) -> -0.0029820891 | H26: =SUMPRODUCT(Random!$X26:$AG26,$B$10:$K$10) -> -0.50184946 | I26: =SUMPRODUCT(Random!$X26:$AG26,$B$11:$K$11) -> -0.15154482 | J26: =SUMPRODUCT(Random!$X26:$AG26,$B$12:$K$12) -> -1.2909418 | K26: =SUMPRODUCT(Random!$X26:$AG26,$B$13:$K$13) -> 1.1865358 | M26: =NORMSDIST(B26) -> 0.4241344 | N26: =NORMSDIST(C26) -> 0.17678844 | O26: =NORMSDIST(D26) -> 0.78255388 | P26: =NORMSDIST(E26) -> 0.4030945 | Q26: =NORMSDIST(F26) -> 0.71261602 | R26: =NORMSDIST(G26) -> 0.49881032 | S26: =NORMSDIST(H26) -> 0.30788671 | T26: =NORMSDIST(I26) -> 0.43977298 | ... V26: =NORMSDIST(K26) -> 0.88229461 | X26: =IF(pd_annual=0,"never",LN(1-M26)/LN(1-pd_annual)) -> 13.519207 | Y26: =IF(pd_annual=0,"never",LN(1-N26)/LN(1-pd_annual)) -> 4.7656185 | Z26: =IF(pd_annual=0,"never",LN(1-O26)/LN(1-pd_annual)) -> 37.377012 | AA26: =IF(pd_annual=0,"never",LN(1-P26)/LN(1-pd_annual)) -> 12.640158 | AB26: =IF(pd_annual=0,"never",LN(1-Q26)/LN(1-pd_annual)) -> 30.545691 | AC26: =IF(pd_annual=0,"never",LN(1-R26)/LN(1-pd_annual)) -> 16.921531 | AD26: =IF(pd_annual=0,"never",LN(1-S26)/LN(1-pd_annual)) -> 9.0148858 | AE26: =IF(pd_annual=0,"never",LN(1-T26)/LN(1-pd_annual)) -> 14.193652 | ... AG26: =IF(pd_annual=0,"never",LN(1-V26)/LN(1-pd_annual)) -> 52.412198 | AI26: =IF(pd_annual=0,21,MIN(21,MAX(1,ROUNDUP(4*X26,0)))) -> 21 | AJ26: =IF(pd_annual=0,21,MIN(21,MAX(1,ROUNDUP(4*Y26,0)))) -> 20 | AK26: =IF(pd_annual=0,21,MIN(21,MAX(1,ROUNDUP(4*Z26,0)))) -> 21 | AL26: =IF(pd_annual=0,21,MIN(21,MAX(1,ROUNDUP(4*AA26,0)))) -> 21 | AM26: =IF(pd_annual=0,21,MIN(21,MAX(1,ROUNDUP(4*AB26,0)))) -> 21 | AN26: =IF(pd_annual=0,21,MIN(21,MAX(1,ROUNDUP(4*AC26,0)))) -> 21 | AO26: =IF(pd_annual=0,21,MIN(21,MAX(1,ROUNDUP(4*AD26,0)))) -> 21 | AP26: =IF(pd_annual=0,21,MIN(21,MAX(1,ROUNDUP(4*AE26,0)))) -> 21 | ... AR26: =IF(pd_annual=0,21,MIN(21,MAX(1,ROUNDUP(4*AG26,0)))) -> 21 | AT26: =COUNTIF($AI26:$AR26,"<=20") -> 2
A27: 10 | B27: =SUMPRODUCT(Random!$X27:$AG27,$B$4:$K$4) -> 1.2193973 | C27: =SUMPRODUCT(Random!$X27:$AG27,$B$5:$K$5) -> -0.95429711 | D27: =SUMPRODUCT(Random!$X27:$AG27,$B$6:$K$6) -> 1.0662155 | E27: =SUMPRODUCT(Random!$X27:$AG27,$B$7:$K$7) -> -0.66358854 | F27: =SUMPRODUCT(Random!$X27:$AG27,$B$8:$K$8) -> 0.13089586 | G27: =SUMPRODUCT(Random!$X27:$AG27,$B$9:$K$9) -> 1.7412494 | H27: =SUMPRODUCT(Random!$X27:$AG27,$B$10:$K$10) -> 1.9268308 | I27: =SUMPRODUCT(Random!$X27:$AG27,$B$11:$K$11) -> 0.55482902 | J27: =SUMPRODUCT(Random!$X27:$AG27,$B$12:$K$12) -> 1.4373396 | K27: =SUMPRODUCT(Random!$X27:$AG27,$B$13:$K$13) -> 1.0493349 | M27: =NORMSDIST(B27) -> 0.88865329 | N27: =NORMSDIST(C27) -> 0.16996663 | O27: =NORMSDIST(D27) -> 0.85683689 | P27: =NORMSDIST(E27) -> 0.25347685 | Q27: =NORMSDIST(F27) -> 0.55207116 | R27: =NORMSDIST(G27) -> 0.95918007 | S27: =NORMSDIST(H27) -> 0.97299964 | T27: =NORMSDIST(I27) -> 0.71049419 | ... V27: =NORMSDIST(K27) -> 0.85298799 | X27: =IF(pd_annual=0,"never",LN(1-M27)/LN(1-pd_annual)) -> 53.77264 | Y27: =IF(pd_annual=0,"never",LN(1-N27)/LN(1-pd_annual)) -> 4.5634561 | Z27: =IF(pd_annual=0,"never",LN(1-O27)/LN(1-pd_annual)) -> 47.615769 | AA27: =IF(pd_annual=0,"never",LN(1-P27)/LN(1-pd_annual)) -> 7.1610574 | AB27: =IF(pd_annual=0,"never",LN(1-Q27)/LN(1-pd_annual)) -> 19.67373 | AC27: =IF(pd_annual=0,"never",LN(1-R27)/LN(1-pd_annual)) -> 78.354446 | AD27: =IF(pd_annual=0,"never",LN(1-S27)/LN(1-pd_annual)) -> 88.479388 | AE27: =IF(pd_annual=0,"never",LN(1-T27)/LN(1-pd_annual)) -> 30.365491 | ... AG27: =IF(pd_annual=0,"never",LN(1-V27)/LN(1-pd_annual)) -> 46.965883 | AI27: =IF(pd_annual=0,21,MIN(21,MAX(1,ROUNDUP(4*X27,0)))) -> 21 | AJ27: =IF(pd_annual=0,21,MIN(21,MAX(1,ROUNDUP(4*Y27,0)))) -> 19 | AK27: =IF(pd_annual=0,21,MIN(21,MAX(1,ROUNDUP(4*Z27,0)))) -> 21 | AL27: =IF(pd_annual=0,21,MIN(21,MAX(1,ROUNDUP(4*AA27,0)))) -> 21 | AM27: =IF(pd_annual=0,21,MIN(21,MAX(1,ROUNDUP(4*AB27,0)))) -> 21 | AN27: =IF(pd_annual=0,21,MIN(21,MAX(1,ROUNDUP(4*AC27,0)))) -> 21 | AO27: =IF(pd_annual=0,21,MIN(21,MAX(1,ROUNDUP(4*AD27,0)))) -> 21 | AP27: =IF(pd_annual=0,21,MIN(21,MAX(1,ROUNDUP(4*AE27,0)))) -> 21 | ... AR27: =IF(pd_annual=0,21,MIN(21,MAX(1,ROUNDUP(4*AG27,0)))) -> 21 | AT27: =COUNTIF($AI27:$AR27,"<=20") -> 1
A28: 11 | B28: =SUMPRODUCT(Random!$X28:$AG28,$B$4:$K$4) -> -0.38228961 | C28: =SUMPRODUCT(Random!$X28:$AG28,$B$5:$K$5) -> 0.54277729 | D28: =SUMPRODUCT(Random!$X28:$AG28,$B$6:$K$6) -> 0.79046162 | E28: =SUMPRODUCT(Random!$X28:$AG28,$B$7:$K$7) -> -0.094954462 | F28: =SUMPRODUCT(Random!$X28:$AG28,$B$8:$K$8) -> 1.1016836 | G28: =SUMPRODUCT(Random!$X28:$AG28,$B$9:$K$9) -> 2.3013433 | H28: =SUMPRODUCT(Random!$X28:$AG28,$B$10:$K$10) -> -0.13345487 | I28: =SUMPRODUCT(Random!$X28:$AG28,$B$11:$K$11) -> 0.49927458 | J28: =SUMPRODUCT(Random!$X28:$AG28,$B$12:$K$12) -> -0.28925599 | K28: =SUMPRODUCT(Random!$X28:$AG28,$B$13:$K$13) -> 0.3980959 | M28: =NORMSDIST(B28) -> 0.35112328 | N28: =NORMSDIST(C28) -> 0.70635843 | O28: =NORMSDIST(D28) -> 0.78537088 | P28: =NORMSDIST(E28) -> 0.4621755 | Q28: =NORMSDIST(F28) -> 0.86470037 | R28: =NORMSDIST(G28) -> 0.98931388 | S28: =NORMSDIST(H28) -> 0.44691683 | T28: =NORMSDIST(I28) -> 0.69120702 | ... V28: =NORMSDIST(K28) -> 0.65472025 | X28: =IF(pd_annual=0,"never",LN(1-M28)/LN(1-pd_annual)) -> 10.595086 | Y28: =IF(pd_annual=0,"never",LN(1-N28)/LN(1-pd_annual)) -> 30.018019 | Z28: =IF(pd_annual=0,"never",LN(1-O28)/LN(1-pd_annual)) -> 37.696438 | AA28: =IF(pd_annual=0,"never",LN(1-P28)/LN(1-pd_annual)) -> 15.193353 | AB28: =IF(pd_annual=0,"never",LN(1-Q28)/LN(1-pd_annual)) -> 48.999651 | AC28: =IF(pd_annual=0,"never",LN(1-R28)/LN(1-pd_annual)) -> 111.1854 | AD28: =IF(pd_annual=0,"never",LN(1-S28)/LN(1-pd_annual)) -> 14.508034 | AE28: =IF(pd_annual=0,"never",LN(1-T28)/LN(1-pd_annual)) -> 28.785565 | ... AG28: =IF(pd_annual=0,"never",LN(1-V28)/LN(1-pd_annual)) -> 26.049691 | AI28: =IF(pd_annual=0,21,MIN(21,MAX(1,ROUNDUP(4*X28,0)))) -> 21 | AJ28: =IF(pd_annual=0,21,MIN(21,MAX(1,ROUNDUP(4*Y28,0)))) -> 21 | AK28: =IF(pd_annual=0,21,MIN(21,MAX(1,ROUNDUP(4*Z28,0)))) -> 21 | AL28: =IF(pd_annual=0,21,MIN(21,MAX(1,ROUNDUP(4*AA28,0)))) -> 21 | AM28: =IF(pd_annual=0,21,MIN(21,MAX(1,ROUNDUP(4*AB28,0)))) -> 21 | AN28: =IF(pd_annual=0,21,MIN(21,MAX(1,ROUNDUP(4*AC28,0)))) -> 21 | AO28: =IF(pd_annual=0,21,MIN(21,MAX(1,ROUNDUP(4*AD28,0)))) -> 21 | AP28: =IF(pd_annual=0,21,MIN(21,MAX(1,ROUNDUP(4*AE28,0)))) -> 21 | ... AR28: =IF(pd_annual=0,21,MIN(21,MAX(1,ROUNDUP(4*AG28,0)))) -> 21 | AT28: =COUNTIF($AI28:$AR28,"<=20") -> 0
A29: 12 | B29: =SUMPRODUCT(Random!$X29:$AG29,$B$4:$K$4) -> 0.96914654 | C29: =SUMPRODUCT(Random!$X29:$AG29,$B$5:$K$5) -> 0.7132103 | D29: =SUMPRODUCT(Random!$X29:$AG29,$B$6:$K$6) -> -0.3077929 | E29: =SUMPRODUCT(Random!$X29:$AG29,$B$7:$K$7) -> 0.069182553 | F29: =SUMPRODUCT(Random!$X29:$AG29,$B$8:$K$8) -> 1.6156147 | G29: =SUMPRODUCT(Random!$X29:$AG29,$B$9:$K$9) -> 1.5515284 | H29: =SUMPRODUCT(Random!$X29:$AG29,$B$10:$K$10) -> 0.53401842 | I29: =SUMPRODUCT(Random!$X29:$AG29,$B$11:$K$11) -> -0.60322341 | J29: =SUMPRODUCT(Random!$X29:$AG29,$B$12:$K$12) -> 0.095194577 | K29: =SUMPRODUCT(Random!$X29:$AG29,$B$13:$K$13) -> -1.5986673 | M29: =NORMSDIST(B29) -> 0.83376396 | N29: =NORMSDIST(C29) -> 0.76214218 | O29: =NORMSDIST(D29) -> 0.37911996 | P29: =NORMSDIST(E29) -> 0.52757784 | Q29: =NORMSDIST(F29) -> 0.94691118 | R29: =NORMSDIST(G29) -> 0.93961245 | S29: =NORMSDIST(H29) -> 0.7033356 | T29: =NORMSDIST(I29) -> 0.27318004 | ... V29: =NORMSDIST(K29) -> 0.054947272 | X29: =IF(pd_annual=0,"never",LN(1-M29)/LN(1-pd_annual)) -> 43.955387 | Y29: =IF(pd_annual=0,"never",LN(1-N29)/LN(1-pd_annual)) -> 35.179128 | Z29: =IF(pd_annual=0,"never",LN(1-O29)/LN(1-pd_annual)) -> 11.675505 | AA29: =IF(pd_annual=0,"never",LN(1-P29)/LN(1-pd_annual)) -> 18.369565 | AB29: =IF(pd_annual=0,"never",LN(1-Q29)/LN(1-pd_annual)) -> 71.916843 | AC29: =IF(pd_annual=0,"never",LN(1-R29)/LN(1-pd_annual)) -> 68.761272 | AD29: =IF(pd_annual=0,"never",LN(1-S29)/LN(1-pd_annual)) -> 29.767134 | AE29: =IF(pd_annual=0,"never",LN(1-T29)/LN(1-pd_annual)) -> 7.8162882 | ... AG29: =IF(pd_annual=0,"never",LN(1-V29)/LN(1-pd_annual)) -> 1.3844144 | AI29: =IF(pd_annual=0,21,MIN(21,MAX(1,ROUNDUP(4*X29,0)))) -> 21 | AJ29: =IF(pd_annual=0,21,MIN(21,MAX(1,ROUNDUP(4*Y29,0)))) -> 21 | AK29: =IF(pd_annual=0,21,MIN(21,MAX(1,ROUNDUP(4*Z29,0)))) -> 21 | AL29: =IF(pd_annual=0,21,MIN(21,MAX(1,ROUNDUP(4*AA29,0)))) -> 21 | AM29: =IF(pd_annual=0,21,MIN(21,MAX(1,ROUNDUP(4*AB29,0)))) -> 21 | AN29: =IF(pd_annual=0,21,MIN(21,MAX(1,ROUNDUP(4*AC29,0)))) -> 21 | AO29: =IF(pd_annual=0,21,MIN(21,MAX(1,ROUNDUP(4*AD29,0)))) -> 21 | AP29: =IF(pd_annual=0,21,MIN(21,MAX(1,ROUNDUP(4*AE29,0)))) -> 21 | ... AR29: =IF(pd_annual=0,21,MIN(21,MAX(1,ROUNDUP(4*AG29,0)))) -> 6 | AT29: =COUNTIF($AI29:$AR29,"<=20") -> 1
... A1017: 1000 | B1017: =SUMPRODUCT(Random!$X1017:$AG1017,$B$4:$K$4) -> 0.3798051 | C1017: =SUMPRODUCT(Random!$X1017:$AG1017,$B$5:$K$5) -> -0.23103048 | D1017: =SUMPRODUCT(Random!$X1017:$AG1017,$B$6:$K$6) -> 2.1848268 | E1017: =SUMPRODUCT(Random!$X1017:$AG1017,$B$7:$K$7) -> 0.84082515 | F1017: =SUMPRODUCT(Random!$X1017:$AG1017,$B$8:$K$8) -> 1.7194137 | G1017: =SUMPRODUCT(Random!$X1017:$AG1017,$B$9:$K$9) -> -0.94843256 | H1017: =SUMPRODUCT(Random!$X1017:$AG1017,$B$10:$K$10) -> 0.93222001 | I1017: =SUMPRODUCT(Random!$X1017:$AG1017,$B$11:$K$11) -> -0.49789143 | J1017: =SUMPRODUCT(Random!$X1017:$AG1017,$B$12:$K$12) -> 0.94588372 | K1017: =SUMPRODUCT(Random!$X1017:$AG1017,$B$13:$K$13) -> 0.51926915 | M1017: =NORMSDIST(B1017) -> 0.64795495 | N1017: =NORMSDIST(C1017) -> 0.40864556 | O1017: =NORMSDIST(D1017) -> 0.98554923 | P1017: =NORMSDIST(E1017) -> 0.79977705 | Q1017: =NORMSDIST(F1017) -> 0.95723046 | R1017: =NORMSDIST(G1017) -> 0.17145465 | S1017: =NORMSDIST(H1017) -> 0.82438858 | T1017: =NORMSDIST(I1017) -> 0.30928029 | ... V1017: =NORMSDIST(K1017) -> 0.69821347 | X1017: =IF(pd_annual=0,"never",LN(1-M1017)/LN(1-pd_annual)) -> 25.574354 | Y1017: =IF(pd_annual=0,"never",LN(1-N1017)/LN(1-pd_annual)) -> 12.869036 | Z1017: =IF(pd_annual=0,"never",LN(1-O1017)/LN(1-pd_annual)) -> 103.79227 | AA1017: =IF(pd_annual=0,"never",LN(1-P1017)/LN(1-pd_annual)) -> 39.398462 | AB1017: =IF(pd_annual=0,"never",LN(1-Q1017)/LN(1-pd_annual)) -> 77.211543 | AC1017: =IF(pd_annual=0,"never",LN(1-R1017)/LN(1-pd_annual)) -> 4.6074109 | AD1017: =IF(pd_annual=0,"never",LN(1-S1017)/LN(1-pd_annual)) -> 42.611381 | AE1017: =IF(pd_annual=0,"never",LN(1-T1017)/LN(1-pd_annual)) -> 9.0642597 | ... AG1017: =IF(pd_annual=0,"never",LN(1-V1017)/LN(1-pd_annual)) -> 29.347791 | AI1017: =IF(pd_annual=0,21,MIN(21,MAX(1,ROUNDUP(4*X1017,0)))) -> 21 | AJ1017: =IF(pd_annual=0,21,MIN(21,MAX(1,ROUNDUP(4*Y1017,0)))) -> 21 | AK1017: =IF(pd_annual=0,21,MIN(21,MAX(1,ROUNDUP(4*Z1017,0)))) -> 21 | AL1017: =IF(pd_annual=0,21,MIN(21,MAX(1,ROUNDUP(4*AA1017,0)))) -> 21 | AM1017: =IF(pd_annual=0,21,MIN(21,MAX(1,ROUNDUP(4*AB1017,0)))) -> 21 | AN1017: =IF(pd_annual=0,21,MIN(21,MAX(1,ROUNDUP(4*AC1017,0)))) -> 19 | AO1017: =IF(pd_annual=0,21,MIN(21,MAX(1,ROUNDUP(4*AD1017,0)))) -> 21 | AP1017: =IF(pd_annual=0,21,MIN(21,MAX(1,ROUNDUP(4*AE1017,0)))) -> 21 | ... AR1017: =IF(pd_annual=0,21,MIN(21,MAX(1,ROUNDUP(4*AG1017,0)))) -> 21 | AT1017: =COUNTIF($AI1017:$AR1017,"<=20") -> 1

Sheet CashFlows
A1: Pool cash flows and the waterfall, every case and quarter ($MM)
A2: Pool = promised per bond x (10 - LGD x number of bonds in default by that quarter), the BIS model summed over the 10 bonds. Class A = min(pool, due to A); Class B = min(pool - A, due to B); equity = the rest. No carry-forwards: each quarter stands alone.
B12: Pool, quarter: | W12: Class A, quarter: | AR12: Class B, quarter: | BM12: Equity, quarter:
A14: One bond promised | B14: =Inputs!$B$25 -> 0.15 | C14: =Inputs!$B$26 -> 0.15 | D14: =Inputs!$B$27 -> 0.15 | E14: =Inputs!$B$28 -> 0.15 | F14: =Inputs!$B$29 -> 0.15 | G14: =Inputs!$B$30 -> 0.15 | H14: =Inputs!$B$31 -> 0.15 | I14: =Inputs!$B$32 -> 0.15 | J14: =Inputs!$B$33 -> 0.15 | K14: =Inputs!$B$34 -> 0.15 | L14: =Inputs!$B$35 -> 0.15 | M14: =Inputs!$B$36 -> 0.15 | N14: =Inputs!$B$37 -> 0.15 | O14: =Inputs!$B$38 -> 0.15 | P14: =Inputs!$B$39 -> 0.15 | Q14: =Inputs!$B$40 -> 0.15 | R14: =Inputs!$B$41 -> 0.15 | S14: =Inputs!$B$42 -> 0.15 | T14: =Inputs!$B$43 -> 0.15 | U14: =Inputs!$B$44 -> 10.15
A15: Due to Class A | B15: =Inputs!$D$25 -> 0.1 | C15: =Inputs!$D$26 -> 0.1 | D15: =Inputs!$D$27 -> 0.1 | E15: =Inputs!$D$28 -> 0.1 | F15: =Inputs!$D$29 -> 0.1 | G15: =Inputs!$D$30 -> 0.1 | H15: =Inputs!$D$31 -> 0.1 | I15: =Inputs!$D$32 -> 0.1 | J15: =Inputs!$D$33 -> 0.1 | K15: =Inputs!$D$34 -> 0.1 | L15: =Inputs!$D$35 -> 0.1 | M15: =Inputs!$D$36 -> 0.1 | N15: =Inputs!$D$37 -> 0.1 | O15: =Inputs!$D$38 -> 0.1 | P15: =Inputs!$D$39 -> 0.1 | Q15: =Inputs!$D$40 -> 0.1 | R15: =Inputs!$D$41 -> 0.1 | S15: =Inputs!$D$42 -> 0.1 | T15: =Inputs!$D$43 -> 0.1 | U15: =Inputs!$D$44 -> 20.1
A16: Due to Class B | B16: =Inputs!$E$25 -> 0.1 | C16: =Inputs!$E$26 -> 0.1 | D16: =Inputs!$E$27 -> 0.1 | E16: =Inputs!$E$28 -> 0.1 | F16: =Inputs!$E$29 -> 0.1 | G16: =Inputs!$E$30 -> 0.1 | H16: =Inputs!$E$31 -> 0.1 | I16: =Inputs!$E$32 -> 0.1 | J16: =Inputs!$E$33 -> 0.1 | K16: =Inputs!$E$34 -> 0.1 | L16: =Inputs!$E$35 -> 0.1 | M16: =Inputs!$E$36 -> 0.1 | N16: =Inputs!$E$37 -> 0.1 | O16: =Inputs!$E$38 -> 0.1 | P16: =Inputs!$E$39 -> 0.1 | Q16: =Inputs!$E$40 -> 0.1 | R16: =Inputs!$E$41 -> 0.1 | S16: =Inputs!$E$42 -> 0.1 | T16: =Inputs!$E$43 -> 0.1 | U16: =Inputs!$E$44 -> 10.1
A17: Case | B17: 1 | C17: 2 | D17: 3 | E17: 4 | F17: 5 | G17: 6 | H17: 7 | I17: 8 | J17: 9 | K17: 10 | L17: 11 | M17: 12 | N17: 13 | O17: 14 | P17: 15 | Q17: 16 | R17: 17 | S17: 18 | T17: 19 | U17: 20 | W17: 1 | X17: 2 | Y17: 3 | Z17: 4 | AA17: 5 | AB17: 6 | AC17: 7 | AD17: 8 | AE17: 9 | AF17: 10 | AG17: 11 | AH17: 12 | AI17: 13 | AJ17: 14 | AK17: 15 | AL17: 16 | AM17: 17 | AN17: 18 | AO17: 19 | AP17: 20 | AR17: 1 | AS17: 2 | AT17: 3 | AU17: 4 | AV17: 5 | AW17: 6 | AX17: 7 | AY17: 8 | AZ17: 9 | BA17: 10 | BB17: 11 | BC17: 12 | BD17: 13 | BE17: 14 | BF17: 15 | BG17: 16 | BH17: 17 | BI17: 18 | BJ17: 19 | BK17: 20 | BM17: 1 | BN17: 2 | BO17: 3 | BP17: 4 | BQ17: 5 | BR17: 6 | BS17: 7 | BT17: 8 | BU17: 9 | BV17: 10 | BW17: 11 | BX17: 12 | BY17: 13 | BZ17: 14 | CA17: 15 | CB17: 16 | CC17: 17 | CD17: 18 | CE17: 19 | CF17: 20 | CH17: Pool total | CI17: Class A total | CJ17: Class B total | CK17: Equity total | CL17: A short (1/0) | CM17: B short (1/0)
A18: 1 | B18: =B$14*(10-lgd*COUNTIF(Defaults!$AI18:$AR18,"<="&B$17)) -> 1.5 | C18: =C$14*(10-lgd*COUNTIF(Defaults!$AI18:$AR18,"<="&C$17)) -> 1.5 | D18: =D$14*(10-lgd*COUNTIF(Defaults!$AI18:$AR18,"<="&D$17)) -> 1.5 | E18: =E$14*(10-lgd*COUNTIF(Defaults!$AI18:$AR18,"<="&E$17)) -> 1.5 | F18: =F$14*(10-lgd*COUNTIF(Defaults!$AI18:$AR18,"<="&F$17)) -> 1.5 | G18: =G$14*(10-lgd*COUNTIF(Defaults!$AI18:$AR18,"<="&G$17)) -> 1.5 | H18: =H$14*(10-lgd*COUNTIF(Defaults!$AI18:$AR18,"<="&H$17)) -> 1.5 | I18: =I$14*(10-lgd*COUNTIF(Defaults!$AI18:$AR18,"<="&I$17)) -> 1.5 | ... U18: =U$14*(10-lgd*COUNTIF(Defaults!$AI18:$AR18,"<="&U$17)) -> 101.5 | W18: =MIN(B18,B$15) -> 0.1 | X18: =MIN(C18,C$15) -> 0.1 | Y18: =MIN(D18,D$15) -> 0.1 | Z18: =MIN(E18,E$15) -> 0.1 | AA18: =MIN(F18,F$15) -> 0.1 | AB18: =MIN(G18,G$15) -> 0.1 | AC18: =MIN(H18,H$15) -> 0.1 | AD18: =MIN(I18,I$15) -> 0.1 | ... AP18: =MIN(U18,U$15) -> 20.1 | AR18: =MIN(B18-W18,B$16) -> 0.1 | AS18: =MIN(C18-X18,C$16) -> 0.1 | AT18: =MIN(D18-Y18,D$16) -> 0.1 | AU18: =MIN(E18-Z18,E$16) -> 0.1 | AV18: =MIN(F18-AA18,F$16) -> 0.1 | AW18: =MIN(G18-AB18,G$16) -> 0.1 | AX18: =MIN(H18-AC18,H$16) -> 0.1 | AY18: =MIN(I18-AD18,I$16) -> 0.1 | ... BK18: =MIN(U18-AP18,U$16) -> 10.1 | BM18: =B18-W18-AR18 -> 1.3 | BN18: =C18-X18-AS18 -> 1.3 | BO18: =D18-Y18-AT18 -> 1.3 | BP18: =E18-Z18-AU18 -> 1.3 | BQ18: =F18-AA18-AV18 -> 1.3 | BR18: =G18-AB18-AW18 -> 1.3 | BS18: =H18-AC18-AX18 -> 1.3 | BT18: =I18-AD18-AY18 -> 1.3 | ... CF18: =U18-AP18-BK18 -> 71.3 | CH18: =SUM($B18:$U18) -> 130 | CI18: =SUM($W18:$AP18) -> 22 | CJ18: =SUM($AR18:$BK18) -> 12 | CK18: =SUM($BM18:$CF18) -> 96 | CL18: =IF(CI18<SUM($B$15:$U$15)-0.000000001,1,0) -> 0 | CM18: =IF(CJ18<SUM($B$16:$U$16)-0.000000001,1,0) -> 0
A19: 2 | B19: =B$14*(10-lgd*COUNTIF(Defaults!$AI19:$AR19,"<="&B$17)) -> 1.5 | C19: =C$14*(10-lgd*COUNTIF(Defaults!$AI19:$AR19,"<="&C$17)) -> 1.5 | D19: =D$14*(10-lgd*COUNTIF(Defaults!$AI19:$AR19,"<="&D$17)) -> 1.5 | E19: =E$14*(10-lgd*COUNTIF(Defaults!$AI19:$AR19,"<="&E$17)) -> 1.5 | F19: =F$14*(10-lgd*COUNTIF(Defaults!$AI19:$AR19,"<="&F$17)) -> 1.5 | G19: =G$14*(10-lgd*COUNTIF(Defaults!$AI19:$AR19,"<="&G$17)) -> 1.5 | H19: =H$14*(10-lgd*COUNTIF(Defaults!$AI19:$AR19,"<="&H$17)) -> 1.5 | I19: =I$14*(10-lgd*COUNTIF(Defaults!$AI19:$AR19,"<="&I$17)) -> 1.5 | ... U19: =U$14*(10-lgd*COUNTIF(Defaults!$AI19:$AR19,"<="&U$17)) -> 101.5 | W19: =MIN(B19,B$15) -> 0.1 | X19: =MIN(C19,C$15) -> 0.1 | Y19: =MIN(D19,D$15) -> 0.1 | Z19: =MIN(E19,E$15) -> 0.1 | AA19: =MIN(F19,F$15) -> 0.1 | AB19: =MIN(G19,G$15) -> 0.1 | AC19: =MIN(H19,H$15) -> 0.1 | AD19: =MIN(I19,I$15) -> 0.1 | ... AP19: =MIN(U19,U$15) -> 20.1 | AR19: =MIN(B19-W19,B$16) -> 0.1 | AS19: =MIN(C19-X19,C$16) -> 0.1 | AT19: =MIN(D19-Y19,D$16) -> 0.1 | AU19: =MIN(E19-Z19,E$16) -> 0.1 | AV19: =MIN(F19-AA19,F$16) -> 0.1 | AW19: =MIN(G19-AB19,G$16) -> 0.1 | AX19: =MIN(H19-AC19,H$16) -> 0.1 | AY19: =MIN(I19-AD19,I$16) -> 0.1 | ... BK19: =MIN(U19-AP19,U$16) -> 10.1 | BM19: =B19-W19-AR19 -> 1.3 | BN19: =C19-X19-AS19 -> 1.3 | BO19: =D19-Y19-AT19 -> 1.3 | BP19: =E19-Z19-AU19 -> 1.3 | BQ19: =F19-AA19-AV19 -> 1.3 | BR19: =G19-AB19-AW19 -> 1.3 | BS19: =H19-AC19-AX19 -> 1.3 | BT19: =I19-AD19-AY19 -> 1.3 | ... CF19: =U19-AP19-BK19 -> 71.3 | CH19: =SUM($B19:$U19) -> 130 | CI19: =SUM($W19:$AP19) -> 22 | CJ19: =SUM($AR19:$BK19) -> 12 | CK19: =SUM($BM19:$CF19) -> 96 | CL19: =IF(CI19<SUM($B$15:$U$15)-0.000000001,1,0) -> 0 | CM19: =IF(CJ19<SUM($B$16:$U$16)-0.000000001,1,0) -> 0
A20: 3 | B20: =B$14*(10-lgd*COUNTIF(Defaults!$AI20:$AR20,"<="&B$17)) -> 1.5 | C20: =C$14*(10-lgd*COUNTIF(Defaults!$AI20:$AR20,"<="&C$17)) -> 1.5 | D20: =D$14*(10-lgd*COUNTIF(Defaults!$AI20:$AR20,"<="&D$17)) -> 1.5 | E20: =E$14*(10-lgd*COUNTIF(Defaults!$AI20:$AR20,"<="&E$17)) -> 1.5 | F20: =F$14*(10-lgd*COUNTIF(Defaults!$AI20:$AR20,"<="&F$17)) -> 1.5 | G20: =G$14*(10-lgd*COUNTIF(Defaults!$AI20:$AR20,"<="&G$17)) -> 1.5 | H20: =H$14*(10-lgd*COUNTIF(Defaults!$AI20:$AR20,"<="&H$17)) -> 1.5 | I20: =I$14*(10-lgd*COUNTIF(Defaults!$AI20:$AR20,"<="&I$17)) -> 1.5 | ... U20: =U$14*(10-lgd*COUNTIF(Defaults!$AI20:$AR20,"<="&U$17)) -> 101.5 | W20: =MIN(B20,B$15) -> 0.1 | X20: =MIN(C20,C$15) -> 0.1 | Y20: =MIN(D20,D$15) -> 0.1 | Z20: =MIN(E20,E$15) -> 0.1 | AA20: =MIN(F20,F$15) -> 0.1 | AB20: =MIN(G20,G$15) -> 0.1 | AC20: =MIN(H20,H$15) -> 0.1 | AD20: =MIN(I20,I$15) -> 0.1 | ... AP20: =MIN(U20,U$15) -> 20.1 | AR20: =MIN(B20-W20,B$16) -> 0.1 | AS20: =MIN(C20-X20,C$16) -> 0.1 | AT20: =MIN(D20-Y20,D$16) -> 0.1 | AU20: =MIN(E20-Z20,E$16) -> 0.1 | AV20: =MIN(F20-AA20,F$16) -> 0.1 | AW20: =MIN(G20-AB20,G$16) -> 0.1 | AX20: =MIN(H20-AC20,H$16) -> 0.1 | AY20: =MIN(I20-AD20,I$16) -> 0.1 | ... BK20: =MIN(U20-AP20,U$16) -> 10.1 | BM20: =B20-W20-AR20 -> 1.3 | BN20: =C20-X20-AS20 -> 1.3 | BO20: =D20-Y20-AT20 -> 1.3 | BP20: =E20-Z20-AU20 -> 1.3 | BQ20: =F20-AA20-AV20 -> 1.3 | BR20: =G20-AB20-AW20 -> 1.3 | BS20: =H20-AC20-AX20 -> 1.3 | BT20: =I20-AD20-AY20 -> 1.3 | ... CF20: =U20-AP20-BK20 -> 71.3 | CH20: =SUM($B20:$U20) -> 130 | CI20: =SUM($W20:$AP20) -> 22 | CJ20: =SUM($AR20:$BK20) -> 12 | CK20: =SUM($BM20:$CF20) -> 96 | CL20: =IF(CI20<SUM($B$15:$U$15)-0.000000001,1,0) -> 0 | CM20: =IF(CJ20<SUM($B$16:$U$16)-0.000000001,1,0) -> 0
A21: 4 | B21: =B$14*(10-lgd*COUNTIF(Defaults!$AI21:$AR21,"<="&B$17)) -> 1.5 | C21: =C$14*(10-lgd*COUNTIF(Defaults!$AI21:$AR21,"<="&C$17)) -> 1.5 | D21: =D$14*(10-lgd*COUNTIF(Defaults!$AI21:$AR21,"<="&D$17)) -> 1.5 | E21: =E$14*(10-lgd*COUNTIF(Defaults!$AI21:$AR21,"<="&E$17)) -> 1.5 | F21: =F$14*(10-lgd*COUNTIF(Defaults!$AI21:$AR21,"<="&F$17)) -> 1.5 | G21: =G$14*(10-lgd*COUNTIF(Defaults!$AI21:$AR21,"<="&G$17)) -> 1.41 | H21: =H$14*(10-lgd*COUNTIF(Defaults!$AI21:$AR21,"<="&H$17)) -> 1.41 | I21: =I$14*(10-lgd*COUNTIF(Defaults!$AI21:$AR21,"<="&I$17)) -> 1.41 | ... U21: =U$14*(10-lgd*COUNTIF(Defaults!$AI21:$AR21,"<="&U$17)) -> 89.32 | W21: =MIN(B21,B$15) -> 0.1 | X21: =MIN(C21,C$15) -> 0.1 | Y21: =MIN(D21,D$15) -> 0.1 | Z21: =MIN(E21,E$15) -> 0.1 | AA21: =MIN(F21,F$15) -> 0.1 | AB21: =MIN(G21,G$15) -> 0.1 | AC21: =MIN(H21,H$15) -> 0.1 | AD21: =MIN(I21,I$15) -> 0.1 | ... AP21: =MIN(U21,U$15) -> 20.1 | AR21: =MIN(B21-W21,B$16) -> 0.1 | AS21: =MIN(C21-X21,C$16) -> 0.1 | AT21: =MIN(D21-Y21,D$16) -> 0.1 | AU21: =MIN(E21-Z21,E$16) -> 0.1 | AV21: =MIN(F21-AA21,F$16) -> 0.1 | AW21: =MIN(G21-AB21,G$16) -> 0.1 | AX21: =MIN(H21-AC21,H$16) -> 0.1 | AY21: =MIN(I21-AD21,I$16) -> 0.1 | ... BK21: =MIN(U21-AP21,U$16) -> 10.1 | BM21: =B21-W21-AR21 -> 1.3 | BN21: =C21-X21-AS21 -> 1.3 | BO21: =D21-Y21-AT21 -> 1.3 | BP21: =E21-Z21-AU21 -> 1.3 | BQ21: =F21-AA21-AV21 -> 1.3 | BR21: =G21-AB21-AW21 -> 1.21 | BS21: =H21-AC21-AX21 -> 1.21 | BT21: =I21-AD21-AY21 -> 1.21 | ... CF21: =U21-AP21-BK21 -> 59.12 | CH21: =SUM($B21:$U21) -> 116.2 | CI21: =SUM($W21:$AP21) -> 22 | CJ21: =SUM($AR21:$BK21) -> 12 | CK21: =SUM($BM21:$CF21) -> 82.2 | CL21: =IF(CI21<SUM($B$15:$U$15)-0.000000001,1,0) -> 0 | CM21: =IF(CJ21<SUM($B$16:$U$16)-0.000000001,1,0) -> 0
A22: 5 | B22: =B$14*(10-lgd*COUNTIF(Defaults!$AI22:$AR22,"<="&B$17)) -> 1.5 | C22: =C$14*(10-lgd*COUNTIF(Defaults!$AI22:$AR22,"<="&C$17)) -> 1.5 | D22: =D$14*(10-lgd*COUNTIF(Defaults!$AI22:$AR22,"<="&D$17)) -> 1.5 | E22: =E$14*(10-lgd*COUNTIF(Defaults!$AI22:$AR22,"<="&E$17)) -> 1.41 | F22: =F$14*(10-lgd*COUNTIF(Defaults!$AI22:$AR22,"<="&F$17)) -> 1.32 | G22: =G$14*(10-lgd*COUNTIF(Defaults!$AI22:$AR22,"<="&G$17)) -> 1.32 | H22: =H$14*(10-lgd*COUNTIF(Defaults!$AI22:$AR22,"<="&H$17)) -> 1.23 | I22: =I$14*(10-lgd*COUNTIF(Defaults!$AI22:$AR22,"<="&I$17)) -> 1.23 | ... U22: =U$14*(10-lgd*COUNTIF(Defaults!$AI22:$AR22,"<="&U$17)) -> 64.96 | W22: =MIN(B22,B$15) -> 0.1 | X22: =MIN(C22,C$15) -> 0.1 | Y22: =MIN(D22,D$15) -> 0.1 | Z22: =MIN(E22,E$15) -> 0.1 | AA22: =MIN(F22,F$15) -> 0.1 | AB22: =MIN(G22,G$15) -> 0.1 | AC22: =MIN(H22,H$15) -> 0.1 | AD22: =MIN(I22,I$15) -> 0.1 | ... AP22: =MIN(U22,U$15) -> 20.1 | AR22: =MIN(B22-W22,B$16) -> 0.1 | AS22: =MIN(C22-X22,C$16) -> 0.1 | AT22: =MIN(D22-Y22,D$16) -> 0.1 | AU22: =MIN(E22-Z22,E$16) -> 0.1 | AV22: =MIN(F22-AA22,F$16) -> 0.1 | AW22: =MIN(G22-AB22,G$16) -> 0.1 | AX22: =MIN(H22-AC22,H$16) -> 0.1 | AY22: =MIN(I22-AD22,I$16) -> 0.1 | ... BK22: =MIN(U22-AP22,U$16) -> 10.1 | BM22: =B22-W22-AR22 -> 1.3 | BN22: =C22-X22-AS22 -> 1.3 | BO22: =D22-Y22-AT22 -> 1.3 | BP22: =E22-Z22-AU22 -> 1.21 | BQ22: =F22-AA22-AV22 -> 1.12 | BR22: =G22-AB22-AW22 -> 1.12 | BS22: =H22-AC22-AX22 -> 1.03 | BT22: =I22-AD22-AY22 -> 1.03 | ... CF22: =U22-AP22-BK22 -> 34.76 | CH22: =SUM($B22:$U22) -> 88.15 | CI22: =SUM($W22:$AP22) -> 22 | CJ22: =SUM($AR22:$BK22) -> 12 | CK22: =SUM($BM22:$CF22) -> 54.15 | CL22: =IF(CI22<SUM($B$15:$U$15)-0.000000001,1,0) -> 0 | CM22: =IF(CJ22<SUM($B$16:$U$16)-0.000000001,1,0) -> 0
A23: 6 | B23: =B$14*(10-lgd*COUNTIF(Defaults!$AI23:$AR23,"<="&B$17)) -> 1.5 | C23: =C$14*(10-lgd*COUNTIF(Defaults!$AI23:$AR23,"<="&C$17)) -> 1.5 | D23: =D$14*(10-lgd*COUNTIF(Defaults!$AI23:$AR23,"<="&D$17)) -> 1.5 | E23: =E$14*(10-lgd*COUNTIF(Defaults!$AI23:$AR23,"<="&E$17)) -> 1.5 | F23: =F$14*(10-lgd*COUNTIF(Defaults!$AI23:$AR23,"<="&F$17)) -> 1.5 | G23: =G$14*(10-lgd*COUNTIF(Defaults!$AI23:$AR23,"<="&G$17)) -> 1.5 | H23: =H$14*(10-lgd*COUNTIF(Defaults!$AI23:$AR23,"<="&H$17)) -> 1.5 | I23: =I$14*(10-lgd*COUNTIF(Defaults!$AI23:$AR23,"<="&I$17)) -> 1.5 | ... U23: =U$14*(10-lgd*COUNTIF(Defaults!$AI23:$AR23,"<="&U$17)) -> 83.23 | W23: =MIN(B23,B$15) -> 0.1 | X23: =MIN(C23,C$15) -> 0.1 | Y23: =MIN(D23,D$15) -> 0.1 | Z23: =MIN(E23,E$15) -> 0.1 | AA23: =MIN(F23,F$15) -> 0.1 | AB23: =MIN(G23,G$15) -> 0.1 | AC23: =MIN(H23,H$15) -> 0.1 | AD23: =MIN(I23,I$15) -> 0.1 | ... AP23: =MIN(U23,U$15) -> 20.1 | AR23: =MIN(B23-W23,B$16) -> 0.1 | AS23: =MIN(C23-X23,C$16) -> 0.1 | AT23: =MIN(D23-Y23,D$16) -> 0.1 | AU23: =MIN(E23-Z23,E$16) -> 0.1 | AV23: =MIN(F23-AA23,F$16) -> 0.1 | AW23: =MIN(G23-AB23,G$16) -> 0.1 | AX23: =MIN(H23-AC23,H$16) -> 0.1 | AY23: =MIN(I23-AD23,I$16) -> 0.1 | ... BK23: =MIN(U23-AP23,U$16) -> 10.1 | BM23: =B23-W23-AR23 -> 1.3 | BN23: =C23-X23-AS23 -> 1.3 | BO23: =D23-Y23-AT23 -> 1.3 | BP23: =E23-Z23-AU23 -> 1.3 | BQ23: =F23-AA23-AV23 -> 1.3 | BR23: =G23-AB23-AW23 -> 1.3 | BS23: =H23-AC23-AX23 -> 1.3 | BT23: =I23-AD23-AY23 -> 1.3 | ... CF23: =U23-AP23-BK23 -> 53.03 | CH23: =SUM($B23:$U23) -> 110.74 | CI23: =SUM($W23:$AP23) -> 22 | CJ23: =SUM($AR23:$BK23) -> 12 | CK23: =SUM($BM23:$CF23) -> 76.74 | CL23: =IF(CI23<SUM($B$15:$U$15)-0.000000001,1,0) -> 0 | CM23: =IF(CJ23<SUM($B$16:$U$16)-0.000000001,1,0) -> 0
A24: 7 | B24: =B$14*(10-lgd*COUNTIF(Defaults!$AI24:$AR24,"<="&B$17)) -> 1.5 | C24: =C$14*(10-lgd*COUNTIF(Defaults!$AI24:$AR24,"<="&C$17)) -> 1.5 | D24: =D$14*(10-lgd*COUNTIF(Defaults!$AI24:$AR24,"<="&D$17)) -> 1.5 | E24: =E$14*(10-lgd*COUNTIF(Defaults!$AI24:$AR24,"<="&E$17)) -> 1.5 | F24: =F$14*(10-lgd*COUNTIF(Defaults!$AI24:$AR24,"<="&F$17)) -> 1.5 | G24: =G$14*(10-lgd*COUNTIF(Defaults!$AI24:$AR24,"<="&G$17)) -> 1.5 | H24: =H$14*(10-lgd*COUNTIF(Defaults!$AI24:$AR24,"<="&H$17)) -> 1.5 | I24: =I$14*(10-lgd*COUNTIF(Defaults!$AI24:$AR24,"<="&I$17)) -> 1.5 | ... U24: =U$14*(10-lgd*COUNTIF(Defaults!$AI24:$AR24,"<="&U$17)) -> 101.5 | W24: =MIN(B24,B$15) -> 0.1 | X24: =MIN(C24,C$15) -> 0.1 | Y24: =MIN(D24,D$15) -> 0.1 | Z24: =MIN(E24,E$15) -> 0.1 | AA24: =MIN(F24,F$15) -> 0.1 | AB24: =MIN(G24,G$15) -> 0.1 | AC24: =MIN(H24,H$15) -> 0.1 | AD24: =MIN(I24,I$15) -> 0.1 | ... AP24: =MIN(U24,U$15) -> 20.1 | AR24: =MIN(B24-W24,B$16) -> 0.1 | AS24: =MIN(C24-X24,C$16) -> 0.1 | AT24: =MIN(D24-Y24,D$16) -> 0.1 | AU24: =MIN(E24-Z24,E$16) -> 0.1 | AV24: =MIN(F24-AA24,F$16) -> 0.1 | AW24: =MIN(G24-AB24,G$16) -> 0.1 | AX24: =MIN(H24-AC24,H$16) -> 0.1 | AY24: =MIN(I24-AD24,I$16) -> 0.1 | ... BK24: =MIN(U24-AP24,U$16) -> 10.1 | BM24: =B24-W24-AR24 -> 1.3 | BN24: =C24-X24-AS24 -> 1.3 | BO24: =D24-Y24-AT24 -> 1.3 | BP24: =E24-Z24-AU24 -> 1.3 | BQ24: =F24-AA24-AV24 -> 1.3 | BR24: =G24-AB24-AW24 -> 1.3 | BS24: =H24-AC24-AX24 -> 1.3 | BT24: =I24-AD24-AY24 -> 1.3 | ... CF24: =U24-AP24-BK24 -> 71.3 | CH24: =SUM($B24:$U24) -> 130 | CI24: =SUM($W24:$AP24) -> 22 | CJ24: =SUM($AR24:$BK24) -> 12 | CK24: =SUM($BM24:$CF24) -> 96 | CL24: =IF(CI24<SUM($B$15:$U$15)-0.000000001,1,0) -> 0 | CM24: =IF(CJ24<SUM($B$16:$U$16)-0.000000001,1,0) -> 0
A25: 8 | B25: =B$14*(10-lgd*COUNTIF(Defaults!$AI25:$AR25,"<="&B$17)) -> 1.5 | C25: =C$14*(10-lgd*COUNTIF(Defaults!$AI25:$AR25,"<="&C$17)) -> 1.5 | D25: =D$14*(10-lgd*COUNTIF(Defaults!$AI25:$AR25,"<="&D$17)) -> 1.5 | E25: =E$14*(10-lgd*COUNTIF(Defaults!$AI25:$AR25,"<="&E$17)) -> 1.5 | F25: =F$14*(10-lgd*COUNTIF(Defaults!$AI25:$AR25,"<="&F$17)) -> 1.5 | G25: =G$14*(10-lgd*COUNTIF(Defaults!$AI25:$AR25,"<="&G$17)) -> 1.5 | H25: =H$14*(10-lgd*COUNTIF(Defaults!$AI25:$AR25,"<="&H$17)) -> 1.5 | I25: =I$14*(10-lgd*COUNTIF(Defaults!$AI25:$AR25,"<="&I$17)) -> 1.5 | ... U25: =U$14*(10-lgd*COUNTIF(Defaults!$AI25:$AR25,"<="&U$17)) -> 95.41 | W25: =MIN(B25,B$15) -> 0.1 | X25: =MIN(C25,C$15) -> 0.1 | Y25: =MIN(D25,D$15) -> 0.1 | Z25: =MIN(E25,E$15) -> 0.1 | AA25: =MIN(F25,F$15) -> 0.1 | AB25: =MIN(G25,G$15) -> 0.1 | AC25: =MIN(H25,H$15) -> 0.1 | AD25: =MIN(I25,I$15) -> 0.1 | ... AP25: =MIN(U25,U$15) -> 20.1 | AR25: =MIN(B25-W25,B$16) -> 0.1 | AS25: =MIN(C25-X25,C$16) -> 0.1 | AT25: =MIN(D25-Y25,D$16) -> 0.1 | AU25: =MIN(E25-Z25,E$16) -> 0.1 | AV25: =MIN(F25-AA25,F$16) -> 0.1 | AW25: =MIN(G25-AB25,G$16) -> 0.1 | AX25: =MIN(H25-AC25,H$16) -> 0.1 | AY25: =MIN(I25-AD25,I$16) -> 0.1 | ... BK25: =MIN(U25-AP25,U$16) -> 10.1 | BM25: =B25-W25-AR25 -> 1.3 | BN25: =C25-X25-AS25 -> 1.3 | BO25: =D25-Y25-AT25 -> 1.3 | BP25: =E25-Z25-AU25 -> 1.3 | BQ25: =F25-AA25-AV25 -> 1.3 | BR25: =G25-AB25-AW25 -> 1.3 | BS25: =H25-AC25-AX25 -> 1.3 | BT25: =I25-AD25-AY25 -> 1.3 | ... CF25: =U25-AP25-BK25 -> 65.21 | CH25: =SUM($B25:$U25) -> 123.37 | CI25: =SUM($W25:$AP25) -> 22 | CJ25: =SUM($AR25:$BK25) -> 12 | CK25: =SUM($BM25:$CF25) -> 89.37 | CL25: =IF(CI25<SUM($B$15:$U$15)-0.000000001,1,0) -> 0 | CM25: =IF(CJ25<SUM($B$16:$U$16)-0.000000001,1,0) -> 0
A26: 9 | B26: =B$14*(10-lgd*COUNTIF(Defaults!$AI26:$AR26,"<="&B$17)) -> 1.5 | C26: =C$14*(10-lgd*COUNTIF(Defaults!$AI26:$AR26,"<="&C$17)) -> 1.5 | D26: =D$14*(10-lgd*COUNTIF(Defaults!$AI26:$AR26,"<="&D$17)) -> 1.5 | E26: =E$14*(10-lgd*COUNTIF(Defaults!$AI26:$AR26,"<="&E$17)) -> 1.5 | F26: =F$14*(10-lgd*COUNTIF(Defaults!$AI26:$AR26,"<="&F$17)) -> 1.5 | G26: =G$14*(10-lgd*COUNTIF(Defaults!$AI26:$AR26,"<="&G$17)) -> 1.5 | H26: =H$14*(10-lgd*COUNTIF(Defaults!$AI26:$AR26,"<="&H$17)) -> 1.5 | I26: =I$14*(10-lgd*COUNTIF(Defaults!$AI26:$AR26,"<="&I$17)) -> 1.5 | ... U26: =U$14*(10-lgd*COUNTIF(Defaults!$AI26:$AR26,"<="&U$17)) -> 89.32 | W26: =MIN(B26,B$15) -> 0.1 | X26: =MIN(C26,C$15) -> 0.1 | Y26: =MIN(D26,D$15) -> 0.1 | Z26: =MIN(E26,E$15) -> 0.1 | AA26: =MIN(F26,F$15) -> 0.1 | AB26: =MIN(G26,G$15) -> 0.1 | AC26: =MIN(H26,H$15) -> 0.1 | AD26: =MIN(I26,I$15) -> 0.1 | ... AP26: =MIN(U26,U$15) -> 20.1 | AR26: =MIN(B26-W26,B$16) -> 0.1 | AS26: =MIN(C26-X26,C$16) -> 0.1 | AT26: =MIN(D26-Y26,D$16) -> 0.1 | AU26: =MIN(E26-Z26,E$16) -> 0.1 | AV26: =MIN(F26-AA26,F$16) -> 0.1 | AW26: =MIN(G26-AB26,G$16) -> 0.1 | AX26: =MIN(H26-AC26,H$16) -> 0.1 | AY26: =MIN(I26-AD26,I$16) -> 0.1 | ... BK26: =MIN(U26-AP26,U$16) -> 10.1 | BM26: =B26-W26-AR26 -> 1.3 | BN26: =C26-X26-AS26 -> 1.3 | BO26: =D26-Y26-AT26 -> 1.3 | BP26: =E26-Z26-AU26 -> 1.3 | BQ26: =F26-AA26-AV26 -> 1.3 | BR26: =G26-AB26-AW26 -> 1.3 | BS26: =H26-AC26-AX26 -> 1.3 | BT26: =I26-AD26-AY26 -> 1.3 | ... CF26: =U26-AP26-BK26 -> 59.12 | CH26: =SUM($B26:$U26) -> 117.01 | CI26: =SUM($W26:$AP26) -> 22 | CJ26: =SUM($AR26:$BK26) -> 12 | CK26: =SUM($BM26:$CF26) -> 83.01 | CL26: =IF(CI26<SUM($B$15:$U$15)-0.000000001,1,0) -> 0 | CM26: =IF(CJ26<SUM($B$16:$U$16)-0.000000001,1,0) -> 0
A27: 10 | B27: =B$14*(10-lgd*COUNTIF(Defaults!$AI27:$AR27,"<="&B$17)) -> 1.5 | C27: =C$14*(10-lgd*COUNTIF(Defaults!$AI27:$AR27,"<="&C$17)) -> 1.5 | D27: =D$14*(10-lgd*COUNTIF(Defaults!$AI27:$AR27,"<="&D$17)) -> 1.5 | E27: =E$14*(10-lgd*COUNTIF(Defaults!$AI27:$AR27,"<="&E$17)) -> 1.5 | F27: =F$14*(10-lgd*COUNTIF(Defaults!$AI27:$AR27,"<="&F$17)) -> 1.5 | G27: =G$14*(10-lgd*COUNTIF(Defaults!$AI27:$AR27,"<="&G$17)) -> 1.5 | H27: =H$14*(10-lgd*COUNTIF(Defaults!$AI27:$AR27,"<="&H$17)) -> 1.5 | I27: =I$14*(10-lgd*COUNTIF(Defaults!$AI27:$AR27,"<="&I$17)) -> 1.5 | ... U27: =U$14*(10-lgd*COUNTIF(Defaults!$AI27:$AR27,"<="&U$17)) -> 95.41 | W27: =MIN(B27,B$15) -> 0.1 | X27: =MIN(C27,C$15) -> 0.1 | Y27: =MIN(D27,D$15) -> 0.1 | Z27: =MIN(E27,E$15) -> 0.1 | AA27: =MIN(F27,F$15) -> 0.1 | AB27: =MIN(G27,G$15) -> 0.1 | AC27: =MIN(H27,H$15) -> 0.1 | AD27: =MIN(I27,I$15) -> 0.1 | ... AP27: =MIN(U27,U$15) -> 20.1 | AR27: =MIN(B27-W27,B$16) -> 0.1 | AS27: =MIN(C27-X27,C$16) -> 0.1 | AT27: =MIN(D27-Y27,D$16) -> 0.1 | AU27: =MIN(E27-Z27,E$16) -> 0.1 | AV27: =MIN(F27-AA27,F$16) -> 0.1 | AW27: =MIN(G27-AB27,G$16) -> 0.1 | AX27: =MIN(H27-AC27,H$16) -> 0.1 | AY27: =MIN(I27-AD27,I$16) -> 0.1 | ... BK27: =MIN(U27-AP27,U$16) -> 10.1 | BM27: =B27-W27-AR27 -> 1.3 | BN27: =C27-X27-AS27 -> 1.3 | BO27: =D27-Y27-AT27 -> 1.3 | BP27: =E27-Z27-AU27 -> 1.3 | BQ27: =F27-AA27-AV27 -> 1.3 | BR27: =G27-AB27-AW27 -> 1.3 | BS27: =H27-AC27-AX27 -> 1.3 | BT27: =I27-AD27-AY27 -> 1.3 | ... CF27: =U27-AP27-BK27 -> 65.21 | CH27: =SUM($B27:$U27) -> 123.82 | CI27: =SUM($W27:$AP27) -> 22 | CJ27: =SUM($AR27:$BK27) -> 12 | CK27: =SUM($BM27:$CF27) -> 89.82 | CL27: =IF(CI27<SUM($B$15:$U$15)-0.000000001,1,0) -> 0 | CM27: =IF(CJ27<SUM($B$16:$U$16)-0.000000001,1,0) -> 0
A28: 11 | B28: =B$14*(10-lgd*COUNTIF(Defaults!$AI28:$AR28,"<="&B$17)) -> 1.5 | C28: =C$14*(10-lgd*COUNTIF(Defaults!$AI28:$AR28,"<="&C$17)) -> 1.5 | D28: =D$14*(10-lgd*COUNTIF(Defaults!$AI28:$AR28,"<="&D$17)) -> 1.5 | E28: =E$14*(10-lgd*COUNTIF(Defaults!$AI28:$AR28,"<="&E$17)) -> 1.5 | F28: =F$14*(10-lgd*COUNTIF(Defaults!$AI28:$AR28,"<="&F$17)) -> 1.5 | G28: =G$14*(10-lgd*COUNTIF(Defaults!$AI28:$AR28,"<="&G$17)) -> 1.5 | H28: =H$14*(10-lgd*COUNTIF(Defaults!$AI28:$AR28,"<="&H$17)) -> 1.5 | I28: =I$14*(10-lgd*COUNTIF(Defaults!$AI28:$AR28,"<="&I$17)) -> 1.5 | ... U28: =U$14*(10-lgd*COUNTIF(Defaults!$AI28:$AR28,"<="&U$17)) -> 101.5 | W28: =MIN(B28,B$15) -> 0.1 | X28: =MIN(C28,C$15) -> 0.1 | Y28: =MIN(D28,D$15) -> 0.1 | Z28: =MIN(E28,E$15) -> 0.1 | AA28: =MIN(F28,F$15) -> 0.1 | AB28: =MIN(G28,G$15) -> 0.1 | AC28: =MIN(H28,H$15) -> 0.1 | AD28: =MIN(I28,I$15) -> 0.1 | ... AP28: =MIN(U28,U$15) -> 20.1 | AR28: =MIN(B28-W28,B$16) -> 0.1 | AS28: =MIN(C28-X28,C$16) -> 0.1 | AT28: =MIN(D28-Y28,D$16) -> 0.1 | AU28: =MIN(E28-Z28,E$16) -> 0.1 | AV28: =MIN(F28-AA28,F$16) -> 0.1 | AW28: =MIN(G28-AB28,G$16) -> 0.1 | AX28: =MIN(H28-AC28,H$16) -> 0.1 | AY28: =MIN(I28-AD28,I$16) -> 0.1 | ... BK28: =MIN(U28-AP28,U$16) -> 10.1 | BM28: =B28-W28-AR28 -> 1.3 | BN28: =C28-X28-AS28 -> 1.3 | BO28: =D28-Y28-AT28 -> 1.3 | BP28: =E28-Z28-AU28 -> 1.3 | BQ28: =F28-AA28-AV28 -> 1.3 | BR28: =G28-AB28-AW28 -> 1.3 | BS28: =H28-AC28-AX28 -> 1.3 | BT28: =I28-AD28-AY28 -> 1.3 | ... CF28: =U28-AP28-BK28 -> 71.3 | CH28: =SUM($B28:$U28) -> 130 | CI28: =SUM($W28:$AP28) -> 22 | CJ28: =SUM($AR28:$BK28) -> 12 | CK28: =SUM($BM28:$CF28) -> 96 | CL28: =IF(CI28<SUM($B$15:$U$15)-0.000000001,1,0) -> 0 | CM28: =IF(CJ28<SUM($B$16:$U$16)-0.000000001,1,0) -> 0
A29: 12 | B29: =B$14*(10-lgd*COUNTIF(Defaults!$AI29:$AR29,"<="&B$17)) -> 1.5 | C29: =C$14*(10-lgd*COUNTIF(Defaults!$AI29:$AR29,"<="&C$17)) -> 1.5 | D29: =D$14*(10-lgd*COUNTIF(Defaults!$AI29:$AR29,"<="&D$17)) -> 1.5 | E29: =E$14*(10-lgd*COUNTIF(Defaults!$AI29:$AR29,"<="&E$17)) -> 1.5 | F29: =F$14*(10-lgd*COUNTIF(Defaults!$AI29:$AR29,"<="&F$17)) -> 1.5 | G29: =G$14*(10-lgd*COUNTIF(Defaults!$AI29:$AR29,"<="&G$17)) -> 1.41 | H29: =H$14*(10-lgd*COUNTIF(Defaults!$AI29:$AR29,"<="&H$17)) -> 1.41 | I29: =I$14*(10-lgd*COUNTIF(Defaults!$AI29:$AR29,"<="&I$17)) -> 1.41 | ... U29: =U$14*(10-lgd*COUNTIF(Defaults!$AI29:$AR29,"<="&U$17)) -> 95.41 | W29: =MIN(B29,B$15) -> 0.1 | X29: =MIN(C29,C$15) -> 0.1 | Y29: =MIN(D29,D$15) -> 0.1 | Z29: =MIN(E29,E$15) -> 0.1 | AA29: =MIN(F29,F$15) -> 0.1 | AB29: =MIN(G29,G$15) -> 0.1 | AC29: =MIN(H29,H$15) -> 0.1 | AD29: =MIN(I29,I$15) -> 0.1 | ... AP29: =MIN(U29,U$15) -> 20.1 | AR29: =MIN(B29-W29,B$16) -> 0.1 | AS29: =MIN(C29-X29,C$16) -> 0.1 | AT29: =MIN(D29-Y29,D$16) -> 0.1 | AU29: =MIN(E29-Z29,E$16) -> 0.1 | AV29: =MIN(F29-AA29,F$16) -> 0.1 | AW29: =MIN(G29-AB29,G$16) -> 0.1 | AX29: =MIN(H29-AC29,H$16) -> 0.1 | AY29: =MIN(I29-AD29,I$16) -> 0.1 | ... BK29: =MIN(U29-AP29,U$16) -> 10.1 | BM29: =B29-W29-AR29 -> 1.3 | BN29: =C29-X29-AS29 -> 1.3 | BO29: =D29-Y29-AT29 -> 1.3 | BP29: =E29-Z29-AU29 -> 1.3 | BQ29: =F29-AA29-AV29 -> 1.3 | BR29: =G29-AB29-AW29 -> 1.21 | BS29: =H29-AC29-AX29 -> 1.21 | BT29: =I29-AD29-AY29 -> 1.21 | ... CF29: =U29-AP29-BK29 -> 65.21 | CH29: =SUM($B29:$U29) -> 122.65 | CI29: =SUM($W29:$AP29) -> 22 | CJ29: =SUM($AR29:$BK29) -> 12 | CK29: =SUM($BM29:$CF29) -> 88.65 | CL29: =IF(CI29<SUM($B$15:$U$15)-0.000000001,1,0) -> 0 | CM29: =IF(CJ29<SUM($B$16:$U$16)-0.000000001,1,0) -> 0
... A1017: 1000 | B1017: =B$14*(10-lgd*COUNTIF(Defaults!$AI1017:$AR1017,"<="&B$17)) -> 1.5 | C1017: =C$14*(10-lgd*COUNTIF(Defaults!$AI1017:$AR1017,"<="&C$17)) -> 1.5 | D1017: =D$14*(10-lgd*COUNTIF(Defaults!$AI1017:$AR1017,"<="&D$17)) -> 1.5 | E1017: =E$14*(10-lgd*COUNTIF(Defaults!$AI1017:$AR1017,"<="&E$17)) -> 1.5 | F1017: =F$14*(10-lgd*COUNTIF(Defaults!$AI1017:$AR1017,"<="&F$17)) -> 1.5 | G1017: =G$14*(10-lgd*COUNTIF(Defaults!$AI1017:$AR1017,"<="&G$17)) -> 1.5 | H1017: =H$14*(10-lgd*COUNTIF(Defaults!$AI1017:$AR1017,"<="&H$17)) -> 1.5 | I1017: =I$14*(10-lgd*COUNTIF(Defaults!$AI1017:$AR1017,"<="&I$17)) -> 1.5 | ... U1017: =U$14*(10-lgd*COUNTIF(Defaults!$AI1017:$AR1017,"<="&U$17)) -> 95.41 | W1017: =MIN(B1017,B$15) -> 0.1 | X1017: =MIN(C1017,C$15) -> 0.1 | Y1017: =MIN(D1017,D$15) -> 0.1 | Z1017: =MIN(E1017,E$15) -> 0.1 | AA1017: =MIN(F1017,F$15) -> 0.1 | AB1017: =MIN(G1017,G$15) -> 0.1 | AC1017: =MIN(H1017,H$15) -> 0.1 | AD1017: =MIN(I1017,I$15) -> 0.1 | ... AP1017: =MIN(U1017,U$15) -> 20.1 | AR1017: =MIN(B1017-W1017,B$16) -> 0.1 | AS1017: =MIN(C1017-X1017,C$16) -> 0.1 | AT1017: =MIN(D1017-Y1017,D$16) -> 0.1 | AU1017: =MIN(E1017-Z1017,E$16) -> 0.1 | AV1017: =MIN(F1017-AA1017,F$16) -> 0.1 | AW1017: =MIN(G1017-AB1017,G$16) -> 0.1 | AX1017: =MIN(H1017-AC1017,H$16) -> 0.1 | AY1017: =MIN(I1017-AD1017,I$16) -> 0.1 | ... BK1017: =MIN(U1017-AP1017,U$16) -> 10.1 | BM1017: =B1017-W1017-AR1017 -> 1.3 | BN1017: =C1017-X1017-AS1017 -> 1.3 | BO1017: =D1017-Y1017-AT1017 -> 1.3 | BP1017: =E1017-Z1017-AU1017 -> 1.3 | BQ1017: =F1017-AA1017-AV1017 -> 1.3 | BR1017: =G1017-AB1017-AW1017 -> 1.3 | BS1017: =H1017-AC1017-AX1017 -> 1.3 | BT1017: =I1017-AD1017-AY1017 -> 1.3 | ... CF1017: =U1017-AP1017-BK1017 -> 65.21 | CH1017: =SUM($B1017:$U1017) -> 123.82 | CI1017: =SUM($W1017:$AP1017) -> 22 | CJ1017: =SUM($AR1017:$BK1017) -> 12 | CK1017: =SUM($BM1017:$CF1017) -> 89.82 | CL1017: =IF(CI1017<SUM($B$15:$U$15)-0.000000001,1,0) -> 0 | CM1017: =IF(CJ1017<SUM($B$16:$U$16)-0.000000001,1,0) -> 0

Sheet Statistics
A1: Statistics across the 1000 cases ($MM, undiscounted)
A3: Total cash received over the 5 years
B4: No-default amount | C4: Mean | D4: Std dev | E4: Std error of the mean | F4: Min | G4: 5th pct | H4: Median | I4: 95th pct | J4: Max | K4: Mean / no-default amount | L4: Share of cases below the no-default amount
A5: Collateral pool | B5: =SUM(Inputs!$C$25:$C$44) -> 130 | C5: =AVERAGE(CashFlows!$CH$18:$CH$1017) -> 117.28336 | D5: =STDEV(CashFlows!$CH$18:$CH$1017) -> 12.032269 | E5: =D5/SQRT(Number_of_Cases) -> 0.38049376 | F5: =MIN(CashFlows!$CH$18:$CH$1017) -> 64.48 | G5: =PERCENTILE(CashFlows!$CH$18:$CH$1017,0.05) -> 94.6855 | H5: =MEDIAN(CashFlows!$CH$18:$CH$1017) -> 122.29 | I5: =PERCENTILE(CashFlows!$CH$18:$CH$1017,0.95) -> 130 | J5: =MAX(CashFlows!$CH$18:$CH$1017) -> 130 | K5: =IF(B5=0,0,C5/B5) -> 0.90217969 | L5: =COUNTIF(CashFlows!$CH$18:$CH$1017,"<"&(B5-0.000000001))/Number_of_Cases -> 0.743
A6: Class A | B6: =SUM(Inputs!$D$25:$D$44) -> 22 | C6: =AVERAGE(CashFlows!$CI$18:$CI$1017) -> 22 | D6: =STDEV(CashFlows!$CI$18:$CI$1017) -> 0 | E6: =D6/SQRT(Number_of_Cases) -> 0 | F6: =MIN(CashFlows!$CI$18:$CI$1017) -> 22 | G6: =PERCENTILE(CashFlows!$CI$18:$CI$1017,0.05) -> 22 | H6: =MEDIAN(CashFlows!$CI$18:$CI$1017) -> 22 | I6: =PERCENTILE(CashFlows!$CI$18:$CI$1017,0.95) -> 22 | J6: =MAX(CashFlows!$CI$18:$CI$1017) -> 22 | K6: =IF(B6=0,0,C6/B6) -> 1 | L6: =COUNTIF(CashFlows!$CI$18:$CI$1017,"<"&(B6-0.000000001))/Number_of_Cases -> 0
A7: Class B | B7: =SUM(Inputs!$E$25:$E$44) -> 12 | C7: =AVERAGE(CashFlows!$CJ$18:$CJ$1017) -> 12 | D7: =STDEV(CashFlows!$CJ$18:$CJ$1017) -> 0 | E7: =D7/SQRT(Number_of_Cases) -> 0 | F7: =MIN(CashFlows!$CJ$18:$CJ$1017) -> 12 | G7: =PERCENTILE(CashFlows!$CJ$18:$CJ$1017,0.05) -> 12 | H7: =MEDIAN(CashFlows!$CJ$18:$CJ$1017) -> 12 | I7: =PERCENTILE(CashFlows!$CJ$18:$CJ$1017,0.95) -> 12 | J7: =MAX(CashFlows!$CJ$18:$CJ$1017) -> 12 | K7: =IF(B7=0,0,C7/B7) -> 1 | L7: =COUNTIF(CashFlows!$CJ$18:$CJ$1017,"<"&(B7-0.000000001))/Number_of_Cases -> 0
A8: Equity (bank) | B8: =B5-B6-B7 -> 96 | C8: =AVERAGE(CashFlows!$CK$18:$CK$1017) -> 83.28336 | D8: =STDEV(CashFlows!$CK$18:$CK$1017) -> 12.032269 | E8: =D8/SQRT(Number_of_Cases) -> 0.38049376 | F8: =MIN(CashFlows!$CK$18:$CK$1017) -> 30.48 | G8: =PERCENTILE(CashFlows!$CK$18:$CK$1017,0.05) -> 60.6855 | H8: =MEDIAN(CashFlows!$CK$18:$CK$1017) -> 88.29 | I8: =PERCENTILE(CashFlows!$CK$18:$CK$1017,0.95) -> 96 | J8: =MAX(CashFlows!$CK$18:$CK$1017) -> 96 | K8: =IF(B8=0,0,C8/B8) -> 0.867535 | L8: =COUNTIF(CashFlows!$CK$18:$CK$1017,"<"&(B8-0.000000001))/Number_of_Cases -> 0.743
A9: Std error of the mean = std dev / square root of the number of cases. It treats the cases as independent; moment matching makes them slightly dependent, so it is approximate.
A11: Number of bonds defaulting within 5 years
A12: Defaults | B12: Cases | C12: Simulated | D12: If independent (binomial) | E12: Avg pool cash | F12: Avg equity cash
A13: 0 | B13: =COUNTIF(Defaults!$AT$18:$AT$1017,A13) -> 257 | C13: =B13/Number_of_Cases -> 0.257 | D13: =BINOMDIST(A13,10,1-(1-pd_annual)^5,FALSE) -> 0.12988579 | E13: =IF(B13=0,"",AVERAGEIF(Defaults!$AT$18:$AT$1017,A13,CashFlows!$CH$18:$CH$1017)) -> 130 | F13: =IF(B13=0,"",AVERAGEIF(Defaults!$AT$18:$AT$1017,A13,CashFlows!$CK$18:$CK$1017)) -> 96
A14: 1 | B14: =COUNTIF(Defaults!$AT$18:$AT$1017,A14) -> 253 | C14: =B14/Number_of_Cases -> 0.253 | D14: =BINOMDIST(A14,10,1-(1-pd_annual)^5,FALSE) -> 0.29410432 | E14: =IF(B14=0,"",AVERAGEIF(Defaults!$AT$18:$AT$1017,A14,CashFlows!$CH$18:$CH$1017)) -> 123.1313 | F14: =IF(B14=0,"",AVERAGEIF(Defaults!$AT$18:$AT$1017,A14,CashFlows!$CK$18:$CK$1017)) -> 89.131304
A15: 2 | B15: =COUNTIF(Defaults!$AT$18:$AT$1017,A15) -> 200 | C15: =B15/Number_of_Cases -> 0.2 | D15: =BINOMDIST(A15,10,1-(1-pd_annual)^5,FALSE) -> 0.29967719 | E15: =IF(B15=0,"",AVERAGEIF(Defaults!$AT$18:$AT$1017,A15,CashFlows!$CH$18:$CH$1017)) -> 116.0857 | F15: =IF(B15=0,"",AVERAGEIF(Defaults!$AT$18:$AT$1017,A15,CashFlows!$CK$18:$CK$1017)) -> 82.0857
A16: 3 | B16: =COUNTIF(Defaults!$AT$18:$AT$1017,A16) -> 131 | C16: =B16/Number_of_Cases -> 0.131 | D16: =BINOMDIST(A16,10,1-(1-pd_annual)^5,FALSE) -> 0.18095149 | E16: =IF(B16=0,"",AVERAGEIF(Defaults!$AT$18:$AT$1017,A16,CashFlows!$CH$18:$CH$1017)) -> 109.13374 | F16: =IF(B16=0,"",AVERAGEIF(Defaults!$AT$18:$AT$1017,A16,CashFlows!$CK$18:$CK$1017)) -> 75.13374
A17: 4 | B17: =COUNTIF(Defaults!$AT$18:$AT$1017,A17) -> 77 | C17: =B17/Number_of_Cases -> 0.077 | D17: =BINOMDIST(A17,10,1-(1-pd_annual)^5,FALSE) -> 0.071703439 | E17: =IF(B17=0,"",AVERAGEIF(Defaults!$AT$18:$AT$1017,A17,CashFlows!$CH$18:$CH$1017)) -> 101.9126 | F17: =IF(B17=0,"",AVERAGEIF(Defaults!$AT$18:$AT$1017,A17,CashFlows!$CK$18:$CK$1017)) -> 67.912597
A18: 5 | B18: =COUNTIF(Defaults!$AT$18:$AT$1017,A18) -> 49 | C18: =B18/Number_of_Cases -> 0.049 | D18: =BINOMDIST(A18,10,1-(1-pd_annual)^5,FALSE) -> 0.019483231 | E18: =IF(B18=0,"",AVERAGEIF(Defaults!$AT$18:$AT$1017,A18,CashFlows!$CH$18:$CH$1017)) -> 94.96551 | F18: =IF(B18=0,"",AVERAGEIF(Defaults!$AT$18:$AT$1017,A18,CashFlows!$CK$18:$CK$1017)) -> 60.96551
A19: 6 | B19: =COUNTIF(Defaults!$AT$18:$AT$1017,A19) -> 16 | C19: =B19/Number_of_Cases -> 0.016 | D19: =BINOMDIST(A19,10,1-(1-pd_annual)^5,FALSE) -> 0.0036763724 | E19: =IF(B19=0,"",AVERAGEIF(Defaults!$AT$18:$AT$1017,A19,CashFlows!$CH$18:$CH$1017)) -> 87.536875 | F19: =IF(B19=0,"",AVERAGEIF(Defaults!$AT$18:$AT$1017,A19,CashFlows!$CK$18:$CK$1017)) -> 53.536875
A20: 7 | B20: =COUNTIF(Defaults!$AT$18:$AT$1017,A20) -> 11 | C20: =B20/Number_of_Cases -> 0.011 | D20: =BINOMDIST(A20,10,1-(1-pd_annual)^5,FALSE) -> 0.00047568692 | E20: =IF(B20=0,"",AVERAGEIF(Defaults!$AT$18:$AT$1017,A20,CashFlows!$CH$18:$CH$1017)) -> 79.940909 | F20: =IF(B20=0,"",AVERAGEIF(Defaults!$AT$18:$AT$1017,A20,CashFlows!$CK$18:$CK$1017)) -> 45.940909
A21: 8 | B21: =COUNTIF(Defaults!$AT$18:$AT$1017,A21) -> 5 | C21: =B21/Number_of_Cases -> 0.005 | D21: =BINOMDIST(A21,10,1-(1-pd_annual)^5,FALSE) -> 4.039171e-05 | E21: =IF(B21=0,"",AVERAGEIF(Defaults!$AT$18:$AT$1017,A21,CashFlows!$CH$18:$CH$1017)) -> 72.496 | F21: =IF(B21=0,"",AVERAGEIF(Defaults!$AT$18:$AT$1017,A21,CashFlows!$CK$18:$CK$1017)) -> 38.496
A22: 9 | B22: =COUNTIF(Defaults!$AT$18:$AT$1017,A22) -> 1 | C22: =B22/Number_of_Cases -> 0.001 | D22: =BINOMDIST(A22,10,1-(1-pd_annual)^5,FALSE) -> 2.0324482e-06 | E22: =IF(B22=0,"",AVERAGEIF(Defaults!$AT$18:$AT$1017,A22,CashFlows!$CH$18:$CH$1017)) -> 64.48 | F22: =IF(B22=0,"",AVERAGEIF(Defaults!$AT$18:$AT$1017,A22,CashFlows!$CK$18:$CK$1017)) -> 30.48
A23: 10 | B23: =COUNTIF(Defaults!$AT$18:$AT$1017,A23) -> 0 | C23: =B23/Number_of_Cases -> 0 | D23: =BINOMDIST(A23,10,1-(1-pd_annual)^5,FALSE) -> 4.6021338e-08 | E23: =IF(B23=0,"",AVERAGEIF(Defaults!$AT$18:$AT$1017,A23,CashFlows!$CH$18:$CH$1017)) | F23: =IF(B23=0,"",AVERAGEIF(Defaults!$AT$18:$AT$1017,A23,CashFlows!$CK$18:$CK$1017))
A26: Quarterly cash flows
A27: Quarter | B27: Pool promised | C27: Pool expected (exact) | D27: Pool mean | E27: Pool 5th pct | F27: Pool 95th pct | G27: Class A mean | H27: Class B mean | I27: Equity mean | J27: Equity 5th pct | K27: Equity 95th pct
A28: 1 | B28: =Inputs!$C$25 -> 1.5 | C28: =B28*((1-lgd)+lgd*(1-pd_annual)^(A28/4)) -> 1.4908618 | D28: =AVERAGE(CashFlows!$B$18:$B$1017) -> 1.49091 | E28: =PERCENTILE(CashFlows!$B$18:$B$1017,0.05) -> 1.41 | F28: =PERCENTILE(CashFlows!$B$18:$B$1017,0.95) -> 1.5 | G28: =AVERAGE(CashFlows!$W$18:$W$1017) -> 0.1 | H28: =AVERAGE(CashFlows!$AR$18:$AR$1017) -> 0.1 | I28: =AVERAGE(CashFlows!$BM$18:$BM$1017) -> 1.29091 | J28: =PERCENTILE(CashFlows!$BM$18:$BM$1017,0.05) -> 1.21 | K28: =PERCENTILE(CashFlows!$BM$18:$BM$1017,0.95) -> 1.3
A29: 2 | B29: =Inputs!$C$26 -> 1.5 | C29: =B29*((1-lgd)+lgd*(1-pd_annual)^(A29/4)) -> 1.4818163 | D29: =AVERAGE(CashFlows!$C$18:$C$1017) -> 1.48155 | E29: =PERCENTILE(CashFlows!$C$18:$C$1017,0.05) -> 1.41 | F29: =PERCENTILE(CashFlows!$C$18:$C$1017,0.95) -> 1.5 | G29: =AVERAGE(CashFlows!$X$18:$X$1017) -> 0.1 | H29: =AVERAGE(CashFlows!$AS$18:$AS$1017) -> 0.1 | I29: =AVERAGE(CashFlows!$BN$18:$BN$1017) -> 1.28155 | J29: =PERCENTILE(CashFlows!$BN$18:$BN$1017,0.05) -> 1.21 | K29: =PERCENTILE(CashFlows!$BN$18:$BN$1017,0.95) -> 1.3
A30: 3 | B30: =Inputs!$C$27 -> 1.5 | C30: =B30*((1-lgd)+lgd*(1-pd_annual)^(A30/4)) -> 1.4728627 | D30: =AVERAGE(CashFlows!$D$18:$D$1017) -> 1.47264 | E30: =PERCENTILE(CashFlows!$D$18:$D$1017,0.05) -> 1.32 | F30: =PERCENTILE(CashFlows!$D$18:$D$1017,0.95) -> 1.5 | G30: =AVERAGE(CashFlows!$Y$18:$Y$1017) -> 0.1 | H30: =AVERAGE(CashFlows!$AT$18:$AT$1017) -> 0.1 | I30: =AVERAGE(CashFlows!$BO$18:$BO$1017) -> 1.27264 | J30: =PERCENTILE(CashFlows!$BO$18:$BO$1017,0.05) -> 1.12 | K30: =PERCENTILE(CashFlows!$BO$18:$BO$1017,0.95) -> 1.3
A31: 4 | B31: =Inputs!$C$28 -> 1.5 | C31: =B31*((1-lgd)+lgd*(1-pd_annual)^(A31/4)) -> 1.464 | D31: =AVERAGE(CashFlows!$E$18:$E$1017) -> 1.46274 | E31: =PERCENTILE(CashFlows!$E$18:$E$1017,0.05) -> 1.32 | F31: =PERCENTILE(CashFlows!$E$18:$E$1017,0.95) -> 1.5 | G31: =AVERAGE(CashFlows!$Z$18:$Z$1017) -> 0.1 | H31: =AVERAGE(CashFlows!$AU$18:$AU$1017) -> 0.1 | I31: =AVERAGE(CashFlows!$BP$18:$BP$1017) -> 1.26274 | J31: =PERCENTILE(CashFlows!$BP$18:$BP$1017,0.05) -> 1.12 | K31: =PERCENTILE(CashFlows!$BP$18:$BP$1017,0.95) -> 1.3
A32: 5 | B32: =Inputs!$C$29 -> 1.5 | C32: =B32*((1-lgd)+lgd*(1-pd_annual)^(A32/4)) -> 1.4552273 | D32: =AVERAGE(CashFlows!$F$18:$F$1017) -> 1.45338 | E32: =PERCENTILE(CashFlows!$F$18:$F$1017,0.05) -> 1.32 | F32: =PERCENTILE(CashFlows!$F$18:$F$1017,0.95) -> 1.5 | G32: =AVERAGE(CashFlows!$AA$18:$AA$1017) -> 0.1 | H32: =AVERAGE(CashFlows!$AV$18:$AV$1017) -> 0.1 | I32: =AVERAGE(CashFlows!$BQ$18:$BQ$1017) -> 1.25338 | J32: =PERCENTILE(CashFlows!$BQ$18:$BQ$1017,0.05) -> 1.12 | K32: =PERCENTILE(CashFlows!$BQ$18:$BQ$1017,0.95) -> 1.3
A33: 6 | B33: =Inputs!$C$30 -> 1.5 | C33: =B33*((1-lgd)+lgd*(1-pd_annual)^(A33/4)) -> 1.4465437 | D33: =AVERAGE(CashFlows!$G$18:$G$1017) -> 1.44366 | E33: =PERCENTILE(CashFlows!$G$18:$G$1017,0.05) -> 1.23 | F33: =PERCENTILE(CashFlows!$G$18:$G$1017,0.95) -> 1.5 | G33: =AVERAGE(CashFlows!$AB$18:$AB$1017) -> 0.1 | H33: =AVERAGE(CashFlows!$AW$18:$AW$1017) -> 0.1 | I33: =AVERAGE(CashFlows!$BR$18:$BR$1017) -> 1.24366 | J33: =PERCENTILE(CashFlows!$BR$18:$BR$1017,0.05) -> 1.03 | K33: =PERCENTILE(CashFlows!$BR$18:$BR$1017,0.95) -> 1.3
A34: 7 | B34: =Inputs!$C$31 -> 1.5 | C34: =B34*((1-lgd)+lgd*(1-pd_annual)^(A34/4)) -> 1.4379482 | D34: =AVERAGE(CashFlows!$H$18:$H$1017) -> 1.43565 | E34: =PERCENTILE(CashFlows!$H$18:$H$1017,0.05) -> 1.23 | F34: =PERCENTILE(CashFlows!$H$18:$H$1017,0.95) -> 1.5 | G34: =AVERAGE(CashFlows!$AC$18:$AC$1017) -> 0.1 | H34: =AVERAGE(CashFlows!$AX$18:$AX$1017) -> 0.1 | I34: =AVERAGE(CashFlows!$BS$18:$BS$1017) -> 1.23565 | J34: =PERCENTILE(CashFlows!$BS$18:$BS$1017,0.05) -> 1.03 | K34: =PERCENTILE(CashFlows!$BS$18:$BS$1017,0.95) -> 1.3
A35: 8 | B35: =Inputs!$C$32 -> 1.5 | C35: =B35*((1-lgd)+lgd*(1-pd_annual)^(A35/4)) -> 1.42944 | D35: =AVERAGE(CashFlows!$I$18:$I$1017) -> 1.42953 | E35: =PERCENTILE(CashFlows!$I$18:$I$1017,0.05) -> 1.23 | F35: =PERCENTILE(CashFlows!$I$18:$I$1017,0.95) -> 1.5 | G35: =AVERAGE(CashFlows!$AD$18:$AD$1017) -> 0.1 | H35: =AVERAGE(CashFlows!$AY$18:$AY$1017) -> 0.1 | I35: =AVERAGE(CashFlows!$BT$18:$BT$1017) -> 1.22953 | J35: =PERCENTILE(CashFlows!$BT$18:$BT$1017,0.05) -> 1.03 | K35: =PERCENTILE(CashFlows!$BT$18:$BT$1017,0.95) -> 1.3
A36: 9 | B36: =Inputs!$C$33 -> 1.5 | C36: =B36*((1-lgd)+lgd*(1-pd_annual)^(A36/4)) -> 1.4210182 | D36: =AVERAGE(CashFlows!$J$18:$J$1017) -> 1.42035 | E36: =PERCENTILE(CashFlows!$J$18:$J$1017,0.05) -> 1.23 | F36: =PERCENTILE(CashFlows!$J$18:$J$1017,0.95) -> 1.5 | G36: =AVERAGE(CashFlows!$AE$18:$AE$1017) -> 0.1 | H36: =AVERAGE(CashFlows!$AZ$18:$AZ$1017) -> 0.1 | I36: =AVERAGE(CashFlows!$BU$18:$BU$1017) -> 1.22035 | J36: =PERCENTILE(CashFlows!$BU$18:$BU$1017,0.05) -> 1.03 | K36: =PERCENTILE(CashFlows!$BU$18:$BU$1017,0.95) -> 1.3
A37: 10 | B37: =Inputs!$C$34 -> 1.5 | C37: =B37*((1-lgd)+lgd*(1-pd_annual)^(A37/4)) -> 1.4126819 | D37: =AVERAGE(CashFlows!$K$18:$K$1017) -> 1.41279 | E37: =PERCENTILE(CashFlows!$K$18:$K$1017,0.05) -> 1.23 | F37: =PERCENTILE(CashFlows!$K$18:$K$1017,0.95) -> 1.5 | G37: =AVERAGE(CashFlows!$AF$18:$AF$1017) -> 0.1 | H37: =AVERAGE(CashFlows!$BA$18:$BA$1017) -> 0.1 | I37: =AVERAGE(CashFlows!$BV$18:$BV$1017) -> 1.21279 | J37: =PERCENTILE(CashFlows!$BV$18:$BV$1017,0.05) -> 1.03 | K37: =PERCENTILE(CashFlows!$BV$18:$BV$1017,0.95) -> 1.3
A38: 11 | B38: =Inputs!$C$35 -> 1.5 | C38: =B38*((1-lgd)+lgd*(1-pd_annual)^(A38/4)) -> 1.4044303 | D38: =AVERAGE(CashFlows!$L$18:$L$1017) -> 1.40523 | E38: =PERCENTILE(CashFlows!$L$18:$L$1017,0.05) -> 1.14 | F38: =PERCENTILE(CashFlows!$L$18:$L$1017,0.95) -> 1.5 | G38: =AVERAGE(CashFlows!$AG$18:$AG$1017) -> 0.1 | H38: =AVERAGE(CashFlows!$BB$18:$BB$1017) -> 0.1 | I38: =AVERAGE(CashFlows!$BW$18:$BW$1017) -> 1.20523 | J38: =PERCENTILE(CashFlows!$BW$18:$BW$1017,0.05) -> 0.94 | K38: =PERCENTILE(CashFlows!$BW$18:$BW$1017,0.95) -> 1.3
A39: 12 | B39: =Inputs!$C$36 -> 1.5 | C39: =B39*((1-lgd)+lgd*(1-pd_annual)^(A39/4)) -> 1.3962624 | D39: =AVERAGE(CashFlows!$M$18:$M$1017) -> 1.39785 | E39: =PERCENTILE(CashFlows!$M$18:$M$1017,0.05) -> 1.14 | F39: =PERCENTILE(CashFlows!$M$18:$M$1017,0.95) -> 1.5 | G39: =AVERAGE(CashFlows!$AH$18:$AH$1017) -> 0.1 | H39: =AVERAGE(CashFlows!$BC$18:$BC$1017) -> 0.1 | I39: =AVERAGE(CashFlows!$BX$18:$BX$1017) -> 1.19785 | J39: =PERCENTILE(CashFlows!$BX$18:$BX$1017,0.05) -> 0.94 | K39: =PERCENTILE(CashFlows!$BX$18:$BX$1017,0.95) -> 1.3
A40: 13 | B40: =Inputs!$C$37 -> 1.5 | C40: =B40*((1-lgd)+lgd*(1-pd_annual)^(A40/4)) -> 1.3881775 | D40: =AVERAGE(CashFlows!$N$18:$N$1017) -> 1.39029 | E40: =PERCENTILE(CashFlows!$N$18:$N$1017,0.05) -> 1.14 | F40: =PERCENTILE(CashFlows!$N$18:$N$1017,0.95) -> 1.5 | G40: =AVERAGE(CashFlows!$AI$18:$AI$1017) -> 0.1 | H40: =AVERAGE(CashFlows!$BD$18:$BD$1017) -> 0.1 | I40: =AVERAGE(CashFlows!$BY$18:$BY$1017) -> 1.19029 | J40: =PERCENTILE(CashFlows!$BY$18:$BY$1017,0.05) -> 0.94 | K40: =PERCENTILE(CashFlows!$BY$18:$BY$1017,0.95) -> 1.3
A41: 14 | B41: =Inputs!$C$38 -> 1.5 | C41: =B41*((1-lgd)+lgd*(1-pd_annual)^(A41/4)) -> 1.3801746 | D41: =AVERAGE(CashFlows!$O$18:$O$1017) -> 1.383 | E41: =PERCENTILE(CashFlows!$O$18:$O$1017,0.05) -> 1.14 | F41: =PERCENTILE(CashFlows!$O$18:$O$1017,0.95) -> 1.5 | G41: =AVERAGE(CashFlows!$AJ$18:$AJ$1017) -> 0.1 | H41: =AVERAGE(CashFlows!$BE$18:$BE$1017) -> 0.1 | I41: =AVERAGE(CashFlows!$BZ$18:$BZ$1017) -> 1.183 | J41: =PERCENTILE(CashFlows!$BZ$18:$BZ$1017,0.05) -> 0.94 | K41: =PERCENTILE(CashFlows!$BZ$18:$BZ$1017,0.95) -> 1.3
A42: 15 | B42: =Inputs!$C$39 -> 1.5 | C42: =B42*((1-lgd)+lgd*(1-pd_annual)^(A42/4)) -> 1.3722531 | D42: =AVERAGE(CashFlows!$P$18:$P$1017) -> 1.374 | E42: =PERCENTILE(CashFlows!$P$18:$P$1017,0.05) -> 1.14 | F42: =PERCENTILE(CashFlows!$P$18:$P$1017,0.95) -> 1.5 | G42: =AVERAGE(CashFlows!$AK$18:$AK$1017) -> 0.1 | H42: =AVERAGE(CashFlows!$BF$18:$BF$1017) -> 0.1 | I42: =AVERAGE(CashFlows!$CA$18:$CA$1017) -> 1.174 | J42: =PERCENTILE(CashFlows!$CA$18:$CA$1017,0.05) -> 0.94 | K42: =PERCENTILE(CashFlows!$CA$18:$CA$1017,0.95) -> 1.3
A43: 16 | B43: =Inputs!$C$40 -> 1.5 | C43: =B43*((1-lgd)+lgd*(1-pd_annual)^(A43/4)) -> 1.3644119 | D43: =AVERAGE(CashFlows!$Q$18:$Q$1017) -> 1.36563 | E43: =PERCENTILE(CashFlows!$Q$18:$Q$1017,0.05) -> 1.14 | F43: =PERCENTILE(CashFlows!$Q$18:$Q$1017,0.95) -> 1.5 | G43: =AVERAGE(CashFlows!$AL$18:$AL$1017) -> 0.1 | H43: =AVERAGE(CashFlows!$BG$18:$BG$1017) -> 0.1 | I43: =AVERAGE(CashFlows!$CB$18:$CB$1017) -> 1.16563 | J43: =PERCENTILE(CashFlows!$CB$18:$CB$1017,0.05) -> 0.94 | K43: =PERCENTILE(CashFlows!$CB$18:$CB$1017,0.95) -> 1.3
A44: 17 | B44: =Inputs!$C$41 -> 1.5 | C44: =B44*((1-lgd)+lgd*(1-pd_annual)^(A44/4)) -> 1.3566504 | D44: =AVERAGE(CashFlows!$R$18:$R$1017) -> 1.35852 | E44: =PERCENTILE(CashFlows!$R$18:$R$1017,0.05) -> 1.05 | F44: =PERCENTILE(CashFlows!$R$18:$R$1017,0.95) -> 1.5 | G44: =AVERAGE(CashFlows!$AM$18:$AM$1017) -> 0.1 | H44: =AVERAGE(CashFlows!$BH$18:$BH$1017) -> 0.1 | I44: =AVERAGE(CashFlows!$CC$18:$CC$1017) -> 1.15852 | J44: =PERCENTILE(CashFlows!$CC$18:$CC$1017,0.05) -> 0.85 | K44: =PERCENTILE(CashFlows!$CC$18:$CC$1017,0.95) -> 1.3
A45: 18 | B45: =Inputs!$C$42 -> 1.5 | C45: =B45*((1-lgd)+lgd*(1-pd_annual)^(A45/4)) -> 1.3489676 | D45: =AVERAGE(CashFlows!$S$18:$S$1017) -> 1.35159 | E45: =PERCENTILE(CashFlows!$S$18:$S$1017,0.05) -> 1.05 | F45: =PERCENTILE(CashFlows!$S$18:$S$1017,0.95) -> 1.5 | G45: =AVERAGE(CashFlows!$AN$18:$AN$1017) -> 0.1 | H45: =AVERAGE(CashFlows!$BI$18:$BI$1017) -> 0.1 | I45: =AVERAGE(CashFlows!$CD$18:$CD$1017) -> 1.15159 | J45: =PERCENTILE(CashFlows!$CD$18:$CD$1017,0.05) -> 0.85 | K45: =PERCENTILE(CashFlows!$CD$18:$CD$1017,0.95) -> 1.3
A46: 19 | B46: =Inputs!$C$43 -> 1.5 | C46: =B46*((1-lgd)+lgd*(1-pd_annual)^(A46/4)) -> 1.3413629 | D46: =AVERAGE(CashFlows!$T$18:$T$1017) -> 1.34394 | E46: =PERCENTILE(CashFlows!$T$18:$T$1017,0.05) -> 1.05 | F46: =PERCENTILE(CashFlows!$T$18:$T$1017,0.95) -> 1.5 | G46: =AVERAGE(CashFlows!$AO$18:$AO$1017) -> 0.1 | H46: =AVERAGE(CashFlows!$BJ$18:$BJ$1017) -> 0.1 | I46: =AVERAGE(CashFlows!$CE$18:$CE$1017) -> 1.14394 | J46: =PERCENTILE(CashFlows!$CE$18:$CE$1017,0.05) -> 0.85 | K46: =PERCENTILE(CashFlows!$CE$18:$CE$1017,0.95) -> 1.3
A47: 20 | B47: =Inputs!$C$44 -> 101.5 | C47: =B47*((1-lgd)+lgd*(1-pd_annual)^(A47/4)) -> 90.256197 | D47: =AVERAGE(CashFlows!$U$18:$U$1017) -> 90.41011 | E47: =PERCENTILE(CashFlows!$U$18:$U$1017,0.05) -> 71.05 | F47: =PERCENTILE(CashFlows!$U$18:$U$1017,0.95) -> 101.5 | G47: =AVERAGE(CashFlows!$AP$18:$AP$1017) -> 20.1 | H47: =AVERAGE(CashFlows!$BK$18:$BK$1017) -> 10.1 | I47: =AVERAGE(CashFlows!$CF$18:$CF$1017) -> 60.21011 | J47: =PERCENTILE(CashFlows!$CF$18:$CF$1017,0.05) -> 40.85 | K47: =PERCENTILE(CashFlows!$CF$18:$CF$1017,0.95) -> 71.3
A50: Distribution of total 5-year cash (bins are a share of the no-default amount)
A51: Above | B51: Up to | C51: Label | D51: Pool cases | E51: Equity cases
A52: 0.4 | B52: 0.425 | C52: ="up to "&TEXT(B52,"0.0%") -> up to 42.5% | D52: =COUNTIFS(CashFlows!$CH$18:$CH$1017,"<="&($B$5*$B52+0.000000001)) -> 0 | E52: =COUNTIFS(CashFlows!$CK$18:$CK$1017,"<="&($B$8*$B52+0.000000001)) -> 6
A53: 0.425 | B53: 0.45 | C53: =TEXT(B53,"0.0%") -> 45.0% | D53: =COUNTIFS(CashFlows!$CH$18:$CH$1017,">"&($B$5*$A53+0.000000001),CashFlows!$CH$18:$CH$1017,"<="&($B$5*$B53+0.000000001)) -> 0 | E53: =COUNTIFS(CashFlows!$CK$18:$CK$1017,">"&($B$8*$A53+0.000000001),CashFlows!$CK$18:$CK$1017,"<="&($B$8*$B53+0.000000001)) -> 1
A54: 0.45 | B54: 0.475 | C54: =TEXT(B54,"0.0%") -> 47.5% | D54: =COUNTIFS(CashFlows!$CH$18:$CH$1017,">"&($B$5*$A54+0.000000001),CashFlows!$CH$18:$CH$1017,"<="&($B$5*$B54+0.000000001)) -> 0 | E54: =COUNTIFS(CashFlows!$CK$18:$CK$1017,">"&($B$8*$A54+0.000000001),CashFlows!$CK$18:$CK$1017,"<="&($B$8*$B54+0.000000001)) -> 4
A55: 0.475 | B55: 0.5 | C55: =TEXT(B55,"0.0%") -> 50.0% | D55: =COUNTIFS(CashFlows!$CH$18:$CH$1017,">"&($B$5*$A55+0.000000001),CashFlows!$CH$18:$CH$1017,"<="&($B$5*$B55+0.000000001)) -> 1 | E55: =COUNTIFS(CashFlows!$CK$18:$CK$1017,">"&($B$8*$A55+0.000000001),CashFlows!$CK$18:$CK$1017,"<="&($B$8*$B55+0.000000001)) -> 5
A56: 0.5 | B56: 0.525 | C56: =TEXT(B56,"0.0%") -> 52.5% | D56: =COUNTIFS(CashFlows!$CH$18:$CH$1017,">"&($B$5*$A56+0.000000001),CashFlows!$CH$18:$CH$1017,"<="&($B$5*$B56+0.000000001)) -> 0 | E56: =COUNTIFS(CashFlows!$CK$18:$CK$1017,">"&($B$8*$A56+0.000000001),CashFlows!$CK$18:$CK$1017,"<="&($B$8*$B56+0.000000001)) -> 1
A57: 0.525 | B57: 0.55 | C57: =TEXT(B57,"0.0%") -> 55.0% | D57: =COUNTIFS(CashFlows!$CH$18:$CH$1017,">"&($B$5*$A57+0.000000001),CashFlows!$CH$18:$CH$1017,"<="&($B$5*$B57+0.000000001)) -> 2 | E57: =COUNTIFS(CashFlows!$CK$18:$CK$1017,">"&($B$8*$A57+0.000000001),CashFlows!$CK$18:$CK$1017,"<="&($B$8*$B57+0.000000001)) -> 7
A58: 0.55 | B58: 0.575 | C58: =TEXT(B58,"0.0%") -> 57.5% | D58: =COUNTIFS(CashFlows!$CH$18:$CH$1017,">"&($B$5*$A58+0.000000001),CashFlows!$CH$18:$CH$1017,"<="&($B$5*$B58+0.000000001)) -> 3 | E58: =COUNTIFS(CashFlows!$CK$18:$CK$1017,">"&($B$8*$A58+0.000000001),CashFlows!$CK$18:$CK$1017,"<="&($B$8*$B58+0.000000001)) -> 6
A59: 0.575 | B59: 0.6 | C59: =TEXT(B59,"0.0%") -> 60.0% | D59: =COUNTIFS(CashFlows!$CH$18:$CH$1017,">"&($B$5*$A59+0.000000001),CashFlows!$CH$18:$CH$1017,"<="&($B$5*$B59+0.000000001)) -> 2 | E59: =COUNTIFS(CashFlows!$CK$18:$CK$1017,">"&($B$8*$A59+0.000000001),CashFlows!$CK$18:$CK$1017,"<="&($B$8*$B59+0.000000001)) -> 3
A60: 0.6 | B60: 0.625 | C60: =TEXT(B60,"0.0%") -> 62.5% | D60: =COUNTIFS(CashFlows!$CH$18:$CH$1017,">"&($B$5*$A60+0.000000001),CashFlows!$CH$18:$CH$1017,"<="&($B$5*$B60+0.000000001)) -> 6 | E60: =COUNTIFS(CashFlows!$CK$18:$CK$1017,">"&($B$8*$A60+0.000000001),CashFlows!$CK$18:$CK$1017,"<="&($B$8*$B60+0.000000001)) -> 11
A61: 0.625 | B61: 0.65 | C61: =TEXT(B61,"0.0%") -> 65.0% | D61: =COUNTIFS(CashFlows!$CH$18:$CH$1017,">"&($B$5*$A61+0.000000001),CashFlows!$CH$18:$CH$1017,"<="&($B$5*$B61+0.000000001)) -> 3 | E61: =COUNTIFS(CashFlows!$CK$18:$CK$1017,">"&($B$8*$A61+0.000000001),CashFlows!$CK$18:$CK$1017,"<="&($B$8*$B61+0.000000001)) -> 33
A62: 0.65 | B62: 0.675 | C62: =TEXT(B62,"0.0%") -> 67.5% | D62: =COUNTIFS(CashFlows!$CH$18:$CH$1017,">"&($B$5*$A62+0.000000001),CashFlows!$CH$18:$CH$1017,"<="&($B$5*$B62+0.000000001)) -> 8 | E62: =COUNTIFS(CashFlows!$CK$18:$CK$1017,">"&($B$8*$A62+0.000000001),CashFlows!$CK$18:$CK$1017,"<="&($B$8*$B62+0.000000001)) -> 5
A63: 0.675 | B63: 0.7 | C63: =TEXT(B63,"0.0%") -> 70.0% | D63: =COUNTIFS(CashFlows!$CH$18:$CH$1017,">"&($B$5*$A63+0.000000001),CashFlows!$CH$18:$CH$1017,"<="&($B$5*$B63+0.000000001)) -> 7 | E63: =COUNTIFS(CashFlows!$CK$18:$CK$1017,">"&($B$8*$A63+0.000000001),CashFlows!$CK$18:$CK$1017,"<="&($B$8*$B63+0.000000001)) -> 21
A64: 0.7 | B64: 0.725 | C64: =TEXT(B64,"0.0%") -> 72.5% | D64: =COUNTIFS(CashFlows!$CH$18:$CH$1017,">"&($B$5*$A64+0.000000001),CashFlows!$CH$18:$CH$1017,"<="&($B$5*$B64+0.000000001)) -> 14 | E64: =COUNTIFS(CashFlows!$CK$18:$CK$1017,">"&($B$8*$A64+0.000000001),CashFlows!$CK$18:$CK$1017,"<="&($B$8*$B64+0.000000001)) -> 50
... A75: 0.975 | B75: 1 | C75: =TEXT(B75,"0.0%") -> 100.0% | D75: =COUNTIFS(CashFlows!$CH$18:$CH$1017,">"&($B$5*$A75+0.000000001),CashFlows!$CH$18:$CH$1017,"<="&($B$5*$B75+0.000000001)) -> 257 | E75: =COUNTIFS(CashFlows!$CK$18:$CK$1017,">"&($B$8*$A75+0.000000001),CashFlows!$CK$18:$CK$1017,"<="&($B$8*$B75+0.000000001)) -> 257

Sheet Sensitivity
A1: Sensitivities
A2: The tables are values from the Python run on the same random numbers. To reproduce any row, type its input on the Inputs sheet: the 'This workbook now' row recalculates and should match it.
B4: Value | C4: avg defaults | D4: P(no default) | E4: equity mean | F4: equity std | G4: equity 5th pct | H4: equity min | I4: P(A shortfall) | J4: P(B shortfall)
A5: This workbook now | C5: =AVERAGE(Defaults!$AT$18:$AT$1017) -> 1.821 | D5: =COUNTIF(Defaults!$AT$18:$AT$1017,0)/Number_of_Cases -> 0.257 | E5: =Statistics!C8 -> 83.28336 | F5: =Statistics!D8 -> 12.032269 | G5: =Statistics!G8 -> 60.6855 | H5: =Statistics!F8 -> 30.48 | I5: =SUM(CashFlows!$CL$18:$CL$1017)/Number_of_Cases -> 0 | J5: =SUM(CashFlows!$CM$18:$CM$1017)/Number_of_Cases -> 0
A7: Annual default probability
B8: Value | C8: avg defaults | D8: P(no default) | E8: equity mean | F8: equity std | G8: equity 5th pct | H8: equity min | I8: P(A shortfall) | J8: P(B shortfall)
B9: 0.01 | C9: 0.514 | D9: 0.652 | E9: 92.4444 | F9: 6.0053126 | G9: 81.48 | H9: 46.98 | I9: 0 | J9: 0
B10: 0.02 | C10: 0.96 | D10: 0.472 | E10: 89.30265 | F10: 8.559274 | G10: 73.5855 | H10: 44.01 | I10: 0 | J10: 0
B11: 0.04 | C11: 1.821 | D11: 0.257 | E11: 83.28336 | F11: 12.032269 | G11: 60.6855 | H11: 30.48 | I11: 0 | J11: 0
B12: 0.06 | C12: 2.644 | D12: 0.136 | E12: 77.51223 | F12: 14.249951 | G12: 50.9565 | H12: 28.86 | I12: 0 | J12: 0
B13: 0.08 | C13: 3.426 | D13: 0.076 | E13: 72.01869 | F13: 15.603984 | G13: 44.55 | H13: 21.87 | I13: 0 | J13: 0
B14: 0.12 | C14: 4.73 | D14: 0.019 | E14: 62.71428 | F14: 16.557273 | G14: 33.612 | H14: 20.34 | I14: 0 | J14: 0
A17: Loss given default
B18: Value | C18: avg defaults | D18: P(no default) | E18: equity mean | F18: equity std | G18: equity 5th pct | H18: equity min | I18: P(A shortfall) | J18: P(B shortfall)
B19: 0.4 | C19: 1.821 | D19: 0.257 | E19: 87.52224 | F19: 8.0215129 | G19: 72.457 | H19: 52.32 | I19: 0 | J19: 0
B20: 0.5 | C20: 1.821 | D20: 0.257 | E20: 85.4028 | F20: 10.026891 | G20: 66.57125 | H20: 41.4 | I20: 0 | J20: 0
B21: 0.6 | C21: 1.821 | D21: 0.257 | E21: 83.28336 | F21: 12.032269 | G21: 60.6855 | H21: 30.48 | I21: 0 | J21: 0
B22: 0.7 | C22: 1.821 | D22: 0.257 | E22: 81.16392 | F22: 14.037647 | G22: 54.79975 | H22: 19.56 | I22: 0 | J22: 0
B23: 0.8 | C23: 1.821 | D23: 0.257 | E23: 79.04626 | F23: 16.035303 | G23: 48.914 | H23: 10.42 | I23: 0 | J23: 0.001
B24: 0.9 | C24: 1.821 | D24: 0.257 | E24: 76.944855 | F24: 17.97086 | G24: 43.02825 | H24: 8.635 | I24: 0.001 | J24: 0.006
B25: 1 | C25: 1.821 | D25: 0.257 | E25: 74.8752 | F25: 19.801657 | G25: 37.1425 | H25: 6.9 | I25: 0.001 | J25: 0.006
A28: Correlation
B29: Value | C29: avg defaults | D29: P(no default) | E29: equity mean | F29: equity std | G29: equity 5th pct | H29: equity min | I29: P(A shortfall) | J29: P(B shortfall)
B30: 0 | C30: 1.833 | D30: 0.145 | E30: 83.2236 | F30: 8.7609782 | G30: 67.68 | H30: 45.54 | I30: 0 | J30: 0
B31: 0.1 | C31: 1.822 | D31: 0.207 | E31: 83.27826 | F31: 10.571088 | G31: 63.3765 | H31: 44.01 | I31: 0 | J31: 0
B32: 0.2 | C32: 1.821 | D32: 0.257 | E32: 83.28336 | F32: 12.032269 | G32: 60.6855 | H32: 30.48 | I32: 0 | J32: 0
B33: 0.4 | C33: 1.844 | D33: 0.357 | E33: 83.15625 | F33: 15.378749 | G33: 52.6155 | H33: 19.98 | I33: 0 | J33: 0
B34: 0.6 | C34: 1.817 | D34: 0.463 | E34: 83.32653 | F34: 17.99397 | G34: 40.98 | H34: 18.27 | I34: 0 | J34: 0
B35: 0.8 | C35: 1.782 | D35: 0.594 | E35: 83.55309 | F35: 21.291801 | G35: 28.866 | H35: 18 | I35: 0 | J35: 0
A38: Class B notional ($MM)
B39: Value | C39: avg defaults | D39: P(no default) | E39: equity mean | F39: equity std | G39: equity 5th pct | H39: equity min | I39: P(A shortfall) | J39: P(B shortfall)
B40: 10 | C40: 1.821 | D40: 0.257 | E40: 83.28336 | F40: 12.032269 | G40: 60.6855 | H40: 30.48 | I40: 0 | J40: 0
B41: 20 | C41: 1.821 | D41: 0.257 | E41: 71.28336 | F41: 12.032269 | G41: 48.6855 | H41: 18.48 | I41: 0 | J41: 0
B42: 30 | C42: 1.821 | D42: 0.257 | E42: 59.28707 | F42: 12.016533 | G42: 36.6855 | H42: 10.19 | I42: 0 | J42: 0.001
B43: 40 | C43: 1.821 | D43: 0.257 | E43: 47.3537 | F43: 11.790998 | G43: 24.6855 | H43: 8.2 | I43: 0 | J43: 0.017
B44: 50 | C44: 1.821 | D44: 0.257 | E44: 35.61564 | F44: 11.104691 | G44: 12.78 | H44: 6.3 | I44: 0 | J44: 0.033
B45: 60 | C45: 1.821 | D45: 0.257 | E45: 24.69592 | F45: 9.1636353 | G45: 10.07 | H45: 4.4 | I45: 0 | J45: 0.159
A48: LGD 100%: annual default probability
B49: Value | C49: avg defaults | D49: P(no default) | E49: equity mean | F49: equity std | G49: equity 5th pct | H49: equity min | I49: P(A shortfall) | J49: P(B shortfall)
B50: 0.04 | C50: 1.821 | D50: 0.257 | E50: 74.8752 | F50: 19.801657 | G50: 37.1425 | H50: 6.9 | I50: 0.001 | J50: 0.006
B51: 0.08 | C51: 3.426 | D51: 0.076 | E51: 56.6929 | F51: 24.541661 | G51: 11.7975 | H51: 3.15 | I51: 0.019 | J51: 0.045
B52: 0.12 | C52: 4.73 | D52: 0.019 | E52: 42.42455 | F52: 24.458519 | G52: 8.1975 | H52: 1.85 | I52: 0.056 | J52: 0.118
B53: 0.2 | C53: 6.734 | D53: 0.001 | E53: 23.7548 | F53: 19.311128 | G53: 4.65 | H53: 0.9 | I53: 0.247 | J53: 0.406
A56: LGD 100%: correlation
B57: Value | C57: avg defaults | D57: P(no default) | E57: equity mean | F57: equity std | G57: equity 5th pct | H57: equity min | I57: P(A shortfall) | J57: P(B shortfall)
B58: 0 | C58: 1.833 | D58: 0.145 | E58: 74.706 | F58: 14.60163 | G58: 48.8 | H58: 11.9 | I58: 0 | J58: 0
B59: 0.2 | C59: 1.821 | D59: 0.257 | E59: 74.8752 | F59: 19.801657 | G59: 37.1425 | H59: 6.9 | I59: 0.001 | J59: 0.006
B60: 0.4 | C60: 1.844 | D60: 0.357 | E60: 75.0794 | F60: 24.124901 | G60: 23.6925 | H60: 1.45 | I60: 0.016 | J60: 0.029
B61: 0.6 | C61: 1.817 | D61: 0.463 | E61: 75.8664 | F61: 27.19205 | G61: 12.0425 | H61: 0.1 | I61: 0.032 | J61: 0.051
B62: 0.8 | C62: 1.782 | D62: 0.594 | E62: 77.42235 | F62: 29.908008 | G62: 8.35 | H62: 0 | I62: 0.069 | J62: 0.089

Sheet Notes
A1: Methodology
A2: Miniproject 3 (Part 1): Simplified CDO Analysis. Raj Pawar (rsp9234) and Michael Brick (mb11311). Project page: https://pawarraj8888.github.io/valuation-assignments/cdo-analysis/
A4: Key assumptions
A5: Collateral | B5: 10 bonds, $10 MM face each, 5 years, 6% annual coupon paid quarterly. Each bond promises $0.15 MM per quarter and $10.15 MM in quarter 20, so the pool promises $1.5 MM per quarter, $101.5 MM at maturity and $130 MM in total.
A6: Default Model | B6: We use the BIS debt model from class. (1 - LGD) = 40% of every promised payment is non-defaultable and is always paid. The other 60% stops in the quarter of default. So a defaulted bond still pays 40% of its coupons and 40% of its principal, on the original dates.
A7: Default Timing | B7: Each bond has a 4% annual default probability. Its default time in years comes from the formula in class, t = ln(1 - u) / ln(1 - 0.04), and the bond defaults in quarter ceil(4t). Past quarter 20 it survives.
A8: Correlation | B8: We apply the 0.20 correlation to the normal random numbers behind the default times (Cholesky factor of a 10 x 10 matrix with 0.20 off the diagonal) and then take u = N(x).
A9: Random Numbers | B9: 1000 cases x 10 bonds of standard normals, generated once (seed 6103) and stored in fixed_random_numbers.csv. Cases are numbered 1 to 1000 and every run uses the same numbers. Before use they are de-meaned and moment matched as shown in class, so that across the 1000 cases each bond's numbers have mean 0 and variance 1 and are uncorrelated with the other bonds' numbers.
A10: Classes | B10: Class A: $20 MM, 2% coupon. Class B: $10 MM, 4% coupon. We treat both as bullet bonds with quarterly coupons and principal at year 5, since the collateral only returns principal at maturity. Class A is owed $0.10 MM per quarter and $20.10 MM at maturity, Class B $0.10 MM and $10.10 MM.
A11: Waterfall | B11: Each quarter Class A is paid first, then Class B, and the residual goes to the bank. No carry-forwards: a shortfall is not made up later and no cash is held back.
A12: Units | B12: $ millions. Totals are undiscounted sums over the 20 quarters. The 9% YTM and 1% risk-free rate are not used until Part 2.
A14: Implementation steps
A15: BIS Bond Function | B15: Given the period a bond defaults in, the function returns the promised cash flows before it and (1 - LGD) x promised from it onward. We checked it against the Lecture 5 slide (face 1000, 5.5%, LGD 60%, pi 3%, r 4%) and it gives 984.73, the same as the slide.
A16: Fixed Random Numbers | B16: Read the 1000 x 10 table of independent normals from the csv file (it is created from the seed if it is missing).
A17: Moment Matching | B17: Subtract each column's mean, compute the covariance matrix of the draws and its Cholesky factor, and multiply the de-meaned draws by the inverse of that factor. As drawn, the column means were up to 0.067 away from 0, the variances ran from 0.96 to 1.04 and two bonds' numbers were correlated by up to 0.09. After matching the means are 0, the variances are 1 and the correlations are 0.
A18: Correlated Defaults | B18: Multiply the matched numbers by the Cholesky factor of the correlation matrix, convert to uniforms, then to default times and default quarters. Because of the moment matching the correlated normals have a pairwise correlation of exactly 0.20 across the cases. For the default times it comes out at 0.175.
A19: Collateral Cash Flows | B19: Apply the BIS function to every case and bond (1000 x 10 x 20 array) and add up the bonds to get the pool.
A20: Check | B20: We compare the simulated mean pool cash flow in each quarter with the exact expected value, promised x [0.4 + 0.6 x 0.96^(k/4)]. The largest gap over the 20 quarters is 0.20%.
A21: Waterfall | B21: A = min(pool, due to A), B = min(pool - A, due to B), equity = pool - A - B, quarter by quarter. The three always add back to the pool.
A22: Case Viewer | B22: Setting CASE in the notebook, the case cell in the Excel workbook or the case box on the dashboard (1 to 1000) shows that case's random numbers, default quarters and quarterly cash flows.
A23: Statistics and Sensitivities | B23: Distributions of total and quarterly cash flows. Then we rerun the model on the same random numbers with the default probability, LGD, correlation and Class B size changed one at a time.
A24: Cross-checks | B24: We also built the model with live formulas in Excel and in JavaScript for the dashboard, and wrote a plain loop version for the tests. All three give the same cash flows as the Python model in all 1000 cases.
